Workbook

Sheet ASSUMPTIONS
A1: JD BRITT — FINANCIAL PLAN ASSUMPTIONS
A2: Ivory cell = editable input (change freely) White = formula (do not edit) Green text = cross-sheet reference (edit on source sheet) Underlined header = click to navigate
A3: Assumption | B3: PATH A Military → Retire → PhD | C3: PATH B Separate → CS / Tech Job | D3: PATH C Separate → PhD → Research | E3: Source / Notes | F3: ↳ Feeds PROJECTIONS | G3: ⟵ Source Sheet
A4: SERVICE & TIMELINE
A5: TAFMS Date (entered service) | B5: Feb 2014 | C5: Feb 2014 | D5: Feb 2014 | E5: Resume / service records
A6: Current Year (base year) | B6: 2026 | C6: 2026 | D6: 2026 | E6: Projection start year
A7: Current Age (at projection start) | B7: 36 | C7: 36 | D7: 36 | E7: Born ~1990; joined at 24 in Feb 2014
A8: Path A: Military Retirement Year | B8: 2034 | C8: N/A | D8: N/A | E8: Feb 2014 + 20 yrs service = Feb 2034
A9: Path B/C: Separation Year | B9: N/A | C9: 2027 | D9: 2027 | E9: Nov 2027 if CNODP not accepted
A10: Years of Active Service (at 2026) | B10: 12.1 | C10: 12.1 | D10: 12.1 | E10: 2026 − 2014
A11: CURRENT COMPENSATION SNAPSHOT (read-only — edit values on INCOME sheet)
A12: Base Pay (Monthly) | B12: =INCOME!B6 -> 5591.66 | C12: =INCOME!B6 -> 5591.66 | D12: =INCOME!B6 -> 5591.66 | E12: From INCOME sheet | F12: → Gross Income (all paths, active duty) | G12: View in INCOME sheet → Base Pay row
A13: BAH — Housing Allowance (Monthly) | B13: =INCOME!B7 -> 2741.66 | C13: =INCOME!B7 -> 2741.66 | D13: =INCOME!B7 -> 2741.66 | E13: Tax-free; from INCOME | F13: → Tax-Free Income (BAH, active duty) | G13: View in INCOME sheet → BAH row
A14: BAS — Food Allowance (Monthly) | B14: =INCOME!B8 -> 477 | C14: =INCOME!B8 -> 477 | D14: =INCOME!B8 -> 477 | E14: Tax-free; from INCOME | F14: → Tax-Free Income (BAS, active duty) | G14: View in INCOME sheet → BAS row
A15: Gross Monthly Income (Current) | B15: =INCOME!B97 -> 8810.32 | C15: =INCOME!B97 -> 8810.32 | D15: =INCOME!B97 -> 8810.32 | E15: INCOME!B97 — all income | F15: Info only — not projected directly | G15: View in INCOME sheet → Gross Total
A16: Net Monthly Income (Current) | B16: =INCOME!B99 -> 7720.37 | C16: =INCOME!B99 -> 7720.37 | D16: =INCOME!B99 -> 7720.37 | E16: INCOME!B99 — after deductions | F16: Info only — not projected directly | G16: View in INCOME sheet → Net Total
A17: MILITARY RETIREMENT & PENSION (Path A only)
A18: Retirement System | B18: High-3 | C18: N/A | D18: N/A | E18: Pre-2018 entry → High-3 (not BRS)
A19: High-3 Avg Base Pay (est. at retirement) | B19: 7266 | C19: 0 | D19: 0 | E19: Est. E-8 avg of highest 36-mo base pay at 20 yrs (2024 tables). Source: dfas.mil
A20: Pension Multiplier (2.5% × 20 yrs) | B20: 0.5 | C20: 0 | D20: 0 | E20: 2.5% × 20 = 50%
A21: Monthly Pension (before tax) | B21: =B19*B20 -> 3633 | C21: 0 | D21: 0 | E21: High-3 × multiplier | F21: → Path A Gross Income (pension, yr 9+)
A22: Annual Pension | B22: =B21*12 -> 43596 | C22: 0 | D22: 0 | E22: Monthly × 12
A23: Pension COLA (annual increase) | B23: 0.028 | C23: 0 | D23: 0 | E23: 2026 COLA: 2.8%. Long-term avg ~2.5%. Source: militarypay.defense.gov | F23: → Path A Gross Income (pension COLA rate)
A24: Pension Start Year | B24: 2034 | C24: N/A | D24: N/A | E24: Retire at 44 (entered at 24; 20 yrs service)
A25: HEALTHCARE COSTS
A26: TRICARE Retiree Annual Cost (Path A) | B26: 182 | C26: N/A | D26: N/A | E26: 2025 TRICARE Select Group A: $181.92/yr. Source: tricare.mil | F26: → Path A Healthcare (TRICARE, yr 9+)
A27: TRICARE Annual Increase Rate (Path A) | B27: 0.03 | C27: N/A | D27: N/A | E27: ~3%/yr Congressional adjustment | F27: → Path A Healthcare (TRICARE inflation)
A28: Civilian Health Insurance Annual | B28: N/A | C28: 3000 | D28: 0 | E28: Path B: employer-sponsored ~$3K OOP. Path C: PhD = university-covered ($0). Source: KFF 2025 | F28: → Path B Healthcare (yr 2+) → Path C Healthcare (yr 8+)
A29: Civilian Healthcare Inflation | B29: N/A | C29: 0.08 | D29: 0.08 | E29: ~8%/yr. Source: Covered California 2026 avg | F29: → Path B/C Healthcare (inflation rate)
A30: Gap Year Health Insurance (Path C) | B30: N/A | C30: N/A | D30: 3000 | E30: Path C gap year: marketplace plan ~$3K. Source: healthcare.gov estimates | F30: → Path C Healthcare (gap year only)
A31: VA DISABILITY & BENEFITS
A32: Assumed VA Disability Rating | B32: 0.3 | C32: 0.3 | D32: 0.3 | E32: 30% conservative est. — common for 12+ yrs. Actual unknown until filed. Source: va.gov
A33: VA Disability Monthly Payment (2026) | B33: =IF(ISBLANK(B88),552.47,IF(B88="Yes",B90,0)) -> 552.47 | C33: =IF(ISBLANK(C88),552.47,IF(C88="Yes",B90,0)) -> 552.47 | D33: =IF(ISBLANK(D88),552.47,IF(D88="Yes",B90,0)) -> 552.47 | E33: 30% single, no dep: $537.42 (2025) + 2.8% COLA = $552.47. Source: va.gov | F33: → Tax-Free Income: VA disability (all paths)
A34: VA Disability COLA (annual) | B34: 0.028 | C34: 0.028 | D34: 0.028 | E34: 2026 COLA: 2.8%. Source: va.gov | F34: → Tax-Free Income: VA COLA rate (all paths)
A35: VA Disability Start Year (est.) | B35: 2034 | C35: 2028 | D35: 2028 | E35: Path A: at retirement. Path B/C: at separation Nov 2027 → effective 2028
A36: POST-9/11 GI BILL
A37: GI Bill Eligibility (months) | B37: 36 | C37: 36 | D37: 36 | E37: Forever GI Bill — no expiration
A38: GI Bill BAH Monthly (Bay Area rate) | B38: =IF(B95="CUSTOM",4992,B97) -> 4992 | C38: 0 | D38: =IF(B95="CUSTOM",4992,B97) -> 4992 | E38: Bay Area (94305): $4,992/mo. Path B: not used for school. Source: va.gov BAH calculator | F38: → Tax-Free Income: GI Bill BAH Path A: yrs 9-13 | Path C: yrs 3-7
A39: GI Bill Book Stipend (annual) | B39: 1000 | C39: 0 | D39: 1000 | E39: $1,000/yr for books. Path B: N/A | F39: → Tax-Free Income: GI Bill books (same years as BAH)
A40: GI Bill Stacks with PhD Stipend? | B40: YES | C40: N/A | D40: YES | E40: Universities do NOT reduce stipend for GI Bill. Source: SCO confirmation
A41: GI Bill Usage Timing | B41: Post-retire PhD (2035-2039) | C41: Not modeled | D41: PhD 2028-2032 | E41: Path A uses after retirement; Path C uses immediately during PhD
A42: CAREER & SALARY PROJECTIONS
A43: Path A — PhD Start Year | B43: 2035 | C43: N/A | D43: N/A | E43: After retirement 2034
A44: Path C — PhD Start Year | B44: N/A | C44: N/A | D44: 2028 | E44: Fall 2028, after gap year (Nov 2027 sep)
A45: PhD Duration (years) | B45: 5 | C45: 0 | D45: 5 | E45: Standard CS/ML PhD: 4-6 yrs | F45: → Gross Income: PhD stipend Path A: yrs 9-13 | Path C: yrs 3-7
A46: PhD Annual Stipend | B46: =IF(B95="CUSTOM",47000,B96) -> 47000 | C46: 0 | D46: =IF(B95="CUSTOM",47000,B96) -> 47000 | E46: Avg of targets: Stanford $57K, MIT $51.2K, CMU $42.9K, Berkeley $44K, GT $40.8K → ~$47K/yr. Source: university sites | F46: → Path B Gross Income: CS job salary (yr 2+) | G46: View in INCOME sheet → CS job column
A47: CS/Tech Job Annual Salary (Path B) | B47: N/A | C47: =IF(C75="GENERIC_IC",INCOME!C6*12,C76) -> 175000 | D47: N/A | E47: From INCOME sheet — current CS job estimate ~$117K/yr. Ref: levels.fyi | F47: → Path B Gross Income: CS salary (override)
A48: Research Scientist Starting Salary | B48: =IF(B82="CONSERVATIVE",220000,B83) -> 230000 | C48: 0 | D48: =IF(B82="CONSERVATIVE",220000,B83) -> 230000 | E48: Conservative: Intel Labs ~$200K, DeepMind ~$264K avg, Anthropic ~$442K median. Using $220K. Source: levels.fyi | F48: → Research Scientist salary Path A: yr 14+ | Path C: yr 8+
A49: Path A — Research Scientist Start Year | B49: 2040 | C49: N/A | D49: N/A | E49: After 5-yr PhD ending 2039
A50: Path C — Research Scientist Start Year | B50: N/A | C50: N/A | D50: 2033 | E50: After 5-yr PhD ending 2032
A51: Salary Growth Rate (all civilian) | B51: 0.04 | C51: 0.04 | D51: 0.04 | E51: Tech median 3.3-3.7%; AI/ML roles 4-5%+. Using 4%. Source: Dice 2025 | F51: → Salary growth rate (all civilian phases)
A52: Military Annual Pay Raise | B52: 0.025 | C52: N/A | D52: N/A | E52: Historical avg ~2-3%/yr | F52: → Military pay raise (all paths, active duty)
A53: INVESTMENT & SAVINGS
A54: Current TSP Balance | B54: =ASSETS!B10 -> 75000 | C54: =ASSETS!B10 -> 75000 | D54: =ASSETS!B10 -> 75000 | E54: From ASSETS sheet. All Roth. | F54: → Portfolio starting balance (TSP component) | G54: View in ASSETS sheet → TSP row
A55: Current Roth IRA Balance | B55: =ASSETS!B19 -> 30000 | C55: =ASSETS!B19 -> 30000 | D55: =ASSETS!B19 -> 30000 | E55: From ASSETS sheet. Not yet invested. | F55: → Portfolio starting balance (Roth IRA) | G55: View in ASSETS sheet → Roth IRA row
A56: Current Brokerage Balance | B56: =ASSETS!B20 -> 58000 | C56: =ASSETS!B20 -> 58000 | D56: =ASSETS!B20 -> 58000 | E56: From ASSETS sheet. | F56: → Portfolio starting balance (Brokerage) | G56: View in ASSETS sheet → Brokerage row
A57: Current Cash (Checking + Savings) | B57: =ASSETS!B7+ASSETS!B8 -> 20000 | C57: =ASSETS!B7+ASSETS!B8 -> 20000 | D57: =ASSETS!B7+ASSETS!B8 -> 20000 | E57: From ASSETS sheet | F57: → Portfolio starting balance (Cash) | G57: View in ASSETS sheet → Cash rows
A58: Starting Portfolio (Total) | B58: =B54+B55+B56+B57 -> 183000 | C58: =C54+C55+C56+C57 -> 183000 | D58: =D54+D55+D56+D57 -> 183000 | E58: Sum of investable assets | F58: → Portfolio: starting total (sum of accounts)
A59: Investment Return Rate (nominal) | B59: 0.07 | C59: 0.07 | D59: 0.07 | E59: Historical S&P avg 10.4%; Vanguard 10yr forecast 3.5-5.5%. Using 7% moderate. Source: Vanguard | F59: → Portfolio: annual growth rate (all paths)
A60: Monthly Ret. Savings — Active Duty | B60: 1900 | C60: 1900 | D60: 1900 | E60: Current TSP + Roth IRA monthly contribution. Verify vs actual allotment. | F60: → Retirement savings: active duty rate
A61: Monthly Ret. Savings — Civilian / Career | B61: 500 | C61: 500 | D61: 500 | E61: Estimated 401(k) / IRA during civilian career | F61: → Retirement savings: civilian career rate
A62: Monthly Ret. Savings — PhD Years | B62: 0 | C62: 0 | D62: 0 | E62: Assumes $0 savings during PhD. Roth IRA possible if stipend > ~$14K. Revisit if admitted. | F62: → Retirement savings: PhD years ($0)
A63: TAX RATES (Federal Effective + State)
A64: Effective Federal Tax Rate — Military | B64: 0.12 | C64: 0.12 | D64: 0.12 | E64: ~12% effective on taxable portion (BAH/BAS exempt). Source: IRS 2026 brackets | F64: → Taxes: military federal rate (Path A)
A65: Effective Federal Tax Rate — Civilian (mid income) | B65: N/A | C65: 0.22 | D65: 0.22 | E65: 22% bracket for $80K-$170K (single). Source: IRS | F65: → Taxes: civilian mid-income rate (B/C early)
A66: Effective Federal Tax Rate — High Income | B66: 0.24 | C66: 0.24 | D66: 0.24 | E66: Effective ~24% marginal at $200K+. Source: IRS/Tax Foundation | F66: → Taxes: high-income rate (all research sci phases)
A67: State Tax Rate (California) | B67: 0.07 | C67: 0.07 | D67: 0.07 | E67: CA effective: 7-9% at $120K; 10-11% at $200K. Using 7% avg. Source: FTB | F67: → Taxes: CA state rate (all paths)
A68: GENERAL ASSUMPTIONS
A69: Inflation Rate (CPI, annual) | B69: 0.028 | C69: 0.028 | D69: 0.028 | E69: Feb 2026 CPI: 2.4%. 2025 avg: 2.6%. Long-term avg ~3%. Using 2.8%. Source: BLS
A70: Monthly Living Expenses (current) | B70: =EXPENSES!B126 -> 2393.82 | C70: =EXPENSES!B126 -> 2393.82 | D70: =EXPENSES!B126 -> 2393.82 | E70: From EXPENSES sheet grand total | F70: → Living Expenses: current monthly base | G70: View in EXPENSES sheet → Grand Total
A71: Living Expense Annual Growth Rate | B71: 0.03 | C71: 0.03 | D71: 0.03 | E71: Bay Area CPI ~2.5%; food 4.8%. Blended ~3%. Source: BLS SF CPI | F71: → Living Expenses: annual growth rate
A72: Life Expectancy (pension valuation) | B72: 82 | C72: 82 | D72: 82 | E72: US male avg ~76; military retirees tend higher. Source: CDC
A74: CS CAREER PATH CONFIGURATION — Affects PROJECTIONS gross income directly
A75: Path B: CS/Tech Company | C75: MSFT_SWE | E75: Select a company → salary auto-updates ASSUMPTIONS!C47 and all PROJECTIONS. Options: GENERIC_IC, MSFT_SWE, GOOG_SWE, NVDA_IC, INTEL_IC, STARTUP_TECH | F75: → Drives C47 (CS Salary) → PROJECTIONS Path B | G75: CAREER_DATA!B5:B10
A76: Path B: Computed Annual Base Salary | C76: =IFERROR(VLOOKUP(C75,CAREER_DATA!$A$5:$H$10,4,FALSE()),117637.8) -> 175000 | E76: Auto-lookup from CAREER_DATA. Override C47 directly to use a custom value. | F76: → C47 references this | G76: CAREER_DATA Table 1, col D
A77: Path B: Annual RSU/Stock Comp | C77: =IFERROR(VLOOKUP(C75,CAREER_DATA!$A$5:$H$10,6,FALSE()),20000) -> 90000 | E77: Annual vesting RSU. Not counted in taxable gross — enters as non-guaranteed comp. For reference only. | F77: Reference only — not in PROJECTIONS gross | G77: CAREER_DATA Table 1, col F
A78: Path B: Total Comp Year 1 (Cash + RSU) | C78: =IFERROR(VLOOKUP(C75,CAREER_DATA!$A$5:$H$10,8,FALSE()),137638) -> 291250 | E78: Total comp = base + bonus + RSU. Use for realistic planning context. PROJECTIONS models base salary only. | F78: Reference only | G78: CAREER_DATA Table 1, col H
A79: Path B: Company Growth Rate Override | C79: =IFERROR(VLOOKUP(C75,CAREER_DATA!$A$5:$H$10,7,FALSE()),0.04) -> 0.04 | E79: Company-specific salary growth. Used by PROJECTIONS!B51 if overridden here. Default 4% if not overridden. | F79: → Optional override for B51 (growth rate) | G79: CAREER_DATA Table 1, col G
A81: RESEARCH SCIENTIST EMPLOYER — Post-PhD employer affects Paths A & C income projections
A82: Post-PhD Employer / Research Path | B82: DEEPMIND | E82: Applies to Paths A & C after PhD. Options: CONSERVATIVE, INTEL_LABS, NEURALINK, MSFT_RESEARCH, DEEPMIND, NVDA_RESEARCH, ANTHROPIC | F82: → Drives B48/D48 (RS Salary) → PROJECTIONS | G82: CAREER_DATA!B14:B20
A83: RS Employer: Computed Starting Salary | B83: =IFERROR(VLOOKUP(B82,CAREER_DATA!$A$14:$H$20,4,FALSE()),220000) -> 230000 | E83: Auto-lookup research scientist base salary. Applies to both Path A (2040+) and Path C (2034+). | F83: → B48, D48 reference this | G83: CAREER_DATA Table 2, col D
A84: RS Employer: Annual RSU (reference) | B84: =IFERROR(VLOOKUP(B82,CAREER_DATA!$A$14:$H$20,6,FALSE()),30000) -> 120000 | E84: RSU reference only. Not in PROJECTIONS gross income (variable/non-guaranteed). | F84: Reference only | G84: CAREER_DATA Table 2, col F
A85: RS Employer: Total Comp Year 1 (Cash + RSU) | B85: =IFERROR(VLOOKUP(B82,CAREER_DATA!$A$14:$H$20,8,FALSE()),272000) -> 384500 | E85: Realistic total compensation at selected employer in year 1. For planning context. | F85: Reference only | G85: CAREER_DATA Table 2, col H
A87: VA DISABILITY CONFIGURATION — Rating drives monthly payment for all applicable paths
A88: VA Benefits Active | B88: Yes | C88: Yes | D88: Yes | E88: Yes/No per path. Default: Yes for all paths (30% current assumption). Set to No to zero out VA income for a path. | F88: → B33/C33/D33 conditional on this
A89: VA Disability Rating % | B89: 30% | E89: Select from: 0%, 10%, 20%, 30%, 40%, 50%, 60%, 70%, 80%, 90%, 100%. Drives B90 auto-lookup. | F89: → B90 (monthly auto-calc) → B33/C33/D33
A90: VA Monthly Payment (2026 auto-lookup) | B90: =IFERROR(VLOOKUP(B89,CAREER_DATA!$A$24:$B$34,2,FALSE()),552.47) -> 552.47 | E90: Auto-calculates from 2026 VA rates table (CAREER_DATA Table 3). Updates when rating changes. | F90: → Updates B33/C33/D33 VA monthly | G90: CAREER_DATA Table 3, col B
A91: VA COLA (annual) | B91: 0.028 | E91: VA COLA matches pension COLA — 2.8% (2026 rate). Usually same as pension COLA annually. | F91: → Mirrors B34/C34/D34
A92: Healthcare Eligibility at 100% Rating | B92: 100% = free VA healthcare; 50%+ = priority group 1 | E92: Note: 50%+ VA rating qualifies for Priority Group 1 (free VA healthcare). This reduces civilian healthcare costs for Paths B/C.
A94: GRAD SCHOOL CONFIGURATION — School selection drives stipend, BAH, and location costs
A95: Selected PhD Program (Paths A & C) | B95: CUSTOM | E95: Select a program to auto-populate stipend, GI Bill BAH, state tax, and estimated housing. Options in SCHOOL_DATA. Set to CUSTOM to keep existing values. | F95: → Drives B46/D46, B38/D38, state tax override | G95: SCHOOL_DATA!A5:A13
A96: PhD Annual Stipend (from program) | B96: =IFERROR(VLOOKUP(B95,SCHOOL_DATA!$A$5:$L$13,5,FALSE()),47000) -> 47000 | E96: Auto-lookup from SCHOOL_DATA. Updates ASSUMPTIONS!B46/D46 via the links below. | F96: → B46/D46 reference B96 when school set | G96: SCHOOL_DATA col E
A97: GI Bill BAH Monthly (from program location) | B97: =IFERROR(VLOOKUP(B95,SCHOOL_DATA!$A$5:$L$13,6,FALSE()),4992) -> 4992 | E97: Location-specific GI Bill BAH. Bay Area ($4,992) vs CMU Pittsburgh ($1,400) = $43K/yr difference. | F97: → B38/D38 reference B97 when school set | G97: SCHOOL_DATA col F
A98: School: State Income Tax Rate | B98: =IFERROR(VLOOKUP(B95,SCHOOL_DATA!$A$5:$L$13,10,FALSE()),0.07) -> 0.07 | E98: Location-based state tax during PhD years. WA=0%, MA=5%, CA=7%, PA=3.07%. Used in PROJECTIONS PhD phase. | F98: → Reference for PhD-phase state tax | G98: SCHOOL_DATA col J
A99: School: Estimated Monthly Rent | B99: =IFERROR(VLOOKUP(B95,SCHOOL_DATA!$A$5:$L$13,9,FALSE()),2500) -> 2500 | E99: Estimated monthly housing for selected school location. Update EXPENSES!B10 (rent) to match. | F99: → Reference for EXPENSES rent line | G99: SCHOOL_DATA col I
A100: University Health Coverage? | B100: =IFERROR(VLOOKUP(B95,SCHOOL_DATA!$A$5:$L$13,8,FALSE()),"Yes") -> Yes | E100: Most PhD programs cover health insurance. Yes = $0 healthcare cost during PhD years. | F100: → Informs PhD healthcare cost in PROJECTIONS
A102: SCENARIO PREVIEW — Auto-updates when selectors change above (no VBA needed)
A103: Metric | B103: PATH A | C103: PATH B | D103: PATH C | E103: Note
A104: CS Salary (Year 1) | B104: N/A | C104: =C76 -> 175000 | D104: N/A | E104: Path B: from company selector above
A105: RS Salary (Year 1) | B105: =B83 -> 230000 | C105: N/A | D105: =B83 -> 230000 | E105: Paths A & C: from PhD employer selector
...

Sheet CAREER_DATA
A1: CAREER DATA — Compensation Reference Tables
A3: TABLE 1 — PATH B: CS/TECH COMPANY OPTIONS (Immediate CS career — No PhD)
A4: Company ID | B4: Display Name / Label | C4: Role Type | D4: Base Salary | E4: Annual Bonus (% of base) | F4: Annual RSU | G4: Growth Rate | H4: Total Comp (Year 1) | I4: Notes / Source
A5: GENERIC_IC | B5: Generic Big Tech IC | C5: SWE/IC L3-equiv | D5: 117638 | E5: 0.1 | F5: 20000 | G5: 0.04 | H5: =D5+D5*E5+F5 -> 149401.8 | I5: Current default. Reflects typical non-PhD IC at mid-tier big tech. Source: levels.fyi 2026
A6: MSFT_SWE | B6: Microsoft SWE (L62-63) | C6: SWE / IC | D6: 175000 | E6: 0.15 | F6: 90000 | G6: 0.04 | H6: =D6+D6*E6+F6 -> 291250 | I6: Source: levels.fyi 2026 median; L62-63 range $291K median TC
A7: GOOG_SWE | B7: Google SWE (L4-L5) | C7: SWE / IC | D7: 190000 | E7: 0.15 | F7: 110000 | G7: 0.04 | H7: =D7+D7*E7+F7 -> 328500 | I7: Source: levels.fyi 2026; L4-L5 range $329K median TC
A8: NVDA_IC | B8: NVIDIA (IC4-IC5) | C8: SWE / Systems | D8: 195000 | E8: 0.15 | F8: 150000 | G8: 0.05 | H8: =D8+D8*E8+F8 -> 374250 | I8: Source: levels.fyi 2026; IC4-5 range, median TC ~$374K. Strong AI/hardware pipeline
A9: INTEL_IC | B9: Intel (Grade 7-8) | C9: Systems / HW | D9: 155000 | E9: 0.1 | F9: 40000 | G9: 0.03 | H9: =D9+D9*E9+F9 -> 210500 | I9: Source: levels.fyi 2026; Grade 7-8 range, median TC ~$211K. Intel Labs entry point
A10: STARTUP_TECH | B10: Tech Startup (funded) | C10: SWE / ML Eng | D10: 140000 | E10: 0.05 | F10: 40000 | G10: 0.05 | H10: =D10+D10*E10+F10 -> 187000 | I10: Estimate: seed-to-series B startup. Equity varies widely. ±$30K on base
A12: TABLE 2 — POST-PhD RESEARCH SCIENTIST EMPLOYER OPTIONS (Paths A & C after PhD)
A13: Company ID | B13: Display Name / Label | C13: Role Type | D13: Base Salary | E13: Annual Bonus (% of base) | F13: Annual RSU | G13: Growth Rate | H13: Total Comp (Year 1) | I13: Notes / Source
A14: CONSERVATIVE | B14: Conservative / Default | C14: Research Scientist | D14: 220000 | E14: 0.1 | F14: 30000 | G14: 0.04 | H14: =D14+D14*E14+F14 -> 272000 | I14: Default model assumption. Realistic floor for PhD-holders at established labs. Source: Internal estimate
A15: INTEL_LABS | B15: Intel Labs | C15: Research Scientist | D15: 190000 | E15: 0.1 | F15: 50000 | G15: 0.03 | H15: =D15+D15*E15+F15 -> 259000 | I15: Source: levels.fyi 2026; median TC ~$274K. Neuromorphic/Loihi lab aligned with BCI goals. Intel Folsom team relevant
A16: NEURALINK | B16: Neuralink | C16: Research Eng./Sci. | D16: 185000 | E16: 0.1 | F16: 60000 | G16: 0.04 | H16: =D16+D16*E16+F16 -> 263500 | I16: Source: levels.fyi 2026; total comp ~$261K. BCI-direct alignment. Equity component variable. Elon Musk risk factor
A17: MSFT_RESEARCH | B17: Microsoft Research | C17: Research Scientist | D17: 200000 | E17: 0.15 | F17: 80000 | G17: 0.04 | H17: =D17+D17*E17+F17 -> 310000 | I17: Source: levels.fyi 2026; median TC ~$310K. Strong AI/ML research. MSR has BCI-adjacent work (Project Rio, etc.)
A18: DEEPMIND | B18: Google DeepMind | C18: Research Scientist | D18: 230000 | E18: 0.15 | F18: 120000 | G18: 0.04 | H18: =D18+D18*E18+F18 -> 384500 | I18: Source: levels.fyi 2026; median TC ~$373K. Premier AI research lab. PhD pipeline to DeepMind strong for BCI/neuro
A19: NVDA_RESEARCH | B19: NVIDIA Research | C19: Research Scientist | D19: 250000 | E19: 0.15 | F19: 150000 | G19: 0.05 | H19: =D19+D19*E19+F19 -> 437500 | I19: Source: levels.fyi 2026; median TC ~$438K. AI/ML research growing rapidly. Neuromorphics + robotics alignment
A20: ANTHROPIC | B20: Anthropic | C20: Research Scientist | D20: 400000 | E20: 0 | F20: 100000 | G20: 0.05 | H20: =D20+D20*E20+F20 -> 500000 | I20: Source: levels.fyi 2026; median TC ~$746K (high equity). $400K base is conservative planning estimate. Alignment research
A22: TABLE 3 — VA DISABILITY RATES (2026, Veteran Alone, No Dependents — 2.8% COLA)
A23: Rating % | B23: Monthly 2026 | C23: Annual 2026 | D23: Notes
A24: 0% | B24: 0 | C24: =B24*12 -> 0 | D24: 0% rating — no compensation
A25: 10% | B25: 180.42 | C25: =B25*12 -> 2165.04 | D25: 2026 rate. No increase for dependents at 10-20%
A26: 20% | B26: 356 | C26: =B26*12 -> 4272 | D26: 2026 rate (estimated 2.8% COLA from 2025). Source: va.gov
A27: 30% | B27: 552.47 | C27: =B27*12 -> 6629.64 | D27: 2026 confirmed rate. Source: va.gov / ASSUMPTIONS row 33
A28: 40% | B28: 795.84 | C28: =B28*12 -> 9550.08 | D28: 2026 rate. Source: va.gov/disability/compensation-rates
A29: 50% | B29: 1132.9 | C29: =B29*12 -> 13594.8 | D29: 2026 rate. Source: va.gov
A30: 60% | B30: 1435.01 | C30: =B30*12 -> 17220.12 | D30: 2026 rate. Source: va.gov
A31: 70% | B31: 1808.44 | C31: =B31*12 -> 21701.28 | D31: 2026 rate. Source: va.gov
A32: 80% | B32: 2102.14 | C32: =B32*12 -> 25225.68 | D32: 2026 rate. Source: va.gov
A33: 90% | B33: 2362.3 | C33: =B33*12 -> 28347.6 | D33: 2026 rate. Source: va.gov
A34: 100% | B34: 3938.57 | C34: =B34*12 -> 47262.84 | D34: 2026 rate (P&T / Total). Source: va.gov. Additional SMC may apply
A36: SELECTOR RANGES — These named areas are referenced by ASSUMPTIONS dropdowns
A37: B Company IDs (B5:B10): | B37: GENERIC_IC,MSFT_SWE,GOOG_SWE,NVDA_IC,INTEL_IC,STARTUP_TECH
A38: PhD Employer IDs (B14:B20): | B38: CONSERVATIVE,INTEL_LABS,NEURALINK,MSFT_RESEARCH,DEEPMIND,NVDA_RESEARCH,ANTHROPIC
A39: VA Rating % (A24:A34): | B39: 0%,10%,20%,30%,40%,50%,60%,70%,80%,90%,100%

Sheet SCHOOL_DATA
A1: SCHOOL DATA — PhD Program Financial Reference (Paths A & C)
A3: TABLE 1 — GRAD SCHOOL FINANCIAL DATA (Stipend, GI Bill BAH, State Tax, Housing)
A4: Program ID | B4: School | C4: Location | D4: State | E4: Stipend/Yr | F4: GI Bill BAH /Month | G4: GI Bill Eligible? | H4: Univ Health Covered? | I4: Est. Rent /Month | J4: State Tax Rate | K4: App Fee | L4: Notes / Source
A5: STAN-CS-PHD | B5: Stanford | C5: Stanford, CA | D5: CA | E5: 57000 | F5: 4992 | G5: Yes | H5: Yes | I5: 2800 | J5: 0.07 | K5: 125 | L5: Stipend ~$57K/yr (2025-26). BAH: zip 94305, $4,992/mo confirmed va.gov. Yellow Ribbon covers tuition. Source: cs.stanford.edu, va.gov
A6: UCB-EECS-PHD | B6: UC Berkeley | C6: Berkeley, CA | D6: CA | E6: 44000 | F6: 4992 | G6: Yes | H6: Yes | I6: 2600 | J6: 0.07 | K6: 135 | L6: Stipend ~$44K/yr. BAH: Berkeley same zone as Stanford ($4,992). In-state tuition waived for PhD. Source: eecs.berkeley.edu, va.gov
A7: MIT-EECS-PHD | B7: MIT | C7: Cambridge, MA | D7: MA | E7: 56340 | F7: 3513 | G7: Yes | H7: Yes | I7: 2400 | J7: 0.05 | K7: 90 | L7: Stipend $4,695/mo ($56.3K/yr). BAH: Cambridge MA zip 02139 = $3,513/mo confirmed. MA flat tax 5%. Source: eecs.mit.edu, va.gov
A8: CMU-SCS-PHD | B8: CMU | C8: Pittsburgh, PA | D8: PA | E8: 42900 | F8: 1400 | G8: Yes | H8: Yes | I8: 1200 | J8: 0.031 | K8: 100 | L8: Stipend ~$42.9K/yr. BAH: Pittsburgh zip 15213 = $1,400/mo confirmed (significant disadvantage vs Bay Area). PA flat tax 3.07%. Source: csd.cs.cmu.edu, va.gov
A9: UW-CSE-PHD | B9: UW | C9: Seattle, WA | D9: WA | E9: 38000 | F9: 3200 | G9: Yes | H9: Yes | I9: 2000 | J9: 0 | K9: 90 | L9: Stipend RA/TA ~$38K/yr. BAH: Seattle WA ~$3,200/mo estimated (2026). WA has NO state income tax. Source: cs.washington.edu, va.gov est.
A10: UCD-CS-PHD | B10: UC Davis | C10: Davis, CA | D10: CA | E10: 39800 | F10: 1980 | G10: Yes | H10: Yes | I10: 1400 | J10: 0.07 | K10: 135 | L10: Stipend GSR/TA ~$39.8K/yr. BAH: Davis CA zip 95616 ~$1,980/mo est. Accessible from Sacramento. Source: cs.ucdavis.edu, va.gov est.
A11: IST-IGPC-MD | B11: Science Tokyo | C11: Tokyo, Japan | D11: N/A | E11: 13200 | F11: 0 | G11: No | H11: Yes | I11: 800 | J11: 0 | K11: 200 | L11: MEXT scholarship: JPY 148,000/mo (~$1,100 USD). Not eligible for US GI Bill. State tax N/A. Source: isct.ac.jp, mext.go.jp
A12: CAM-CS-PHD | B12: Cambridge | C12: Cambridge, UK | D12: N/A | E12: 25200 | F12: 0 | G12: No | H12: Yes | I12: 1600 | J12: 0 | K12: 25 | L12: Maintenance ~GBP 19,237/yr (~$25.2K USD). Not eligible for US GI Bill. Gates Cambridge funding option. Source: cst.cam.ac.uk
A13: CUSTOM | B13: Custom / Other | C13: — | D13: — | E13: 47000 | F13: 4992 | G13: Yes | H13: Yes | I13: 2500 | J13: 0.07 | K13: 0 | L13: Default custom option. Uses current ASSUMPTIONS values. Override stipend/BAH manually in ASSUMPTIONS rows 46 and 38.
A15: School IDs for dropdown (A5:A13): | B15: STAN-CS-PHD,UCB-EECS-PHD,MIT-EECS-PHD,CMU-SCS-PHD,UW-CSE-PHD,UCD-CS-PHD,IST-IGPC-MD,CAM-CS-PHD,CUSTOM

Sheet PROJECTIONS
A1: JD BRITT — 50-YEAR FINANCIAL PROJECTION | Three Paths: Military Retirement vs. CS/Tech vs. Grad School → Research
A2: All projections driven by ASSUMPTIONS sheet. Pension, VA disability, and GI Bill are tax-free income. Portfolio = prior × 7% + retirement savings + 20% of positive net cash flow.
D3: PATH A — Military → Retire 2034 → PhD → Research Scientist | M3: PATH B — Separate Nov 2027 → CS / Tech Job (immediate) | V3: PATH C — Separate Nov 2027 → Gap Year → PhD → Research Scientist | AE3: COMPARISON (A advantage over B and C)
A4: Yr # | B4: Year | C4: Age | D4: =HYPERLINK("#ASSUMPTIONS!A4","Status") -> Status | E4: =HYPERLINK("#ASSUMPTIONS!B42","Gross Income") -> Gross Income | F4: =HYPERLINK("#ASSUMPTIONS!B31","Tax-Free Income") -> Tax-Free Income | G4: =HYPERLINK("#ASSUMPTIONS!B63","Taxes") -> Taxes | H4: =HYPERLINK("#ASSUMPTIONS!B25","Healthcare") -> Healthcare | I4: =HYPERLINK("#ASSUMPTIONS!B68","Living Expenses") -> Living Expenses | J4: =HYPERLINK("#ASSUMPTIONS!B53","Ret. Savings") -> Ret. Savings | K4: =HYPERLINK("#ASSUMPTIONS!A4","Net Cash Flow") -> Net Cash Flow | L4: =HYPERLINK("#ASSUMPTIONS!B53","Portfolio") -> Portfolio | M4: =HYPERLINK("#ASSUMPTIONS!A4","Status") -> Status | N4: =HYPERLINK("#ASSUMPTIONS!B42","Gross Income") -> Gross Income | O4: =HYPERLINK("#ASSUMPTIONS!B31","Tax-Free Income") -> Tax-Free Income | P4: =HYPERLINK("#ASSUMPTIONS!B63","Taxes") -> Taxes | Q4: =HYPERLINK("#ASSUMPTIONS!B25","Healthcare") -> Healthcare | R4: =HYPERLINK("#ASSUMPTIONS!B68","Living Expenses") -> Living Expenses | S4: =HYPERLINK("#ASSUMPTIONS!B53","Ret. Savings") -> Ret. Savings | T4: =HYPERLINK("#ASSUMPTIONS!A4","Net Cash Flow") -> Net Cash Flow | U4: =HYPERLINK("#ASSUMPTIONS!B53","Portfolio") -> Portfolio | V4: =HYPERLINK("#ASSUMPTIONS!A4","Status") -> Status | W4: =HYPERLINK("#ASSUMPTIONS!B42","Gross Income") -> Gross Income | X4: =HYPERLINK("#ASSUMPTIONS!B31","Tax-Free Income") -> Tax-Free Income | Y4: =HYPERLINK("#ASSUMPTIONS!B63","Taxes") -> Taxes | Z4: =HYPERLINK("#ASSUMPTIONS!B25","Healthcare") -> Healthcare | AA4: =HYPERLINK("#ASSUMPTIONS!B68","Living Expenses") -> Living Expenses | AB4: =HYPERLINK("#ASSUMPTIONS!B53","Ret. Savings") -> Ret. Savings | AC4: =HYPERLINK("#ASSUMPTIONS!A4","Net Cash Flow") -> Net Cash Flow | AD4: =HYPERLINK("#ASSUMPTIONS!B53","Portfolio") -> Portfolio | AE4: A vs B Income | AF4: A vs C Income | AG4: A vs B Portfolio | AH4: A vs C Portfolio
A5: 0 | B5: 2026 | C5: 36 | D5: Active Duty | E5: =ASSUMPTIONS!$B$12*12*(1+ASSUMPTIONS!$B$52)^0 -> 67099.92 | F5: =(ASSUMPTIONS!$B$13+ASSUMPTIONS!$B$14)*12*(1+ASSUMPTIONS!$B$52)^0 -> 38623.92 | G5: =MAX((E5-F5)*(ASSUMPTIONS!$B$64+ASSUMPTIONS!$B$67),0) -> 5410.44 | H5: 0 | I5: =ASSUMPTIONS!$B$70*12*(1+ASSUMPTIONS!$B$71)^0 -> 28725.84 | J5: =ASSUMPTIONS!$B$60*12 -> 22800 | K5: =E5+F5-G5-H5-I5-J5 -> 48787.56 | L5: =ASSUMPTIONS!$B$58*(1+ASSUMPTIONS!$B$59)+J5+MAX(K5,0)*0.2 -> 228367.51 | M5: Active Duty | N5: =ASSUMPTIONS!$B$12*12*(1+ASSUMPTIONS!$B$52)^0 -> 67099.92 | O5: =(ASSUMPTIONS!$B$13+ASSUMPTIONS!$B$14)*12*(1+ASSUMPTIONS!$B$52)^0 -> 38623.92 | P5: =MAX((N5-O5)*(ASSUMPTIONS!$C$64+ASSUMPTIONS!$C$67),0) -> 5410.44 | Q5: 0 | R5: =ASSUMPTIONS!$B$70*12*(1+ASSUMPTIONS!$B$71)^0 -> 28725.84 | S5: =ASSUMPTIONS!$C$60*12 -> 22800 | T5: =N5+O5-P5-Q5-R5-S5 -> 48787.56 | U5: =ASSUMPTIONS!$C$58*(1+ASSUMPTIONS!$C$59)+S5+MAX(T5,0)*0.2 -> 228367.51 | V5: Active Duty | W5: =ASSUMPTIONS!$B$12*12*(1+ASSUMPTIONS!$B$52)^0 -> 67099.92 | X5: =(ASSUMPTIONS!$B$13+ASSUMPTIONS!$B$14)*12*(1+ASSUMPTIONS!$B$52)^0 -> 38623.92 | Y5: =MAX((W5-X5)*(ASSUMPTIONS!$D$64+ASSUMPTIONS!$D$67),0) -> 5410.44 | Z5: 0 | AA5: =ASSUMPTIONS!$B$70*12*(1+ASSUMPTIONS!$B$71)^0 -> 28725.84 | AB5: =ASSUMPTIONS!$D$60*12 -> 22800 | AC5: =W5+X5-Y5-Z5-AA5-AB5 -> 48787.56 | AD5: =ASSUMPTIONS!$D$58*(1+ASSUMPTIONS!$D$59)+AB5+MAX(AC5,0)*0.2 -> 228367.51 | AE5: =(E5+F5)-(N5+O5) -> 0 | AF5: =(E5+F5)-(W5+X5) -> 0 | AG5: =L5-U5 -> 0 | AH5: =L5-AD5 -> 0
A6: 1 | B6: 2027 | C6: 37 | D6: Active Duty | E6: =ASSUMPTIONS!$B$12*12*(1+ASSUMPTIONS!$B$52)^1 -> 68777.418 | F6: =(ASSUMPTIONS!$B$13+ASSUMPTIONS!$B$14)*12*(1+ASSUMPTIONS!$B$52)^1 -> 39589.518 | G6: =MAX((E6-F6)*(ASSUMPTIONS!$B$64+ASSUMPTIONS!$B$67),0) -> 5545.701 | H6: 0 | I6: =ASSUMPTIONS!$B$70*12*(1+ASSUMPTIONS!$B$71)^1 -> 29587.615 | J6: =ASSUMPTIONS!$B$60*12 -> 22800 | K6: =E6+F6-G6-H6-I6-J6 -> 50433.62 | L6: =L5*(1+ASSUMPTIONS!$B$59)+J6+MAX(K6,0)*0.2 -> 277239.96 | M6: Active Duty | N6: =ASSUMPTIONS!$B$12*12*(1+ASSUMPTIONS!$B$52)^1 -> 68777.418 | O6: =(ASSUMPTIONS!$B$13+ASSUMPTIONS!$B$14)*12*(1+ASSUMPTIONS!$B$52)^1 -> 39589.518 | P6: =MAX((N6-O6)*(ASSUMPTIONS!$C$64+ASSUMPTIONS!$C$67),0) -> 5545.701 | Q6: 0 | R6: =ASSUMPTIONS!$B$70*12*(1+ASSUMPTIONS!$B$71)^1 -> 29587.615 | S6: =ASSUMPTIONS!$C$60*12 -> 22800 | T6: =N6+O6-P6-Q6-R6-S6 -> 50433.62 | U6: =U5*(1+ASSUMPTIONS!$C$59)+S6+MAX(T6,0)*0.2 -> 277239.96 | V6: Active Duty | W6: =ASSUMPTIONS!$B$12*12*(1+ASSUMPTIONS!$B$52)^1 -> 68777.418 | X6: =(ASSUMPTIONS!$B$13+ASSUMPTIONS!$B$14)*12*(1+ASSUMPTIONS!$B$52)^1 -> 39589.518 | Y6: =MAX((W6-X6)*(ASSUMPTIONS!$D$64+ASSUMPTIONS!$D$67),0) -> 5545.701 | Z6: 0 | AA6: =ASSUMPTIONS!$B$70*12*(1+ASSUMPTIONS!$B$71)^1 -> 29587.615 | AB6: =ASSUMPTIONS!$D$60*12 -> 22800 | AC6: =W6+X6-Y6-Z6-AA6-AB6 -> 50433.62 | AD6: =AD5*(1+ASSUMPTIONS!$D$59)+AB6+MAX(AC6,0)*0.2 -> 277239.96 | AE6: =(E6+F6)-(N6+O6) -> 0 | AF6: =(E6+F6)-(W6+X6) -> 0 | AG6: =L6-U6 -> 0 | AH6: =L6-AD6 -> 0
A7: 2 | B7: 2028 | C7: 38 | D7: Active Duty | E7: =ASSUMPTIONS!$B$12*12*(1+ASSUMPTIONS!$B$52)^2 -> 70496.853 | F7: =(ASSUMPTIONS!$B$13+ASSUMPTIONS!$B$14)*12*(1+ASSUMPTIONS!$B$52)^2 -> 40579.256 | G7: =MAX((E7-F7)*(ASSUMPTIONS!$B$64+ASSUMPTIONS!$B$67),0) -> 5684.3435 | H7: 0 | I7: =ASSUMPTIONS!$B$70*12*(1+ASSUMPTIONS!$B$71)^2 -> 30475.244 | J7: =ASSUMPTIONS!$B$60*12 -> 22800 | K7: =E7+F7-G7-H7-I7-J7 -> 52116.522 | L7: =L6*(1+ASSUMPTIONS!$B$59)+J7+MAX(K7,0)*0.2 -> 329870.06 | M7: CS / Tech Job | N7: =ASSUMPTIONS!$C$47*(1+ASSUMPTIONS!$B$51)^0 -> 175000 | O7: =ASSUMPTIONS!$C$33*(1+ASSUMPTIONS!$C$34)^0*12 -> 6629.64 | P7: =MAX((N7-O7)*(ASSUMPTIONS!$C$65+ASSUMPTIONS!$C$67),0) -> 48827.404 | Q7: =ASSUMPTIONS!$C$28*(1+ASSUMPTIONS!$C$29)^0 -> 3000 | R7: =ASSUMPTIONS!$B$70*12*(1+ASSUMPTIONS!$B$71)^2 -> 30475.244 | S7: =ASSUMPTIONS!$C$61*12 -> 6000 | T7: =N7+O7-P7-Q7-R7-S7 -> 93326.992 | U7: =U6*(1+ASSUMPTIONS!$C$59)+S7+MAX(T7,0)*0.2 -> 321312.16 | V7: Gap Year | W7: 0 | X7: =ASSUMPTIONS!$D$33*12 -> 6629.64 | Y7: 0 | Z7: =ASSUMPTIONS!$D$30 -> 3000 | AA7: =ASSUMPTIONS!$B$70*12*(1+ASSUMPTIONS!$B$71)^2 -> 30475.244 | AB7: =ASSUMPTIONS!$D$62*12 -> 0 | AC7: =W7+X7-Y7-Z7-AA7-AB7 -> -26845.604 | AD7: =AD6*(1+ASSUMPTIONS!$D$59)+AB7+MAX(AC7,0)*0.2 -> 296646.76 | AE7: =(E7+F7)-(N7+O7) -> -70553.531 | AF7: =(E7+F7)-(W7+X7) -> 104446.47 | AG7: =L7-U7 -> 8557.9061 | AH7: =L7-AD7 -> 33223.304
A8: 3 | B8: 2029 | C8: 39 | D8: Active Duty | E8: =ASSUMPTIONS!$B$12*12*(1+ASSUMPTIONS!$B$52)^3 -> 72259.275 | F8: =(ASSUMPTIONS!$B$13+ASSUMPTIONS!$B$14)*12*(1+ASSUMPTIONS!$B$52)^3 -> 41593.737 | G8: =MAX((E8-F8)*(ASSUMPTIONS!$B$64+ASSUMPTIONS!$B$67),0) -> 5826.4521 | H8: 0 | I8: =ASSUMPTIONS!$B$70*12*(1+ASSUMPTIONS!$B$71)^3 -> 31389.501 | J8: =ASSUMPTIONS!$B$60*12 -> 22800 | K8: =E8+F8-G8-H8-I8-J8 -> 53837.059 | L8: =L7*(1+ASSUMPTIONS!$B$59)+J8+MAX(K8,0)*0.2 -> 386528.38 | M8: CS / Tech Job | N8: =ASSUMPTIONS!$C$47*(1+ASSUMPTIONS!$B$51)^1 -> 182000 | O8: =ASSUMPTIONS!$C$33*(1+ASSUMPTIONS!$C$34)^1*12 -> 6815.2699 | P8: =MAX((N8-O8)*(ASSUMPTIONS!$C$65+ASSUMPTIONS!$C$67),0) -> 50803.572 | Q8: =ASSUMPTIONS!$C$28*(1+ASSUMPTIONS!$C$29)^1 -> 3240 | R8: =ASSUMPTIONS!$B$70*12*(1+ASSUMPTIONS!$B$71)^3 -> 31389.501 | S8: =ASSUMPTIONS!$C$61*12 -> 6000 | T8: =N8+O8-P8-Q8-R8-S8 -> 97382.197 | U8: =U7*(1+ASSUMPTIONS!$C$59)+S8+MAX(T8,0)*0.2 -> 369280.45 | V8: PhD Student | W8: =ASSUMPTIONS!$D$46 -> 47000 | X8: =ASSUMPTIONS!$D$33*(1+ASSUMPTIONS!$D$34)^1*12+ASSUMPTIONS!$D$38*12+ASSUMPTIONS!$D$39 -> 67719.27 | Y8: =MAX(W8*0.1,0) -> 4700 | Z8: 0 | AA8: =ASSUMPTIONS!$B$70*12*(1+ASSUMPTIONS!$B$71)^3 -> 31389.501 | AB8: =ASSUMPTIONS!$D$62*12 -> 0 | AC8: =W8+X8-Y8-Z8-AA8-AB8 -> 78629.769 | AD8: =AD7*(1+ASSUMPTIONS!$D$59)+AB8+MAX(AC8,0)*0.2 -> 333137.99 | AE8: =(E8+F8)-(N8+O8) -> -74962.258 | AF8: =(E8+F8)-(W8+X8) -> -866.25779 | AG8: =L8-U8 -> 17247.932 | AH8: =L8-AD8 -> 53390.394
A9: 4 | B9: 2030 | C9: 40 | D9: Active Duty | E9: =ASSUMPTIONS!$B$12*12*(1+ASSUMPTIONS!$B$52)^4 -> 74065.757 | F9: =(ASSUMPTIONS!$B$13+ASSUMPTIONS!$B$14)*12*(1+ASSUMPTIONS!$B$52)^4 -> 42633.581 | G9: =MAX((E9-F9)*(ASSUMPTIONS!$B$64+ASSUMPTIONS!$B$67),0) -> 5972.1134 | H9: 0 | I9: =ASSUMPTIONS!$B$70*12*(1+ASSUMPTIONS!$B$71)^4 -> 32331.186 | J9: =ASSUMPTIONS!$B$60*12 -> 22800 | K9: =E9+F9-G9-H9-I9-J9 -> 55596.038 | L9: =L8*(1+ASSUMPTIONS!$B$59)+J9+MAX(K9,0)*0.2 -> 447504.57 | M9: CS / Tech Job | N9: =ASSUMPTIONS!$C$47*(1+ASSUMPTIONS!$B$51)^2 -> 189280 | O9: =ASSUMPTIONS!$C$33*(1+ASSUMPTIONS!$C$34)^2*12 -> 7006.0975 | P9: =MAX((N9-O9)*(ASSUMPTIONS!$C$65+ASSUMPTIONS!$C$67),0) -> 52859.432 | Q9: =ASSUMPTIONS!$C$28*(1+ASSUMPTIONS!$C$29)^2 -> 3499.2 | R9: =ASSUMPTIONS!$B$70*12*(1+ASSUMPTIONS!$B$71)^4 -> 32331.186 | S9: =ASSUMPTIONS!$C$61*12 -> 6000 | T9: =N9+O9-P9-Q9-R9-S9 -> 101596.28 | U9: =U8*(1+ASSUMPTIONS!$C$59)+S9+MAX(T9,0)*0.2 -> 421449.34 | V9: PhD Student | W9: =ASSUMPTIONS!$D$46 -> 47000 | X9: =ASSUMPTIONS!$D$33*(1+ASSUMPTIONS!$D$34)^2*12+ASSUMPTIONS!$D$38*12+ASSUMPTIONS!$D$39 -> 67910.097 | Y9: =MAX(W9*0.1,0) -> 4700 | Z9: 0 | AA9: =ASSUMPTIONS!$B$70*12*(1+ASSUMPTIONS!$B$71)^4 -> 32331.186 | AB9: =ASSUMPTIONS!$D$62*12 -> 0 | AC9: =W9+X9-Y9-Z9-AA9-AB9 -> 77878.911 | AD9: =AD8*(1+ASSUMPTIONS!$D$59)+AB9+MAX(AC9,0)*0.2 -> 372033.43 | AE9: =(E9+F9)-(N9+O9) -> -79586.76 | AF9: =(E9+F9)-(W9+X9) -> 1789.24 | AG9: =L9-U9 -> 26055.239 | AH9: =L9-AD9 -> 75471.147
A10: 5 | B10: 2031 | C10: 41 | D10: Active Duty | E10: =ASSUMPTIONS!$B$12*12*(1+ASSUMPTIONS!$B$52)^5 -> 75917.401 | F10: =(ASSUMPTIONS!$B$13+ASSUMPTIONS!$B$14)*12*(1+ASSUMPTIONS!$B$52)^5 -> 43699.42 | G10: =MAX((E10-F10)*(ASSUMPTIONS!$B$64+ASSUMPTIONS!$B$67),0) -> 6121.4163 | H10: 0 | I10: =ASSUMPTIONS!$B$70*12*(1+ASSUMPTIONS!$B$71)^5 -> 33301.122 | J10: =ASSUMPTIONS!$B$60*12 -> 22800 | K10: =E10+F10-G10-H10-I10-J10 -> 57394.283 | L10: =L9*(1+ASSUMPTIONS!$B$59)+J10+MAX(K10,0)*0.2 -> 513108.75 | M10: CS / Tech Job | N10: =ASSUMPTIONS!$C$47*(1+ASSUMPTIONS!$B$51)^3 -> 196851.2 | O10: =ASSUMPTIONS!$C$33*(1+ASSUMPTIONS!$C$34)^3*12 -> 7202.2682 | P10: =MAX((N10-O10)*(ASSUMPTIONS!$C$65+ASSUMPTIONS!$C$67),0) -> 54998.19 | Q10: =ASSUMPTIONS!$C$28*(1+ASSUMPTIONS!$C$29)^3 -> 3779.136 | R10: =ASSUMPTIONS!$B$70*12*(1+ASSUMPTIONS!$B$71)^5 -> 33301.122 | S10: =ASSUMPTIONS!$C$61*12 -> 6000 | T10: =N10+O10-P10-Q10-R10-S10 -> 105975.02 | U10: =U9*(1+ASSUMPTIONS!$C$59)+S10+MAX(T10,0)*0.2 -> 478145.79 | V10: PhD Student | W10: =ASSUMPTIONS!$D$46 -> 47000 | X10: =ASSUMPTIONS!$D$33*(1+ASSUMPTIONS!$D$34)^3*12+ASSUMPTIONS!$D$38*12+ASSUMPTIONS!$D$39 -> 68106.268 | Y10: =MAX(W10*0.1,0) -> 4700 | Z10: 0 | AA10: =ASSUMPTIONS!$B$70*12*(1+ASSUMPTIONS!$B$71)^5 -> 33301.122 | AB10: =ASSUMPTIONS!$D$62*12 -> 0 | AC10: =W10+X10-Y10-Z10-AA10-AB10 -> 77105.147 | AD10: =AD9*(1+ASSUMPTIONS!$D$59)+AB10+MAX(AC10,0)*0.2 -> 413496.8 | AE10: =(E10+F10)-(N10+O10) -> -84436.647 | AF10: =(E10+F10)-(W10+X10) -> 4510.5527 | AG10: =L10-U10 -> 34962.958 | AH10: =L10-AD10 -> 99611.954
A11: 6 | B11: 2032 | C11: 42 | D11: Active Duty | E11: =ASSUMPTIONS!$B$12*12*(1+ASSUMPTIONS!$B$52)^6 -> 77815.336 | F11: =(ASSUMPTIONS!$B$13+ASSUMPTIONS!$B$14)*12*(1+ASSUMPTIONS!$B$52)^6 -> 44791.906 | G11: =MAX((E11-F11)*(ASSUMPTIONS!$B$64+ASSUMPTIONS!$B$67),0) -> 6274.4517 | H11: 0 | I11: =ASSUMPTIONS!$B$70*12*(1+ASSUMPTIONS!$B$71)^6 -> 34300.155 | J11: =ASSUMPTIONS!$B$60*12 -> 22800 | K11: =E11+F11-G11-H11-I11-J11 -> 59232.635 | L11: =L10*(1+ASSUMPTIONS!$B$59)+J11+MAX(K11,0)*0.2 -> 583672.89 | M11: CS / Tech Job | N11: =ASSUMPTIONS!$C$47*(1+ASSUMPTIONS!$B$51)^4 -> 204725.25 | O11: =ASSUMPTIONS!$C$33*(1+ASSUMPTIONS!$C$34)^4*12 -> 7403.9317 | P11: =MAX((N11-O11)*(ASSUMPTIONS!$C$65+ASSUMPTIONS!$C$67),0) -> 57223.182 | Q11: =ASSUMPTIONS!$C$28*(1+ASSUMPTIONS!$C$29)^4 -> 4081.4669 | R11: =ASSUMPTIONS!$B$70*12*(1+ASSUMPTIONS!$B$71)^6 -> 34300.155 | S11: =ASSUMPTIONS!$C$61*12 -> 6000 | T11: =N11+O11-P11-Q11-R11-S11 -> 110524.38 | U11: =U10*(1+ASSUMPTIONS!$C$59)+S11+MAX(T11,0)*0.2 -> 539720.87 | V11: PhD Student | W11: =ASSUMPTIONS!$D$46 -> 47000 | X11: =ASSUMPTIONS!$D$33*(1+ASSUMPTIONS!$D$34)^4*12+ASSUMPTIONS!$D$38*12+ASSUMPTIONS!$D$39 -> 68307.932 | Y11: =MAX(W11*0.1,0) -> 4700 | Z11: 0 | AA11: =ASSUMPTIONS!$B$70*12*(1+ASSUMPTIONS!$B$71)^6 -> 34300.155 | AB11: =ASSUMPTIONS!$D$62*12 -> 0 | AC11: =W11+X11-Y11-Z11-AA11-AB11 -> 76307.776 | AD11: =AD10*(1+ASSUMPTIONS!$D$59)+AB11+MAX(AC11,0)*0.2 -> 457703.13 | AE11: =(E11+F11)-(N11+O11) -> -89521.938 | AF11: =(E11+F11)-(W11+X11) -> 7299.3097 | AG11: =L11-U11 -> 43952.017 | AH11: =L11-AD11 -> 125969.76
A12: 7 | B12: 2033 | C12: 43 | D12: Active Duty | E12: =ASSUMPTIONS!$B$12*12*(1+ASSUMPTIONS!$B$52)^7 -> 79760.719 | F12: =(ASSUMPTIONS!$B$13+ASSUMPTIONS!$B$14)*12*(1+ASSUMPTIONS!$B$52)^7 -> 45911.703 | G12: =MAX((E12-F12)*(ASSUMPTIONS!$B$64+ASSUMPTIONS!$B$67),0) -> 6431.3129 | H12: 0 | I12: =ASSUMPTIONS!$B$70*12*(1+ASSUMPTIONS!$B$71)^7 -> 35329.16 | J12: =ASSUMPTIONS!$B$60*12 -> 22800 | K12: =E12+F12-G12-H12-I12-J12 -> 61111.95 | L12: =L11*(1+ASSUMPTIONS!$B$59)+J12+MAX(K12,0)*0.2 -> 659552.38 | M12: CS / Tech Job | N12: =ASSUMPTIONS!$C$47*(1+ASSUMPTIONS!$B$51)^5 -> 212914.26 | O12: =ASSUMPTIONS!$C$33*(1+ASSUMPTIONS!$C$34)^5*12 -> 7611.2418 | P12: =MAX((N12-O12)*(ASSUMPTIONS!$C$65+ASSUMPTIONS!$C$67),0) -> 59537.875 | Q12: =ASSUMPTIONS!$C$28*(1+ASSUMPTIONS!$C$29)^5 -> 4407.9842 | R12: =ASSUMPTIONS!$B$70*12*(1+ASSUMPTIONS!$B$71)^7 -> 35329.16 | S12: =ASSUMPTIONS!$C$61*12 -> 6000 | T12: =N12+O12-P12-Q12-R12-S12 -> 115250.48 | U12: =U11*(1+ASSUMPTIONS!$C$59)+S12+MAX(T12,0)*0.2 -> 606551.43 | V12: PhD Student | W12: =ASSUMPTIONS!$D$46 -> 47000 | X12: =ASSUMPTIONS!$D$33*(1+ASSUMPTIONS!$D$34)^5*12+ASSUMPTIONS!$D$38*12+ASSUMPTIONS!$D$39 -> 68515.242 | Y12: =MAX(W12*0.1,0) -> 4700 | Z12: 0 | AA12: =ASSUMPTIONS!$B$70*12*(1+ASSUMPTIONS!$B$71)^7 -> 35329.16 | AB12: =ASSUMPTIONS!$D$62*12 -> 0 | AC12: =W12+X12-Y12-Z12-AA12-AB12 -> 75486.082 | AD12: =AD11*(1+ASSUMPTIONS!$D$59)+AB12+MAX(AC12,0)*0.2 -> 504839.56 | AE12: =(E12+F12)-(N12+O12) -> -94853.077 | AF12: =(E12+F12)-(W12+X12) -> 10157.181 | AG12: =L12-U12 -> 53000.952 | AH12: =L12-AD12 -> 154712.82
A13: 8 | B13: 2034 | C13: 44 | D13: Retirement Year | E13: =ASSUMPTIONS!$B$12*12*(1+ASSUMPTIONS!$B$52)^8*0.75+ASSUMPTIONS!$B$21*12*0.25 -> 72215.053 | F13: =(ASSUMPTIONS!$B$13+ASSUMPTIONS!$B$14)*12*(1+ASSUMPTIONS!$B$52)^8*0.75+ASSUMPTIONS!$B$33*12*0.25 -> 36952.032 | G13: =MAX((E13-F13)*(ASSUMPTIONS!$B$64+ASSUMPTIONS!$B$67),0) -> 6699.9739 | H13: =ASSUMPTIONS!$B$26*0.25 -> 45.5 | I13: =ASSUMPTIONS!$B$70*12*(1+ASSUMPTIONS!$B$71)^8 -> 36389.035 | J13: =ASSUMPTIONS!$B$62*12 -> 0 | K13: =E13+F13-G13-H13-I13-J13 -> 66032.576 | L13: =L12*(1+ASSUMPTIONS!$B$59)+J13+MAX(K13,0)*0.2 -> 718927.56 | M13: CS / Tech Job | N13: =ASSUMPTIONS!$C$47*(1+ASSUMPTIONS!$B$51)^6 -> 221430.83 | O13: =ASSUMPTIONS!$C$33*(1+ASSUMPTIONS!$C$34)^6*12 -> 7824.3566 | P13: =MAX((N13-O13)*(ASSUMPTIONS!$C$65+ASSUMPTIONS!$C$67),0) -> 61945.877 | Q13: =ASSUMPTIONS!$C$28*(1+ASSUMPTIONS!$C$29)^6 -> 4760.623 | R13: =ASSUMPTIONS!$B$70*12*(1+ASSUMPTIONS!$B$71)^8 -> 36389.035 | S13: =ASSUMPTIONS!$C$61*12 -> 6000 | T13: =N13+O13-P13-Q13-R13-S13 -> 120159.65 | U13: =U12*(1+ASSUMPTIONS!$C$59)+S13+MAX(T13,0)*0.2 -> 679041.96 | V13: Research Scientist | W13: =ASSUMPTIONS!$D$48*(1+ASSUMPTIONS!$B$51)^0 -> 230000 | X13: =ASSUMPTIONS!$D$33*(1+ASSUMPTIONS!$D$34)^6*12 -> 7824.3566 | Y13: =MAX((W13-X13)*(ASSUMPTIONS!$D$66+ASSUMPTIONS!$D$67),0) -> 68874.449 | Z13: =ASSUMPTIONS!$D$28*(1+ASSUMPTIONS!$D$29)^6 -> 0 | AA13: =ASSUMPTIONS!$B$70*12*(1+ASSUMPTIONS!$B$71)^8 -> 36389.035 | AB13: =ASSUMPTIONS!$D$61*12 -> 6000 | AC13: =W13+X13-Y13-Z13-AA13-AB13 -> 126560.87 | AD13: =AD12*(1+ASSUMPTIONS!$D$59)+AB13+MAX(AC13,0)*0.2 -> 571490.51 | AE13: =(E13+F13)-(N13+O13) -> -120088.1 | AF13: =(E13+F13)-(W13+X13) -> -128657.27 | AG13: =L13-U13 -> 39885.603 | AH13: =L13-AD13 -> 147437.06
A14: 9 | B14: 2035 | C14: 45 | D14: PhD Student | E14: =ASSUMPTIONS!$B$21*(1+ASSUMPTIONS!$B$23)^1*12+ASSUMPTIONS!$B$46 -> 91816.688 | F14: =ASSUMPTIONS!$B$33*(1+ASSUMPTIONS!$B$34)^1*12+ASSUMPTIONS!$B$38*12+ASSUMPTIONS!$B$39 -> 67719.27 | G14: =MAX((E14-F14)*(ASSUMPTIONS!$B$64+ASSUMPTIONS!$B$67),0) -> 4578.5094 | H14: =ASSUMPTIONS!$B$26*(1+ASSUMPTIONS!$B$27)^1 -> 187.46 | I14: =ASSUMPTIONS!$B$70*12*(1+ASSUMPTIONS!$B$71)^9 -> 37480.706 | J14: =ASSUMPTIONS!$B$62*12 -> 0 | K14: =E14+F14-G14-H14-I14-J14 -> 117289.28 | L14: =L13*(1+ASSUMPTIONS!$B$59)+J14+MAX(K14,0)*0.2 -> 792710.35 | M14: CS / Tech Job | N14: =ASSUMPTIONS!$C$47*(1+ASSUMPTIONS!$B$51)^7 -> 230288.06 | O14: =ASSUMPTIONS!$C$33*(1+ASSUMPTIONS!$C$34)^7*12 -> 8043.4386 | P14: =MAX((N14-O14)*(ASSUMPTIONS!$C$65+ASSUMPTIONS!$C$67),0) -> 64450.941 | Q14: =ASSUMPTIONS!$C$28*(1+ASSUMPTIONS!$C$29)^7 -> 5141.4728 | R14: =ASSUMPTIONS!$B$70*12*(1+ASSUMPTIONS!$B$71)^9 -> 37480.706 | S14: =ASSUMPTIONS!$C$61*12 -> 6000 | T14: =N14+O14-P14-Q14-R14-S14 -> 125258.38 | U14: =U13*(1+ASSUMPTIONS!$C$59)+S14+MAX(T14,0)*0.2 -> 757626.57 | V14: Research Scientist | W14: =ASSUMPTIONS!$D$48*(1+ASSUMPTIONS!$B$51)^1 -> 239200 | X14: =ASSUMPTIONS!$D$33*(1+ASSUMPTIONS!$D$34)^7*12 -> 8043.4386 | Y14: =MAX((W14-X14)*(ASSUMPTIONS!$D$66+ASSUMPTIONS!$D$67),0) -> 71658.534 | Z14: =ASSUMPTIONS!$D$28*(1+ASSUMPTIONS!$D$29)^7 -> 0 | AA14: =ASSUMPTIONS!$B$70*12*(1+ASSUMPTIONS!$B$71)^9 -> 37480.706 | AB14: =ASSUMPTIONS!$D$61*12 -> 6000 | AC14: =W14+X14-Y14-Z14-AA14-AB14 -> 132104.2 | AD14: =AD13*(1+ASSUMPTIONS!$D$59)+AB14+MAX(AC14,0)*0.2 -> 643915.68 | AE14: =(E14+F14)-(N14+O14) -> -78795.542 | AF14: =(E14+F14)-(W14+X14) -> -87707.481 | AG14: =L14-U14 -> 35083.776 | AH14: =L14-AD14 -> 148794.67
A15: 10 | B15: 2036 | C15: 46 | D15: PhD Student | E15: =ASSUMPTIONS!$B$21*(1+ASSUMPTIONS!$B$23)^2*12+ASSUMPTIONS!$B$46 -> 93071.555 | F15: =ASSUMPTIONS!$B$33*(1+ASSUMPTIONS!$B$34)^2*12+ASSUMPTIONS!$B$38*12+ASSUMPTIONS!$B$39 -> 67910.097 | G15: =MAX((E15-F15)*(ASSUMPTIONS!$B$64+ASSUMPTIONS!$B$67),0) -> 4780.677 | H15: =ASSUMPTIONS!$B$26*(1+ASSUMPTIONS!$B$27)^2 -> 193.0838 | I15: =ASSUMPTIONS!$B$70*12*(1+ASSUMPTIONS!$B$71)^10 -> 38605.127 | J15: =ASSUMPTIONS!$B$62*12 -> 0 | K15: =E15+F15-G15-H15-I15-J15 -> 117402.77 | L15: =L14*(1+ASSUMPTIONS!$B$59)+J15+MAX(K15,0)*0.2 -> 871680.63 | M15: CS / Tech Job | N15: =ASSUMPTIONS!$C$47*(1+ASSUMPTIONS!$B$51)^8 -> 239499.58 | O15: =ASSUMPTIONS!$C$33*(1+ASSUMPTIONS!$C$34)^8*12 -> 8268.6548 | P15: =MAX((N15-O15)*(ASSUMPTIONS!$C$65+ASSUMPTIONS!$C$67),0) -> 67056.969 | Q15: =ASSUMPTIONS!$C$28*(1+ASSUMPTIONS!$C$29)^8 -> 5552.7906 | R15: =ASSUMPTIONS!$B$70*12*(1+ASSUMPTIONS!$B$71)^10 -> 38605.127 | S15: =ASSUMPTIONS!$C$61*12 -> 6000 | T15: =N15+O15-P15-Q15-R15-S15 -> 130553.35 | U15: =U14*(1+ASSUMPTIONS!$C$59)+S15+MAX(T15,0)*0.2 -> 842771.11 | V15: Research Scientist | W15: =ASSUMPTIONS!$D$48*(1+ASSUMPTIONS!$B$51)^2 -> 248768 | X15: =ASSUMPTIONS!$D$33*(1+ASSUMPTIONS!$D$34)^8*12 -> 8268.6548 | Y15: =MAX((W15-X15)*(ASSUMPTIONS!$D$66+ASSUMPTIONS!$D$67),0) -> 74554.797 | Z15: =ASSUMPTIONS!$D$28*(1+ASSUMPTIONS!$D$29)^8 -> 0 | AA15: =ASSUMPTIONS!$B$70*12*(1+ASSUMPTIONS!$B$71)^10 -> 38605.127 | AB15: =ASSUMPTIONS!$D$61*12 -> 6000 | AC15: =W15+X15-Y15-Z15-AA15-AB15 -> 137876.73 | AD15: =AD14*(1+ASSUMPTIONS!$D$59)+AB15+MAX(AC15,0)*0.2 -> 722565.13 | AE15: =(E15+F15)-(N15+O15) -> -86786.586 | AF15: =(E15+F15)-(W15+X15) -> -96055.002 | AG15: =L15-U15 -> 28909.523 | AH15: =L15-AD15 -> 149115.5
A16: 11 | B16: 2037 | C16: 47 | D16: PhD Student | E16: =ASSUMPTIONS!$B$21*(1+ASSUMPTIONS!$B$23)^3*12+ASSUMPTIONS!$B$46 -> 94361.559 | F16: =ASSUMPTIONS!$B$33*(1+ASSUMPTIONS!$B$34)^3*12+ASSUMPTIONS!$B$38*12+ASSUMPTIONS!$B$39 -> 68106.268 | G16: =MAX((E16-F16)*(ASSUMPTIONS!$B$64+ASSUMPTIONS!$B$67),0) -> 4988.5052 | H16: =ASSUMPTIONS!$B$26*(1+ASSUMPTIONS!$B$27)^3 -> 198.87631 | I16: =ASSUMPTIONS!$B$70*12*(1+ASSUMPTIONS!$B$71)^11 -> 39763.281 | J16: =ASSUMPTIONS!$B$62*12 -> 0 | K16: =E16+F16-G16-H16-I16-J16 -> 117517.16 | L16: =L15*(1+ASSUMPTIONS!$B$59)+J16+MAX(K16,0)*0.2 -> 956201.71 | M16: CS / Tech Job | N16: =ASSUMPTIONS!$C$47*(1+ASSUMPTIONS!$B$51)^9 -> 249079.57 | O16: =ASSUMPTIONS!$C$33*(1+ASSUMPTIONS!$C$34)^9*12 -> 8500.1772 | P16: =MAX((N16-O16)*(ASSUMPTIONS!$C$65+ASSUMPTIONS!$C$67),0) -> 69768.023 | Q16: =ASSUMPTIONS!$C$28*(1+ASSUMPTIONS!$C$29)^9 -> 5997.0139 | R16: =ASSUMPTIONS!$B$70*12*(1+ASSUMPTIONS!$B$71)^11 -> 39763.281 | S16: =ASSUMPTIONS!$C$61*12 -> 6000 | T16: =N16+O16-P16-Q16-R16-S16 -> 136051.43 | U16: =U15*(1+ASSUMPTIONS!$C$59)+S16+MAX(T16,0)*0.2 -> 934975.37 | V16: Research Scientist | W16: =ASSUMPTIONS!$D$48*(1+ASSUMPTIONS!$B$51)^3 -> 258718.72 | X16: =ASSUMPTIONS!$D$33*(1+ASSUMPTIONS!$D$34)^9*12 -> 8500.1772 | Y16: =MAX((W16-X16)*(ASSUMPTIONS!$D$66+ASSUMPTIONS!$D$67),0) -> 77567.748 | Z16: =ASSUMPTIONS!$D$28*(1+ASSUMPTIONS!$D$29)^9 -> 0 | AA16: =ASSUMPTIONS!$B$70*12*(1+ASSUMPTIONS!$B$71)^11 -> 39763.281 | AB16: =ASSUMPTIONS!$D$61*12 -> 6000 | AC16: =W16+X16-Y16-Z16-AA16-AB16 -> 143887.87 | AD16: =AD15*(1+ASSUMPTIONS!$D$59)+AB16+MAX(AC16,0)*0.2 -> 807922.26 | AE16: =(E16+F16)-(N16+O16) -> -95111.917 | AF16: =(E16+F16)-(W16+X16) -> -104751.07 | AG16: =L16-U16 -> 21226.337 | AH16: =L16-AD16 -> 148279.45
A17: 12 | B17: 2038 | C17: 48 | D17: PhD Student | E17: =ASSUMPTIONS!$B$21*(1+ASSUMPTIONS!$B$23)^4*12+ASSUMPTIONS!$B$46 -> 95687.682 | F17: =ASSUMPTIONS!$B$33*(1+ASSUMPTIONS!$B$34)^4*12+ASSUMPTIONS!$B$38*12+ASSUMPTIONS!$B$39 -> 68307.932 | G17: =MAX((E17-F17)*(ASSUMPTIONS!$B$64+ASSUMPTIONS!$B$67),0) -> 5202.1526 | H17: =ASSUMPTIONS!$B$26*(1+ASSUMPTIONS!$B$27)^4 -> 204.8426 | I17: =ASSUMPTIONS!$B$70*12*(1+ASSUMPTIONS!$B$71)^12 -> 40956.179 | J17: =ASSUMPTIONS!$B$62*12 -> 0 | K17: =E17+F17-G17-H17-I17-J17 -> 117632.44 | L17: =L16*(1+ASSUMPTIONS!$B$59)+J17+MAX(K17,0)*0.2 -> 1046662.3 | M17: CS / Tech Job | N17: =ASSUMPTIONS!$C$47*(1+ASSUMPTIONS!$B$51)^10 -> 259042.75 | O17: =ASSUMPTIONS!$C$33*(1+ASSUMPTIONS!$C$34)^10*12 -> 8738.1821 | P17: =MAX((N17-O17)*(ASSUMPTIONS!$C$65+ASSUMPTIONS!$C$67),0) -> 72588.325 | Q17: =ASSUMPTIONS!$C$28*(1+ASSUMPTIONS!$C$29)^10 -> 6476.775 | R17: =ASSUMPTIONS!$B$70*12*(1+ASSUMPTIONS!$B$71)^12 -> 40956.179 | S17: =ASSUMPTIONS!$C$61*12 -> 6000 | T17: =N17+O17-P17-Q17-R17-S17 -> 141759.65 | U17: =U16*(1+ASSUMPTIONS!$C$59)+S17+MAX(T17,0)*0.2 -> 1034775.6 | V17: Research Scientist | W17: =ASSUMPTIONS!$D$48*(1+ASSUMPTIONS!$B$51)^4 -> 269067.47 | X17: =ASSUMPTIONS!$D$33*(1+ASSUMPTIONS!$D$34)^10*12 -> 8738.1821 | Y17: =MAX((W17-X17)*(ASSUMPTIONS!$D$66+ASSUMPTIONS!$D$67),0) -> 80702.079 | Z17: =ASSUMPTIONS!$D$28*(1+ASSUMPTIONS!$D$29)^10 -> 0 | AA17: =ASSUMPTIONS!$B$70*12*(1+ASSUMPTIONS!$B$71)^12 -> 40956.179 | AB17: =ASSUMPTIONS!$D$61*12 -> 6000 | AC17: =W17+X17-Y17-Z17-AA17-AB17 -> 150147.39 | AD17: =AD16*(1+ASSUMPTIONS!$D$59)+AB17+MAX(AC17,0)*0.2 -> 900506.3 | AE17: =(E17+F17)-(N17+O17) -> -103785.32 | AF17: =(E17+F17)-(W17+X17) -> -113810.04 | AG17: =L17-U17 -> 11886.738 | AH17: =L17-AD17 -> 146156.02
A18: 13 | B18: 2039 | C18: 49 | D18: PhD Student | E18: =ASSUMPTIONS!$B$21*(1+ASSUMPTIONS!$B$23)^5*12+ASSUMPTIONS!$B$46 -> 97050.938 | F18: =ASSUMPTIONS!$B$33*(1+ASSUMPTIONS!$B$34)^5*12+ASSUMPTIONS!$B$38*12+ASSUMPTIONS!$B$39 -> 68515.242 | G18: =MAX((E18-F18)*(ASSUMPTIONS!$B$64+ASSUMPTIONS!$B$67),0) -> 5421.7822 | H18: =ASSUMPTIONS!$B$26*(1+ASSUMPTIONS!$B$27)^5 -> 210.98788 | I18: =ASSUMPTIONS!$B$70*12*(1+ASSUMPTIONS!$B$71)^13 -> 42184.864 | J18: =ASSUMPTIONS!$B$62*12 -> 0 | K18: =E18+F18-G18-H18-I18-J18 -> 117748.54 | L18: =L17*(1+ASSUMPTIONS!$B$59)+J18+MAX(K18,0)*0.2 -> 1143478.4 | M18: CS / Tech Job | N18: =ASSUMPTIONS!$C$47*(1+ASSUMPTIONS!$B$51)^11 -> 269404.46 | O18: =ASSUMPTIONS!$C$33*(1+ASSUMPTIONS!$C$34)^11*12 -> 8982.8512 | P18: =MAX((N18-O18)*(ASSUMPTIONS!$C$65+ASSUMPTIONS!$C$67),0) -> 75522.266 | Q18: =ASSUMPTIONS!$C$28*(1+ASSUMPTIONS!$C$29)^11 -> 6994.917 | R18: =ASSUMPTIONS!$B$70*12*(1+ASSUMPTIONS!$B$71)^13 -> 42184.864 | S18: =ASSUMPTIONS!$C$61*12 -> 6000 | T18: =N18+O18-P18-Q18-R18-S18 -> 147685.26 | U18: =U17*(1+ASSUMPTIONS!$C$59)+S18+MAX(T18,0)*0.2 -> 1142746.9 | V18: Research Scientist | W18: =ASSUMPTIONS!$D$48*(1+ASSUMPTIONS!$B$51)^5 -> 279830.17 | X18: =ASSUMPTIONS!$D$33*(1+ASSUMPTIONS!$D$34)^11*12 -> 8982.8512 | Y18: =MAX((W18-X18)*(ASSUMPTIONS!$D$66+ASSUMPTIONS!$D$67),0) -> 83962.668 | Z18: =ASSUMPTIONS!$D$28*(1+ASSUMPTIONS!$D$29)^11 -> 0 | AA18: =ASSUMPTIONS!$B$70*12*(1+ASSUMPTIONS!$B$71)^13 -> 42184.864 | AB18: =ASSUMPTIONS!$D$61*12 -> 6000 | AC18: =W18+X18-Y18-Z18-AA18-AB18 -> 156665.49 | AD18: =AD17*(1+ASSUMPTIONS!$D$59)+AB18+MAX(AC18,0)*0.2 -> 1000874.8 | AE18: =(E18+F18)-(N18+O18) -> -112821.13 | AF18: =(E18+F18)-(W18+X18) -> -123246.84 | AG18: =L18-U18 -> 731.46622 | AH18: =L18-AD18 -> 142603.55
A19: 14 | B19: 2040 | C19: 50 | D19: Research Scientist | E19: =ASSUMPTIONS!$B$21*(1+ASSUMPTIONS!$B$23)^6*12+ASSUMPTIONS!$B$48*(1+ASSUMPTIONS!$B$51)^0 -> 281452.36 | F19: =ASSUMPTIONS!$B$33*(1+ASSUMPTIONS!$B$34)^6*12 -> 7824.3566 | G19: =MAX((E19-F19)*(ASSUMPTIONS!$B$66+ASSUMPTIONS!$B$67),0) -> 84824.682 | H19: =ASSUMPTIONS!$B$26*(1+ASSUMPTIONS!$B$27)^6 -> 217.31752 | I19: =ASSUMPTIONS!$B$70*12*(1+ASSUMPTIONS!$B$71)^14 -> 43450.41 | J19: =ASSUMPTIONS!$B$61*12 -> 6000 | K19: =E19+F19-G19-H19-I19-J19 -> 154784.31 | L19: =L18*(1+ASSUMPTIONS!$B$59)+J19+MAX(K19,0)*0.2 -> 1260478.7 | M19: CS / Tech Job | N19: =ASSUMPTIONS!$C$47*(1+ASSUMPTIONS!$B$51)^12 -> 280180.64 | O19: =ASSUMPTIONS!$C$33*(1+ASSUMPTIONS!$C$34)^12*12 -> 9234.3711 | P19: =MAX((N19-O19)*(ASSUMPTIONS!$C$65+ASSUMPTIONS!$C$67),0) -> 78574.417 | Q19: =ASSUMPTIONS!$C$28*(1+ASSUMPTIONS!$C$29)^12 -> 7554.5104 | R19: =ASSUMPTIONS!$B$70*12*(1+ASSUMPTIONS!$B$71)^14 -> 43450.41 | S19: =ASSUMPTIONS!$C$61*12 -> 6000 | T19: =N19+O19-P19-Q19-R19-S19 -> 153835.67 | U19: =U18*(1+ASSUMPTIONS!$C$59)+S19+MAX(T19,0)*0.2 -> 1259506.3 | V19: Research Scientist | W19: =ASSUMPTIONS!$D$48*(1+ASSUMPTIONS!$B$51)^6 -> 291023.37 | X19: =ASSUMPTIONS!$D$33*(1+ASSUMPTIONS!$D$34)^12*12 -> 9234.3711 | Y19: =MAX((W19-X19)*(ASSUMPTIONS!$D$66+ASSUMPTIONS!$D$67),0) -> 87354.591 | Z19: =ASSUMPTIONS!$D$28*(1+ASSUMPTIONS!$D$29)^12 -> 0 | AA19: =ASSUMPTIONS!$B$70*12*(1+ASSUMPTIONS!$B$71)^14 -> 43450.41 | AB19: =ASSUMPTIONS!$D$61*12 -> 6000 | AC19: =W19+X19-Y19-Z19-AA19-AB19 -> 163452.74 | AD19: =AD18*(1+ASSUMPTIONS!$D$59)+AB19+MAX(AC19,0)*0.2 -> 1109626.6 | AE19: =(E19+F19)-(N19+O19) -> -138.28893 | AF19: =(E19+F19)-(W19+X19) -> -10981.025 | AG19: =L19-U19 -> 972.39668 | AH19: =L19-AD19 -> 150852.11
A20: 15 | B20: 2041 | C20: 51 | D20: Research Scientist | E20: =ASSUMPTIONS!$B$21*(1+ASSUMPTIONS!$B$23)^7*12+ASSUMPTIONS!$B$48*(1+ASSUMPTIONS!$B$51)^1 -> 292093.03 | F20: =ASSUMPTIONS!$B$33*(1+ASSUMPTIONS!$B$34)^7*12 -> 8043.4386 | G20: =MAX((E20-F20)*(ASSUMPTIONS!$B$66+ASSUMPTIONS!$B$67),0) -> 88055.373 | H20: =ASSUMPTIONS!$B$26*(1+ASSUMPTIONS!$B$27)^7 -> 223.83704 | I20: =ASSUMPTIONS!$B$70*12*(1+ASSUMPTIONS!$B$71)^15 -> 44753.923 | J20: =ASSUMPTIONS!$B$61*12 -> 6000 | K20: =E20+F20-G20-H20-I20-J20 -> 161103.34 | L20: =L19*(1+ASSUMPTIONS!$B$59)+J20+MAX(K20,0)*0.2 -> 1386932.9 | M20: CS / Tech Job | N20: =ASSUMPTIONS!$C$47*(1+ASSUMPTIONS!$B$51)^13 -> 291387.86 | O20: =ASSUMPTIONS!$C$33*(1+ASSUMPTIONS!$C$34)^13*12 -> 9492.9335 | P20: =MAX((N20-O20)*(ASSUMPTIONS!$C$65+ASSUMPTIONS!$C$67),0) -> 81749.53 | Q20: =ASSUMPTIONS!$C$28*(1+ASSUMPTIONS!$C$29)^13 -> 8158.8712 | R20: =ASSUMPTIONS!$B$70*12*(1+ASSUMPTIONS!$B$71)^15 -> 44753.923 | S20: =ASSUMPTIONS!$C$61*12 -> 6000 | T20: =N20+O20-P20-Q20-R20-S20 -> 160218.47 | U20: =U19*(1+ASSUMPTIONS!$C$59)+S20+MAX(T20,0)*0.2 -> 1385715.5 | V20: Research Scientist | W20: =ASSUMPTIONS!$D$48*(1+ASSUMPTIONS!$B$51)^7 -> 302664.31 | X20: =ASSUMPTIONS!$D$33*(1+ASSUMPTIONS!$D$34)^13*12 -> 9492.9335 | Y20: =MAX((W20-X20)*(ASSUMPTIONS!$D$66+ASSUMPTIONS!$D$67),0) -> 90883.126 | Z20: =ASSUMPTIONS!$D$28*(1+ASSUMPTIONS!$D$29)^13 -> 0 | AA20: =ASSUMPTIONS!$B$70*12*(1+ASSUMPTIONS!$B$71)^15 -> 44753.923 | AB20: =ASSUMPTIONS!$D$61*12 -> 6000 | AC20: =W20+X20-Y20-Z20-AA20-AB20 -> 170520.19 | AD20: =AD19*(1+ASSUMPTIONS!$D$59)+AB20+MAX(AC20,0)*0.2 -> 1227404.5 | AE20: =(E20+F20)-(N20+O20) -> -744.32867 | AF20: =(E20+F20)-(W20+X20) -> -12020.774 | AG20: =L20-U20 -> 1217.4368 | AH20: =L20-AD20 -> 159528.39
A21: 16 | B21: 2042 | C21: 52 | D21: Research Scientist | E21: =ASSUMPTIONS!$B$21*(1+ASSUMPTIONS!$B$23)^8*12+ASSUMPTIONS!$B$48*(1+ASSUMPTIONS!$B$51)^2 -> 303142.03 | F21: =ASSUMPTIONS!$B$33*(1+ASSUMPTIONS!$B$34)^8*12 -> 8268.6548 | G21: =MAX((E21-F21)*(ASSUMPTIONS!$B$66+ASSUMPTIONS!$B$67),0) -> 91410.748 | H21: =ASSUMPTIONS!$B$26*(1+ASSUMPTIONS!$B$27)^8 -> 230.55215 | I21: =ASSUMPTIONS!$B$70*12*(1+ASSUMPTIONS!$B$71)^16 -> 46096.54 | J21: =ASSUMPTIONS!$B$61*12 -> 6000 | K21: =E21+F21-G21-H21-I21-J21 -> 167672.85 | L21: =L20*(1+ASSUMPTIONS!$B$59)+J21+MAX(K21,0)*0.2 -> 1523552.8 | M21: CS / Tech Job | N21: =ASSUMPTIONS!$C$47*(1+ASSUMPTIONS!$B$51)^14 -> 303043.38 | O21: =ASSUMPTIONS!$C$33*(1+ASSUMPTIONS!$C$34)^14*12 -> 9758.7356 | P21: =MAX((N21-O21)*(ASSUMPTIONS!$C$65+ASSUMPTIONS!$C$67),0) -> 85052.546 | Q21: =ASSUMPTIONS!$C$28*(1+ASSUMPTIONS!$C$29)^14 -> 8811.5809 | R21: =ASSUMPTIONS!$B$70*12*(1+ASSUMPTIONS!$B$71)^16 -> 46096.54 | S21: =ASSUMPTIONS!$C$61*12 -> 6000 | T21: =N21+O21-P21-Q21-R21-S21 -> 166841.45 | U21: =U20*(1+ASSUMPTIONS!$C$59)+S21+MAX(T21,0)*0.2 -> 1522083.8 | V21: Research Scientist | W21: =ASSUMPTIONS!$D$48*(1+ASSUMPTIONS!$B$51)^8 -> 314770.88 | X21: =ASSUMPTIONS!$D$33*(1+ASSUMPTIONS!$D$34)^14*12 -> 9758.7356 | Y21: =MAX((W21-X21)*(ASSUMPTIONS!$D$66+ASSUMPTIONS!$D$67),0) -> 94553.765 | Z21: =ASSUMPTIONS!$D$28*(1+ASSUMPTIONS!$D$29)^14 -> 0 | AA21: =ASSUMPTIONS!$B$70*12*(1+ASSUMPTIONS!$B$71)^16 -> 46096.54 | AB21: =ASSUMPTIONS!$D$61*12 -> 6000 | AC21: =W21+X21-Y21-Z21-AA21-AB21 -> 177879.31 | AD21: =AD20*(1+ASSUMPTIONS!$D$59)+AB21+MAX(AC21,0)*0.2 -> 1354898.7 | AE21: =(E21+F21)-(N21+O21) -> -1391.4242 | AF21: =(E21+F21)-(W21+X21) -> -13118.928 | AG21: =L21-U21 -> 1468.938 | AH21: =L21-AD21 -> 168654.08
A22: 17 | B22: 2043 | C22: 53 | D22: Research Scientist | E22: =ASSUMPTIONS!$B$21*(1+ASSUMPTIONS!$B$23)^9*12+ASSUMPTIONS!$B$48*(1+ASSUMPTIONS!$B$51)^3 -> 314615.23 | F22: =ASSUMPTIONS!$B$33*(1+ASSUMPTIONS!$B$34)^9*12 -> 8500.1772 | G22: =MAX((E22-F22)*(ASSUMPTIONS!$B$66+ASSUMPTIONS!$B$67),0) -> 94895.666 | H22: =ASSUMPTIONS!$B$26*(1+ASSUMPTIONS!$B$27)^9 -> 237.46872 | I22: =ASSUMPTIONS!$B$70*12*(1+ASSUMPTIONS!$B$71)^17 -> 47479.437 | J22: =ASSUMPTIONS!$B$61*12 -> 6000 | K22: =E22+F22-G22-H22-I22-J22 -> 174502.83 | L22: =L21*(1+ASSUMPTIONS!$B$59)+J22+MAX(K22,0)*0.2 -> 1671102 | M22: CS / Tech Job | N22: =ASSUMPTIONS!$C$47*(1+ASSUMPTIONS!$B$51)^15 -> 315165.11 | O22: =ASSUMPTIONS!$C$33*(1+ASSUMPTIONS!$C$34)^15*12 -> 10031.98 | P22: =MAX((N22-O22)*(ASSUMPTIONS!$C$65+ASSUMPTIONS!$C$67),0) -> 88488.609 | Q22: =ASSUMPTIONS!$C$28*(1+ASSUMPTIONS!$C$29)^15 -> 9516.5073 | R22: =ASSUMPTIONS!$B$70*12*(1+ASSUMPTIONS!$B$71)^17 -> 47479.437 | S22: =ASSUMPTIONS!$C$61*12 -> 6000 | T22: =N22+O22-P22-Q22-R22-S22 -> 173712.54 | U22: =U21*(1+ASSUMPTIONS!$C$59)+S22+MAX(T22,0)*0.2 -> 1669372.2 | V22: Research Scientist | W22: =ASSUMPTIONS!$D$48*(1+ASSUMPTIONS!$B$51)^9 -> 327361.72 | X22: =ASSUMPTIONS!$D$33*(1+ASSUMPTIONS!$D$34)^15*12 -> 10031.98 | Y22: =MAX((W22-X22)*(ASSUMPTIONS!$D$66+ASSUMPTIONS!$D$67),0) -> 98372.218 | Z22: =ASSUMPTIONS!$D$28*(1+ASSUMPTIONS!$D$29)^15 -> 0 | AA22: =ASSUMPTIONS!$B$70*12*(1+ASSUMPTIONS!$B$71)^17 -> 47479.437 | AB22: =ASSUMPTIONS!$D$61*12 -> 6000 | AC22: =W22+X22-Y22-Z22-AA22-AB22 -> 185542.04 | AD22: =AD21*(1+ASSUMPTIONS!$D$59)+AB22+MAX(AC22,0)*0.2 -> 1492850 | AE22: =(E22+F22)-(N22+O22) -> -2081.6887 | AF22: =(E22+F22)-(W22+X22) -> -14278.292 | AG22: =L22-U22 -> 1729.8223 | AH22: =L22-AD22 -> 178252.03
A23: 18 | B23: 2044 | C23: 54 | D23: Research Scientist | E23: =ASSUMPTIONS!$B$21*(1+ASSUMPTIONS!$B$23)^10*12+ASSUMPTIONS!$B$48*(1+ASSUMPTIONS!$B$51)^4 -> 326529.08 | F23: =ASSUMPTIONS!$B$33*(1+ASSUMPTIONS!$B$34)^10*12 -> 8738.1821 | G23: =MAX((E23-F23)*(ASSUMPTIONS!$B$66+ASSUMPTIONS!$B$67),0) -> 98515.178 | H23: =ASSUMPTIONS!$B$26*(1+ASSUMPTIONS!$B$27)^10 -> 244.59278 | I23: =ASSUMPTIONS!$B$70*12*(1+ASSUMPTIONS!$B$71)^18 -> 48903.82 | J23: =ASSUMPTIONS!$B$61*12 -> 6000 | K23: =E23+F23-G23-H23-I23-J23 -> 181603.67 | L23: =L22*(1+ASSUMPTIONS!$B$59)+J23+MAX(K23,0)*0.2 -> 1830399.9 | M23: CS / Tech Job | N23: =ASSUMPTIONS!$C$47*(1+ASSUMPTIONS!$B$51)^16 -> 327771.72 | O23: =ASSUMPTIONS!$C$33*(1+ASSUMPTIONS!$C$34)^16*12 -> 10312.876 | P23: =MAX((N23-O23)*(ASSUMPTIONS!$C$65+ASSUMPTIONS!$C$67),0) -> 92063.064 | Q23: =ASSUMPTIONS!$C$28*(1+ASSUMPTIONS!$C$29)^16 -> 10277.828 | R23: =ASSUMPTIONS!$B$70*12*(1+ASSUMPTIONS!$B$71)^18 -> 48903.82 | S23: =ASSUMPTIONS!$C$61*12 -> 6000 | T23: =N23+O23-P23-Q23-R23-S23 -> 180839.88 | U23: =U22*(1+ASSUMPTIONS!$C$59)+S23+MAX(T23,0)*0.2 -> 1828396.3 | V23: Research Scientist | W23: =ASSUMPTIONS!$D$48*(1+ASSUMPTIONS!$B$51)^10 -> 340456.19 | X23: =ASSUMPTIONS!$D$33*(1+ASSUMPTIONS!$D$34)^16*12 -> 10312.876 | Y23: =MAX((W23-X23)*(ASSUMPTIONS!$D$66+ASSUMPTIONS!$D$67),0) -> 102344.43 | Z23: =ASSUMPTIONS!$D$28*(1+ASSUMPTIONS!$D$29)^16 -> 0 | AA23: =ASSUMPTIONS!$B$70*12*(1+ASSUMPTIONS!$B$71)^18 -> 48903.82 | AB23: =ASSUMPTIONS!$D$61*12 -> 6000 | AC23: =W23+X23-Y23-Z23-AA23-AB23 -> 193520.82 | AD23: =AD22*(1+ASSUMPTIONS!$D$59)+AB23+MAX(AC23,0)*0.2 -> 1642053.7 | AE23: =(E23+F23)-(N23+O23) -> -2817.3327 | AF23: =(E23+F23)-(W23+X23) -> -15501.8 | AG23: =L23-U23 -> 2003.6676 | AH23: =L23-AD23 -> 188346.24
A24: 19 | B24: 2045 | C24: 55 | D24: Research Scientist | E24: =ASSUMPTIONS!$B$21*(1+ASSUMPTIONS!$B$23)^11*12+ASSUMPTIONS!$B$48*(1+ASSUMPTIONS!$B$51)^5 -> 338900.7 | F24: =ASSUMPTIONS!$B$33*(1+ASSUMPTIONS!$B$34)^11*12 -> 8982.8512 | G24: =MAX((E24-F24)*(ASSUMPTIONS!$B$66+ASSUMPTIONS!$B$67),0) -> 102274.53 | H24: =ASSUMPTIONS!$B$26*(1+ASSUMPTIONS!$B$27)^11 -> 251.93056 | I24: =ASSUMPTIONS!$B$70*12*(1+ASSUMPTIONS!$B$71)^19 -> 50370.934 | J24: =ASSUMPTIONS!$B$61*12 -> 6000 | K24: =E24+F24-G24-H24-I24-J24 -> 188986.16 | L24: =L23*(1+ASSUMPTIONS!$B$59)+J24+MAX(K24,0)*0.2 -> 2002325.1 | M24: CS / Tech Job | N24: =ASSUMPTIONS!$C$47*(1+ASSUMPTIONS!$B$51)^17 -> 340882.59 | O24: =ASSUMPTIONS!$C$33*(1+ASSUMPTIONS!$C$34)^17*12 -> 10601.636 | P24: =MAX((N24-O24)*(ASSUMPTIONS!$C$65+ASSUMPTIONS!$C$67),0) -> 95781.476 | Q24: =ASSUMPTIONS!$C$28*(1+ASSUMPTIONS!$C$29)^17 -> 11100.054 | R24: =ASSUMPTIONS!$B$70*12*(1+ASSUMPTIONS!$B$71)^19 -> 50370.934 | S24: =ASSUMPTIONS!$C$61*12 -> 6000 | T24: =N24+O24-P24-Q24-R24-S24 -> 188231.76 | U24: =U23*(1+ASSUMPTIONS!$C$59)+S24+MAX(T24,0)*0.2 -> 2000030.3 | V24: Research Scientist | W24: =ASSUMPTIONS!$D$48*(1+ASSUMPTIONS!$B$51)^11 -> 354074.43 | X24: =ASSUMPTIONS!$D$33*(1+ASSUMPTIONS!$D$34)^17*12 -> 10601.636 | Y24: =MAX((W24-X24)*(ASSUMPTIONS!$D$66+ASSUMPTIONS!$D$67),0) -> 106476.57 | Z24: =ASSUMPTIONS!$D$28*(1+ASSUMPTIONS!$D$29)^17 -> 0 | AA24: =ASSUMPTIONS!$B$70*12*(1+ASSUMPTIONS!$B$71)^19 -> 50370.934 | AB24: =ASSUMPTIONS!$D$61*12 -> 6000 | AC24: =W24+X24-Y24-Z24-AA24-AB24 -> 201828.57 | AD24: =AD23*(1+ASSUMPTIONS!$D$59)+AB24+MAX(AC24,0)*0.2 -> 1803363.2 | AE24: =(E24+F24)-(N24+O24) -> -3600.669 | AF24: =(E24+F24)-(W24+X24) -> -16792.515 | AG24: =L24-U24 -> 2294.8036 | AH24: =L24-AD24 -> 198961.99
A25: 20 | B25: 2046 | C25: 56 | D25: Research Scientist | E25: =ASSUMPTIONS!$B$21*(1+ASSUMPTIONS!$B$23)^12*12+ASSUMPTIONS!$B$48*(1+ASSUMPTIONS!$B$51)^6 -> 351747.88 | F25: =ASSUMPTIONS!$B$33*(1+ASSUMPTIONS!$B$34)^12*12 -> 9234.3711 | G25: =MAX((E25-F25)*(ASSUMPTIONS!$B$66+ASSUMPTIONS!$B$67),0) -> 106179.19 | H25: =ASSUMPTIONS!$B$26*(1+ASSUMPTIONS!$B$27)^12 -> 259.48848 | I25: =ASSUMPTIONS!$B$70*12*(1+ASSUMPTIONS!$B$71)^20 -> 51882.062 | J25: =ASSUMPTIONS!$B$61*12 -> 6000 | K25: =E25+F25-G25-H25-I25-J25 -> 196661.52 | L25: =L24*(1+ASSUMPTIONS!$B$59)+J25+MAX(K25,0)*0.2 -> 2187820.2 | M25: CS / Tech Job | N25: =ASSUMPTIONS!$C$47*(1+ASSUMPTIONS!$B$51)^18 -> 354517.89 | O25: =ASSUMPTIONS!$C$33*(1+ASSUMPTIONS!$C$34)^18*12 -> 10898.482 | P25: =MAX((N25-O25)*(ASSUMPTIONS!$C$65+ASSUMPTIONS!$C$67),0) -> 99649.628 | Q25: =ASSUMPTIONS!$C$28*(1+ASSUMPTIONS!$C$29)^18 -> 11988.058 | R25: =ASSUMPTIONS!$B$70*12*(1+ASSUMPTIONS!$B$71)^20 -> 51882.062 | S25: =ASSUMPTIONS!$C$61*12 -> 6000 | T25: =N25+O25-P25-Q25-R25-S25 -> 195896.62 | U25: =U24*(1+ASSUMPTIONS!$C$59)+S25+MAX(T25,0)*0.2 -> 2185211.8 | V25: Research Scientist | W25: =ASSUMPTIONS!$D$48*(1+ASSUMPTIONS!$B$51)^12 -> 368237.41 | X25: =ASSUMPTIONS!$D$33*(1+ASSUMPTIONS!$D$34)^18*12 -> 10898.482 | Y25: =MAX((W25-X25)*(ASSUMPTIONS!$D$66+ASSUMPTIONS!$D$67),0) -> 110775.07 | Z25: =ASSUMPTIONS!$D$28*(1+ASSUMPTIONS!$D$29)^18 -> 0 | AA25: =ASSUMPTIONS!$B$70*12*(1+ASSUMPTIONS!$B$71)^20 -> 51882.062 | AB25: =ASSUMPTIONS!$D$61*12 -> 6000 | AC25: =W25+X25-Y25-Z25-AA25-AB25 -> 210478.76 | AD25: =AD24*(1+ASSUMPTIONS!$D$59)+AB25+MAX(AC25,0)*0.2 -> 1977694.3 | AE25: =(E25+F25)-(N25+O25) -> -4434.1167 | AF25: =(E25+F25)-(W25+X25) -> -18153.637 | AG25: =L25-U25 -> 2608.4183 | AH25: =L25-AD25 -> 210125.88
A26: 21 | B26: 2047 | C26: 57 | D26: Research Scientist | E26: =ASSUMPTIONS!$B$21*(1+ASSUMPTIONS!$B$23)^13*12+ASSUMPTIONS!$B$48*(1+ASSUMPTIONS!$B$51)^7 -> 365089.11 | F26: =ASSUMPTIONS!$B$33*(1+ASSUMPTIONS!$B$34)^13*12 -> 9492.9335 | G26: =MAX((E26-F26)*(ASSUMPTIONS!$B$66+ASSUMPTIONS!$B$67),0) -> 110234.81 | H26: =ASSUMPTIONS!$B$26*(1+ASSUMPTIONS!$B$27)^13 -> 267.27314 | I26: =ASSUMPTIONS!$B$70*12*(1+ASSUMPTIONS!$B$71)^21 -> 53438.524 | J26: =ASSUMPTIONS!$B$61*12 -> 6000 | K26: =E26+F26-G26-H26-I26-J26 -> 204641.43 | L26: =L25*(1+ASSUMPTIONS!$B$59)+J26+MAX(K26,0)*0.2 -> 2387895.9 | M26: CS / Tech Job | N26: =ASSUMPTIONS!$C$47*(1+ASSUMPTIONS!$B$51)^19 -> 368698.61 | O26: =ASSUMPTIONS!$C$33*(1+ASSUMPTIONS!$C$34)^19*12 -> 11203.639 | P26: =MAX((N26-O26)*(ASSUMPTIONS!$C$65+ASSUMPTIONS!$C$67),0) -> 103673.54 | Q26: =ASSUMPTIONS!$C$28*(1+ASSUMPTIONS!$C$29)^19 -> 12947.103 | R26: =ASSUMPTIONS!$B$70*12*(1+ASSUMPTIONS!$B$71)^21 -> 53438.524 | S26: =ASSUMPTIONS!$C$61*12 -> 6000 | T26: =N26+O26-P26-Q26-R26-S26 -> 203843.08 | U26: =U25*(1+ASSUMPTIONS!$C$59)+S26+MAX(T26,0)*0.2 -> 2384945.2 | V26: Research Scientist | W26: =ASSUMPTIONS!$D$48*(1+ASSUMPTIONS!$B$51)^13 -> 382966.91 | X26: =ASSUMPTIONS!$D$33*(1+ASSUMPTIONS!$D$34)^19*12 -> 11203.639 | Y26: =MAX((W26-X26)*(ASSUMPTIONS!$D$66+ASSUMPTIONS!$D$67),0) -> 115246.61 | Z26: =ASSUMPTIONS!$D$28*(1+ASSUMPTIONS!$D$29)^19 -> 0 | AA26: =ASSUMPTIONS!$B$70*12*(1+ASSUMPTIONS!$B$71)^21 -> 53438.524 | AB26: =ASSUMPTIONS!$D$61*12 -> 6000 | AC26: =W26+X26-Y26-Z26-AA26-AB26 -> 219485.41 | AD26: =AD25*(1+ASSUMPTIONS!$D$59)+AB26+MAX(AC26,0)*0.2 -> 2166030 | AE26: =(E26+F26)-(N26+O26) -> -5320.2062 | AF26: =(E26+F26)-(W26+X26) -> -19588.507 | AG26: =L26-U26 -> 2950.6778 | AH26: =L26-AD26 -> 221865.9
A27: 22 | B27: 2048 | C27: 58 | D27: Research Scientist | E27: =ASSUMPTIONS!$B$21*(1+ASSUMPTIONS!$B$23)^14*12+ASSUMPTIONS!$B$48*(1+ASSUMPTIONS!$B$51)^8 -> 378943.57 | F27: =ASSUMPTIONS!$B$33*(1+ASSUMPTIONS!$B$34)^14*12 -> 9758.7356 | G27: =MAX((E27-F27)*(ASSUMPTIONS!$B$66+ASSUMPTIONS!$B$67),0) -> 114447.3 | H27: =ASSUMPTIONS!$B$26*(1+ASSUMPTIONS!$B$27)^14 -> 275.29133 | I27: =ASSUMPTIONS!$B$70*12*(1+ASSUMPTIONS!$B$71)^22 -> 55041.68 | J27: =ASSUMPTIONS!$B$61*12 -> 6000 | K27: =E27+F27-G27-H27-I27-J27 -> 212938.04 | L27: =L26*(1+ASSUMPTIONS!$B$59)+J27+MAX(K27,0)*0.2 -> 2603636.2 | M27: CS / Tech Job | N27: =ASSUMPTIONS!$C$47*(1+ASSUMPTIONS!$B$51)^20 -> 383446.55 | O27: =ASSUMPTIONS!$C$33*(1+ASSUMPTIONS!$C$34)^20*12 -> 11517.341 | P27: =MAX((N27-O27)*(ASSUMPTIONS!$C$65+ASSUMPTIONS!$C$67),0) -> 107859.47 | Q27: =ASSUMPTIONS!$C$28*(1+ASSUMPTIONS!$C$29)^20 -> 13982.871 | R27: =ASSUMPTIONS!$B$70*12*(1+ASSUMPTIONS!$B$71)^22 -> 55041.68 | S27: =ASSUMPTIONS!$C$61*12 -> 6000 | T27: =N27+O27-P27-Q27-R27-S27 -> 212079.87 | U27: =U26*(1+ASSUMPTIONS!$C$59)+S27+MAX(T27,0)*0.2 -> 2600307.4 | V27: Research Scientist | W27: =ASSUMPTIONS!$D$48*(1+ASSUMPTIONS!$B$51)^14 -> 398285.58 | X27: =ASSUMPTIONS!$D$33*(1+ASSUMPTIONS!$D$34)^20*12 -> 11517.341 | Y27: =MAX((W27-X27)*(ASSUMPTIONS!$D$66+ASSUMPTIONS!$D$67),0) -> 119898.15 | Z27: =ASSUMPTIONS!$D$28*(1+ASSUMPTIONS!$D$29)^20 -> 0 | AA27: =ASSUMPTIONS!$B$70*12*(1+ASSUMPTIONS!$B$71)^22 -> 55041.68 | AB27: =ASSUMPTIONS!$D$61*12 -> 6000 | AC27: =W27+X27-Y27-Z27-AA27-AB27 -> 228863.09 | AD27: =AD26*(1+ASSUMPTIONS!$D$59)+AB27+MAX(AC27,0)*0.2 -> 2369424.7 | AE27: =(E27+F27)-(N27+O27) -> -6261.5835 | AF27: =(E27+F27)-(W27+X27) -> -21100.616 | AG27: =L27-U27 -> 3328.8588 | AH27: =L27-AD27 -> 234211.5
A28: 23 | B28: 2049 | C28: 59 | D28: Research Scientist | E28: =ASSUMPTIONS!$B$21*(1+ASSUMPTIONS!$B$23)^15*12+ASSUMPTIONS!$B$48*(1+ASSUMPTIONS!$B$51)^9 -> 393331.24 | F28: =ASSUMPTIONS!$B$33*(1+ASSUMPTIONS!$B$34)^15*12 -> 10031.98 | G28: =MAX((E28-F28)*(ASSUMPTIONS!$B$66+ASSUMPTIONS!$B$67),0) -> 118822.77 | H28: =ASSUMPTIONS!$B$26*(1+ASSUMPTIONS!$B$27)^15 -> 283.55007 | I28: =ASSUMPTIONS!$B$70*12*(1+ASSUMPTIONS!$B$71)^23 -> 56692.93 | J28: =ASSUMPTIONS!$B$61*12 -> 6000 | K28: =E28+F28-G28-H28-I28-J28 -> 221563.97 | L28: =L27*(1+ASSUMPTIONS!$B$59)+J28+MAX(K28,0)*0.2 -> 2836203.6 | M28: CS / Tech Job | N28: =ASSUMPTIONS!$C$47*(1+ASSUMPTIONS!$B$51)^21 -> 398784.41 | O28: =ASSUMPTIONS!$C$33*(1+ASSUMPTIONS!$C$34)^21*12 -> 11839.827 | P28: =MAX((N28-O28)*(ASSUMPTIONS!$C$65+ASSUMPTIONS!$C$67),0) -> 112213.93 | Q28: =ASSUMPTIONS!$C$28*(1+ASSUMPTIONS!$C$29)^21 -> 15101.501 | R28: =ASSUMPTIONS!$B$70*12*(1+ASSUMPTIONS!$B$71)^23 -> 56692.93 | S28: =ASSUMPTIONS!$C$61*12 -> 6000 | T28: =N28+O28-P28-Q28-R28-S28 -> 220615.88 | U28: =U27*(1+ASSUMPTIONS!$C$59)+S28+MAX(T28,0)*0.2 -> 2832452.1 | V28: Research Scientist | W28: =ASSUMPTIONS!$D$48*(1+ASSUMPTIONS!$B$51)^15 -> 414217.01 | X28: =ASSUMPTIONS!$D$33*(1+ASSUMPTIONS!$D$34)^21*12 -> 11839.827 | Y28: =MAX((W28-X28)*(ASSUMPTIONS!$D$66+ASSUMPTIONS!$D$67),0) -> 124736.93 | Z28: =ASSUMPTIONS!$D$28*(1+ASSUMPTIONS!$D$29)^21 -> 0 | AA28: =ASSUMPTIONS!$B$70*12*(1+ASSUMPTIONS!$B$71)^23 -> 56692.93 | AB28: =ASSUMPTIONS!$D$61*12 -> 6000 | AC28: =W28+X28-Y28-Z28-AA28-AB28 -> 238626.98 | AD28: =AD27*(1+ASSUMPTIONS!$D$59)+AB28+MAX(AC28,0)*0.2 -> 2589009.9 | AE28: =(E28+F28)-(N28+O28) -> -7261.0159 | AF28: =(E28+F28)-(W28+X28) -> -22693.61 | AG28: =L28-U28 -> 3751.4976 | AH28: =L28-AD28 -> 247193.71
A29: 24 | B29: 2050 | C29: 60 | D29: Research Scientist | E29: =ASSUMPTIONS!$B$21*(1+ASSUMPTIONS!$B$23)^16*12+ASSUMPTIONS!$B$48*(1+ASSUMPTIONS!$B$51)^10 -> 408272.86 | F29: =ASSUMPTIONS!$B$33*(1+ASSUMPTIONS!$B$34)^16*12 -> 10312.876 | G29: =MAX((E29-F29)*(ASSUMPTIONS!$B$66+ASSUMPTIONS!$B$67),0) -> 123367.59 | H29: =ASSUMPTIONS!$B$26*(1+ASSUMPTIONS!$B$27)^16 -> 292.05657 | I29: =ASSUMPTIONS!$B$70*12*(1+ASSUMPTIONS!$B$71)^24 -> 58393.718 | J29: =ASSUMPTIONS!$B$61*12 -> 6000 | K29: =E29+F29-G29-H29-I29-J29 -> 230532.36 | L29: =L28*(1+ASSUMPTIONS!$B$59)+J29+MAX(K29,0)*0.2 -> 3086844.3 | M29: CS / Tech Job | N29: =ASSUMPTIONS!$C$47*(1+ASSUMPTIONS!$B$51)^22 -> 414735.79 | O29: =ASSUMPTIONS!$C$33*(1+ASSUMPTIONS!$C$34)^22*12 -> 12171.342 | P29: =MAX((N29-O29)*(ASSUMPTIONS!$C$65+ASSUMPTIONS!$C$67),0) -> 116743.69 | Q29: =ASSUMPTIONS!$C$28*(1+ASSUMPTIONS!$C$29)^22 -> 16309.621 | R29: =ASSUMPTIONS!$B$70*12*(1+ASSUMPTIONS!$B$71)^24 -> 58393.718 | S29: =ASSUMPTIONS!$C$61*12 -> 6000 | T29: =N29+O29-P29-Q29-R29-S29 -> 229460.1 | U29: =U28*(1+ASSUMPTIONS!$C$59)+S29+MAX(T29,0)*0.2 -> 3082615.7 | V29: Research Scientist | W29: =ASSUMPTIONS!$D$48*(1+ASSUMPTIONS!$B$51)^16 -> 430785.69 | X29: =ASSUMPTIONS!$D$33*(1+ASSUMPTIONS!$D$34)^22*12 -> 12171.342 | Y29: =MAX((W29-X29)*(ASSUMPTIONS!$D$66+ASSUMPTIONS!$D$67),0) -> 129770.45 | Z29: =ASSUMPTIONS!$D$28*(1+ASSUMPTIONS!$D$29)^22 -> 0 | AA29: =ASSUMPTIONS!$B$70*12*(1+ASSUMPTIONS!$B$71)^24 -> 58393.718 | AB29: =ASSUMPTIONS!$D$61*12 -> 6000 | AC29: =W29+X29-Y29-Z29-AA29-AB29 -> 248792.86 | AD29: =AD28*(1+ASSUMPTIONS!$D$59)+AB29+MAX(AC29,0)*0.2 -> 2825999.1 | AE29: =(E29+F29)-(N29+O29) -> -8321.3967 | AF29: =(E29+F29)-(W29+X29) -> -24371.295 | AG29: =L29-U29 -> 4228.555 | AH29: =L29-AD29 -> 260845.17
A30: 25 | B30: 2051 | C30: 61 | D30: Research Scientist | E30: =ASSUMPTIONS!$B$21*(1+ASSUMPTIONS!$B$23)^17*12+ASSUMPTIONS!$B$48*(1+ASSUMPTIONS!$B$51)^11 -> 423789.97 | F30: =ASSUMPTIONS!$B$33*(1+ASSUMPTIONS!$B$34)^17*12 -> 10601.636 | G30: =MAX((E30-F30)*(ASSUMPTIONS!$B$66+ASSUMPTIONS!$B$67),0) -> 128088.38 | H30: =ASSUMPTIONS!$B$26*(1+ASSUMPTIONS!$B$27)^17 -> 300.81827 | I30: =ASSUMPTIONS!$B$70*12*(1+ASSUMPTIONS!$B$71)^25 -> 60145.53 | J30: =ASSUMPTIONS!$B$61*12 -> 6000 | K30: =E30+F30-G30-H30-I30-J30 -> 239856.88 | L30: =L29*(1+ASSUMPTIONS!$B$59)+J30+MAX(K30,0)*0.2 -> 3356894.8 | M30: CS / Tech Job | N30: =ASSUMPTIONS!$C$47*(1+ASSUMPTIONS!$B$51)^23 -> 431325.22 | O30: =ASSUMPTIONS!$C$33*(1+ASSUMPTIONS!$C$34)^23*12 -> 12512.14 | P30: =MAX((N30-O30)*(ASSUMPTIONS!$C$65+ASSUMPTIONS!$C$67),0) -> 121455.79 | Q30: =ASSUMPTIONS!$C$28*(1+ASSUMPTIONS!$C$29)^23 -> 17614.391 | R30: =ASSUMPTIONS!$B$70*12*(1+ASSUMPTIONS!$B$71)^25 -> 60145.53 | S30: =ASSUMPTIONS!$C$61*12 -> 6000 | T30: =N30+O30-P30-Q30-R30-S30 -> 238621.65 | U30: =U29*(1+ASSUMPTIONS!$C$59)+S30+MAX(T30,0)*0.2 -> 3352123.2 | V30: Research Scientist | W30: =ASSUMPTIONS!$D$48*(1+ASSUMPTIONS!$B$51)^17 -> 448017.11 | X30: =ASSUMPTIONS!$D$33*(1+ASSUMPTIONS!$D$34)^23*12 -> 12512.14 | Y30: =MAX((W30-X30)*(ASSUMPTIONS!$D$66+ASSUMPTIONS!$D$67),0) -> 135006.54 | Z30: =ASSUMPTIONS!$D$28*(1+ASSUMPTIONS!$D$29)^23 -> 0 | AA30: =ASSUMPTIONS!$B$70*12*(1+ASSUMPTIONS!$B$71)^25 -> 60145.53 | AB30: =ASSUMPTIONS!$D$61*12 -> 6000 | AC30: =W30+X30-Y30-Z30-AA30-AB30 -> 259377.18 | AD30: =AD29*(1+ASSUMPTIONS!$D$59)+AB30+MAX(AC30,0)*0.2 -> 3081694.5 | AE30: =(E30+F30)-(N30+O30) -> -9445.751 | AF30: =(E30+F30)-(W30+X30) -> -26137.645 | AG30: =L30-U30 -> 4771.5999 | AH30: =L30-AD30 -> 275200.27
A31: 26 | B31: 2052 | C31: 62 | D31: Research Scientist | E31: =ASSUMPTIONS!$B$21*(1+ASSUMPTIONS!$B$23)^18*12+ASSUMPTIONS!$B$48*(1+ASSUMPTIONS!$B$51)^12 -> 439904.98 | F31: =ASSUMPTIONS!$B$33*(1+ASSUMPTIONS!$B$34)^18*12 -> 10898.482 | G31: =MAX((E31-F31)*(ASSUMPTIONS!$B$66+ASSUMPTIONS!$B$67),0) -> 132992.02 | H31: =ASSUMPTIONS!$B$26*(1+ASSUMPTIONS!$B$27)^18 -> 309.84282 | I31: =ASSUMPTIONS!$B$70*12*(1+ASSUMPTIONS!$B$71)^26 -> 61949.896 | J31: =ASSUMPTIONS!$B$61*12 -> 6000 | K31: =E31+F31-G31-H31-I31-J31 -> 249551.71 | L31: =L30*(1+ASSUMPTIONS!$B$59)+J31+MAX(K31,0)*0.2 -> 3647787.7 | M31: CS / Tech Job | N31: =ASSUMPTIONS!$C$47*(1+ASSUMPTIONS!$B$51)^24 -> 448578.23 | O31: =ASSUMPTIONS!$C$33*(1+ASSUMPTIONS!$C$34)^24*12 -> 12862.48 | P31: =MAX((N31-O31)*(ASSUMPTIONS!$C$65+ASSUMPTIONS!$C$67),0) -> 126357.57 | Q31: =ASSUMPTIONS!$C$28*(1+ASSUMPTIONS!$C$29)^24 -> 19023.542 | R31: =ASSUMPTIONS!$B$70*12*(1+ASSUMPTIONS!$B$71)^26 -> 61949.896 | S31: =ASSUMPTIONS!$C$61*12 -> 6000 | T31: =N31+O31-P31-Q31-R31-S31 -> 248109.7 | U31: =U30*(1+ASSUMPTIONS!$C$59)+S31+MAX(T31,0)*0.2 -> 3642393.7 | V31: Research Scientist | W31: =ASSUMPTIONS!$D$48*(1+ASSUMPTIONS!$B$51)^18 -> 465937.8 | X31: =ASSUMPTIONS!$D$33*(1+ASSUMPTIONS!$D$34)^24*12 -> 12862.48 | Y31: =MAX((W31-X31)*(ASSUMPTIONS!$D$66+ASSUMPTIONS!$D$67),0) -> 140453.35 | Z31: =ASSUMPTIONS!$D$28*(1+ASSUMPTIONS!$D$29)^24 -> 0 | AA31: =ASSUMPTIONS!$B$70*12*(1+ASSUMPTIONS!$B$71)^26 -> 61949.896 | AB31: =ASSUMPTIONS!$D$61*12 -> 6000 | AC31: =W31+X31-Y31-Z31-AA31-AB31 -> 270397.03 | AD31: =AD30*(1+ASSUMPTIONS!$D$59)+AB31+MAX(AC31,0)*0.2 -> 3357492.5 | AE31: =(E31+F31)-(N31+O31) -> -10637.241 | AF31: =(E31+F31)-(W31+X31) -> -27996.811 | AG31: =L31-U31 -> 5394.0138 | AH31: =L31-AD31 -> 290295.22
A32: 27 | B32: 2053 | C32: 63 | D32: Research Scientist | E32: =ASSUMPTIONS!$B$21*(1+ASSUMPTIONS!$B$23)^19*12+ASSUMPTIONS!$B$48*(1+ASSUMPTIONS!$B$51)^13 -> 456641.17 | F32: =ASSUMPTIONS!$B$33*(1+ASSUMPTIONS!$B$34)^19*12 -> 11203.639 | G32: =MAX((E32-F32)*(ASSUMPTIONS!$B$66+ASSUMPTIONS!$B$67),0) -> 138085.64 | H32: =ASSUMPTIONS!$B$26*(1+ASSUMPTIONS!$B$27)^19 -> 319.1381 | I32: =ASSUMPTIONS!$B$70*12*(1+ASSUMPTIONS!$B$71)^27 -> 63808.393 | J32: =ASSUMPTIONS!$B$61*12 -> 6000 | K32: =E32+F32-G32-H32-I32-J32 -> 259631.65 | L32: =L31*(1+ASSUMPTIONS!$B$59)+J32+MAX(K32,0)*0.2 -> 3961059.2 | M32: CS / Tech Job | N32: =ASSUMPTIONS!$C$47*(1+ASSUMPTIONS!$B$51)^25 -> 466521.36 | O32: =ASSUMPTIONS!$C$33*(1+ASSUMPTIONS!$C$34)^25*12 -> 13222.629 | P32: =MAX((N32-O32)*(ASSUMPTIONS!$C$65+ASSUMPTIONS!$C$67),0) -> 131456.63 | Q32: =ASSUMPTIONS!$C$28*(1+ASSUMPTIONS!$C$29)^25 -> 20545.426 | R32: =ASSUMPTIONS!$B$70*12*(1+ASSUMPTIONS!$B$71)^27 -> 63808.393 | S32: =ASSUMPTIONS!$C$61*12 -> 6000 | T32: =N32+O32-P32-Q32-R32-S32 -> 257933.54 | U32: =U31*(1+ASSUMPTIONS!$C$59)+S32+MAX(T32,0)*0.2 -> 3954948 | V32: Research Scientist | W32: =ASSUMPTIONS!$D$48*(1+ASSUMPTIONS!$B$51)^19 -> 484575.31 | X32: =ASSUMPTIONS!$D$33*(1+ASSUMPTIONS!$D$34)^25*12 -> 13222.629 | Y32: =MAX((W32-X32)*(ASSUMPTIONS!$D$66+ASSUMPTIONS!$D$67),0) -> 146119.33 | Z32: =ASSUMPTIONS!$D$28*(1+ASSUMPTIONS!$D$29)^25 -> 0 | AA32: =ASSUMPTIONS!$B$70*12*(1+ASSUMPTIONS!$B$71)^27 -> 63808.393 | AB32: =ASSUMPTIONS!$D$61*12 -> 6000 | AC32: =W32+X32-Y32-Z32-AA32-AB32 -> 281870.22 | AD32: =AD31*(1+ASSUMPTIONS!$D$59)+AB32+MAX(AC32,0)*0.2 -> 3654891 | AE32: =(E32+F32)-(N32+O32) -> -11899.174 | AF32: =(E32+F32)-(W32+X32) -> -29953.127 | AG32: =L32-U32 -> 6111.2166 | AH32: =L32-AD32 -> 306168.17
A33: 28 | B33: 2054 | C33: 64 | D33: Research Scientist | E33: =ASSUMPTIONS!$B$21*(1+ASSUMPTIONS!$B$23)^20*12+ASSUMPTIONS!$B$48*(1+ASSUMPTIONS!$B$51)^14 -> 474022.73 | F33: =ASSUMPTIONS!$B$33*(1+ASSUMPTIONS!$B$34)^20*12 -> 11517.341 | G33: =MAX((E33-F33)*(ASSUMPTIONS!$B$66+ASSUMPTIONS!$B$67),0) -> 143376.67 | H33: =ASSUMPTIONS!$B$26*(1+ASSUMPTIONS!$B$27)^20 -> 328.71224 | I33: =ASSUMPTIONS!$B$70*12*(1+ASSUMPTIONS!$B$71)^28 -> 65722.644 | J33: =ASSUMPTIONS!$B$61*12 -> 6000 | K33: =E33+F33-G33-H33-I33-J33 -> 270112.04 | L33: =L32*(1+ASSUMPTIONS!$B$59)+J33+MAX(K33,0)*0.2 -> 4298355.8 | M33: CS / Tech Job | N33: =ASSUMPTIONS!$C$47*(1+ASSUMPTIONS!$B$51)^26 -> 485182.21 | O33: =ASSUMPTIONS!$C$33*(1+ASSUMPTIONS!$C$34)^26*12 -> 13592.863 | P33: =MAX((N33-O33)*(ASSUMPTIONS!$C$65+ASSUMPTIONS!$C$67),0) -> 136760.91 | Q33: =ASSUMPTIONS!$C$28*(1+ASSUMPTIONS!$C$29)^26 -> 22189.06 | R33: =ASSUMPTIONS!$B$70*12*(1+ASSUMPTIONS!$B$71)^28 -> 65722.644 | S33: =ASSUMPTIONS!$C$61*12 -> 6000 | T33: =N33+O33-P33-Q33-R33-S33 -> 268102.46 | U33: =U32*(1+ASSUMPTIONS!$C$59)+S33+MAX(T33,0)*0.2 -> 4291414.8 | V33: Research Scientist | W33: =ASSUMPTIONS!$D$48*(1+ASSUMPTIONS!$B$51)^20 -> 503958.32 | X33: =ASSUMPTIONS!$D$33*(1+ASSUMPTIONS!$D$34)^26*12 -> 13592.863 | Y33: =MAX((W33-X33)*(ASSUMPTIONS!$D$66+ASSUMPTIONS!$D$67),0) -> 152013.29 | Z33: =ASSUMPTIONS!$D$28*(1+ASSUMPTIONS!$D$29)^26 -> 0 | AA33: =ASSUMPTIONS!$B$70*12*(1+ASSUMPTIONS!$B$71)^28 -> 65722.644 | AB33: =ASSUMPTIONS!$D$61*12 -> 6000 | AC33: =W33+X33-Y33-Z33-AA33-AB33 -> 293815.25 | AD33: =AD32*(1+ASSUMPTIONS!$D$59)+AB33+MAX(AC33,0)*0.2 -> 3975496.5 | AE33: =(E33+F33)-(N33+O33) -> -13235.004 | AF33: =(E33+F33)-(W33+X33) -> -32011.115 | AG33: =L33-U33 -> 6940.9186 | AH33: =L33-AD33 -> 322859.3
A34: 29 | B34: 2055 | C34: 65 | D34: Research Scientist | E34: =ASSUMPTIONS!$B$21*(1+ASSUMPTIONS!$B$23)^21*12+ASSUMPTIONS!$B$48*(1+ASSUMPTIONS!$B$51)^15 -> 492074.79 | F34: =ASSUMPTIONS!$B$33*(1+ASSUMPTIONS!$B$34)^21*12 -> 11839.827 | G34: =MAX((E34-F34)*(ASSUMPTIONS!$B$66+ASSUMPTIONS!$B$67),0) -> 148872.84 | H34: =ASSUMPTIONS!$B$26*(1+ASSUMPTIONS!$B$27)^21 -> 338.57361 | I34: =ASSUMPTIONS!$B$70*12*(1+ASSUMPTIONS!$B$71)^29 -> 67694.324 | J34: =ASSUMPTIONS!$B$61*12 -> 6000 | K34: =E34+F34-G34-H34-I34-J34 -> 281008.88 | L34: =L33*(1+ASSUMPTIONS!$B$59)+J34+MAX(K34,0)*0.2 -> 4661442.4 | M34: CS / Tech Job | N34: =ASSUMPTIONS!$C$47*(1+ASSUMPTIONS!$B$51)^27 -> 504589.5 | O34: =ASSUMPTIONS!$C$33*(1+ASSUMPTIONS!$C$34)^27*12 -> 13973.463 | P34: =MAX((N34-O34)*(ASSUMPTIONS!$C$65+ASSUMPTIONS!$C$67),0) -> 142278.65 | Q34: =ASSUMPTIONS!$C$28*(1+ASSUMPTIONS!$C$29)^27 -> 23964.184 | R34: =ASSUMPTIONS!$B$70*12*(1+ASSUMPTIONS!$B$71)^29 -> 67694.324 | S34: =ASSUMPTIONS!$C$61*12 -> 6000 | T34: =N34+O34-P34-Q34-R34-S34 -> 278625.8 | U34: =U33*(1+ASSUMPTIONS!$C$59)+S34+MAX(T34,0)*0.2 -> 4653539 | V34: Research Scientist | W34: =ASSUMPTIONS!$D$48*(1+ASSUMPTIONS!$B$51)^21 -> 524116.66 | X34: =ASSUMPTIONS!$D$33*(1+ASSUMPTIONS!$D$34)^27*12 -> 13973.463 | Y34: =MAX((W34-X34)*(ASSUMPTIONS!$D$66+ASSUMPTIONS!$D$67),0) -> 158144.39 | Z34: =ASSUMPTIONS!$D$28*(1+ASSUMPTIONS!$D$29)^27 -> 0 | AA34: =ASSUMPTIONS!$B$70*12*(1+ASSUMPTIONS!$B$71)^29 -> 67694.324 | AB34: =ASSUMPTIONS!$D$61*12 -> 6000 | AC34: =W34+X34-Y34-Z34-AA34-AB34 -> 306251.41 | AD34: =AD33*(1+ASSUMPTIONS!$D$59)+AB34+MAX(AC34,0)*0.2 -> 4321031.5 | AE34: =(E34+F34)-(N34+O34) -> -14648.344 | AF34: =(E34+F34)-(W34+X34) -> -34175.499 | AG34: =L34-U34 -> 7903.3986 | AH34: =L34-AD34 -> 340410.95
A35: 30 | B35: 2056 | C35: 66 | D35: Research Scientist | E35: =ASSUMPTIONS!$B$21*(1+ASSUMPTIONS!$B$23)^22*12+ASSUMPTIONS!$B$48*(1+ASSUMPTIONS!$B$51)^16 -> 510823.49 | F35: =ASSUMPTIONS!$B$33*(1+ASSUMPTIONS!$B$34)^22*12 -> 12171.342 | G35: =MAX((E35-F35)*(ASSUMPTIONS!$B$66+ASSUMPTIONS!$B$67),0) -> 154582.17 | H35: =ASSUMPTIONS!$B$26*(1+ASSUMPTIONS!$B$27)^22 -> 348.73082 | I35: =ASSUMPTIONS!$B$70*12*(1+ASSUMPTIONS!$B$71)^30 -> 69725.153 | J35: =ASSUMPTIONS!$B$61*12 -> 6000 | K35: =E35+F35-G35-H35-I35-J35 -> 292338.78 | L35: =L34*(1+ASSUMPTIONS!$B$59)+J35+MAX(K35,0)*0.2 -> 5052211.2 | M35: CS / Tech Job | N35: =ASSUMPTIONS!$C$47*(1+ASSUMPTIONS!$B$51)^28 -> 524773.08 | O35: =ASSUMPTIONS!$C$33*(1+ASSUMPTIONS!$C$34)^28*12 -> 14364.72 | P35: =MAX((N35-O35)*(ASSUMPTIONS!$C$65+ASSUMPTIONS!$C$67),0) -> 148018.42 | Q35: =ASSUMPTIONS!$C$28*(1+ASSUMPTIONS!$C$29)^28 -> 25881.319 | R35: =ASSUMPTIONS!$B$70*12*(1+ASSUMPTIONS!$B$71)^30 -> 69725.153 | S35: =ASSUMPTIONS!$C$61*12 -> 6000 | T35: =N35+O35-P35-Q35-R35-S35 -> 289512.9 | U35: =U34*(1+ASSUMPTIONS!$C$59)+S35+MAX(T35,0)*0.2 -> 5043189.4 | V35: Research Scientist | W35: =ASSUMPTIONS!$D$48*(1+ASSUMPTIONS!$B$51)^22 -> 545081.32 | X35: =ASSUMPTIONS!$D$33*(1+ASSUMPTIONS!$D$34)^28*12 -> 14364.72 | Y35: =MAX((W35-X35)*(ASSUMPTIONS!$D$66+ASSUMPTIONS!$D$67),0) -> 164522.15 | Z35: =ASSUMPTIONS!$D$28*(1+ASSUMPTIONS!$D$29)^28 -> 0 | AA35: =ASSUMPTIONS!$B$70*12*(1+ASSUMPTIONS!$B$71)^30 -> 69725.153 | AB35: =ASSUMPTIONS!$D$61*12 -> 6000 | AC35: =W35+X35-Y35-Z35-AA35-AB35 -> 319198.74 | AD35: =AD34*(1+ASSUMPTIONS!$D$59)+AB35+MAX(AC35,0)*0.2 -> 4693343.4 | AE35: =(E35+F35)-(N35+O35) -> -16142.968 | AF35: =(E35+F35)-(W35+X35) -> -36451.209 | AG35: =L35-U35 -> 9021.8124 | AH35: =L35-AD35 -> 358867.73 | AI35: ◀ Age 66 — Standard Retirement / Social Security
A36: 31 | B36: 2057 | C36: 67 | D36: Research Scientist | E36: =ASSUMPTIONS!$B$21*(1+ASSUMPTIONS!$B$23)^23*12+ASSUMPTIONS!$B$48*(1+ASSUMPTIONS!$B$51)^17 -> 530295.98 | F36: =ASSUMPTIONS!$B$33*(1+ASSUMPTIONS!$B$34)^23*12 -> 12512.14 | G36: =MAX((E36-F36)*(ASSUMPTIONS!$B$66+ASSUMPTIONS!$B$67),0) -> 160512.99 | H36: =ASSUMPTIONS!$B$26*(1+ASSUMPTIONS!$B$27)^23 -> 359.19275 | I36: =ASSUMPTIONS!$B$70*12*(1+ASSUMPTIONS!$B$71)^31 -> 71816.908 | J36: =ASSUMPTIONS!$B$61*12 -> 6000 | K36: =E36+F36-G36-H36-I36-J36 -> 304119.03 | L36: =L35*(1+ASSUMPTIONS!$B$59)+J36+MAX(K36,0)*0.2 -> 5472689.8 | M36: CS / Tech Job | N36: =ASSUMPTIONS!$C$47*(1+ASSUMPTIONS!$B$51)^29 -> 545764 | O36: =ASSUMPTIONS!$C$33*(1+ASSUMPTIONS!$C$34)^29*12 -> 14766.932 | P36: =MAX((N36-O36)*(ASSUMPTIONS!$C$65+ASSUMPTIONS!$C$67),0) -> 153989.15 | Q36: =ASSUMPTIONS!$C$28*(1+ASSUMPTIONS!$C$29)^29 -> 27951.825 | R36: =ASSUMPTIONS!$B$70*12*(1+ASSUMPTIONS!$B$71)^31 -> 71816.908 | S36: =ASSUMPTIONS!$C$61*12 -> 6000 | T36: =N36+O36-P36-Q36-R36-S36 -> 300773.05 | U36: =U35*(1+ASSUMPTIONS!$C$59)+S36+MAX(T36,0)*0.2 -> 5462367.2 | V36: Research Scientist | W36: =ASSUMPTIONS!$D$48*(1+ASSUMPTIONS!$B$51)^23 -> 566884.57 | X36: =ASSUMPTIONS!$D$33*(1+ASSUMPTIONS!$D$34)^29*12 -> 14766.932 | Y36: =MAX((W36-X36)*(ASSUMPTIONS!$D$66+ASSUMPTIONS!$D$67),0) -> 171156.47 | Z36: =ASSUMPTIONS!$D$28*(1+ASSUMPTIONS!$D$29)^29 -> 0 | AA36: =ASSUMPTIONS!$B$70*12*(1+ASSUMPTIONS!$B$71)^31 -> 71816.908 | AB36: =ASSUMPTIONS!$D$61*12 -> 6000 | AC36: =W36+X36-Y36-Z36-AA36-AB36 -> 332678.13 | AD36: =AD35*(1+ASSUMPTIONS!$D$59)+AB36+MAX(AC36,0)*0.2 -> 5094413.1 | AE36: =(E36+F36)-(N36+O36) -> -17722.819 | AF36: =(E36+F36)-(W36+X36) -> -38843.39 | AG36: =L36-U36 -> 10322.534 | AH36: =L36-AD36 -> 378276.65
A37: 32 | B37: 2058 | C37: 68 | D37: Research Scientist | E37: =ASSUMPTIONS!$B$21*(1+ASSUMPTIONS!$B$23)^24*12+ASSUMPTIONS!$B$48*(1+ASSUMPTIONS!$B$51)^18 -> 550520.47 | F37: =ASSUMPTIONS!$B$33*(1+ASSUMPTIONS!$B$34)^24*12 -> 12862.48 | G37: =MAX((E37-F37)*(ASSUMPTIONS!$B$66+ASSUMPTIONS!$B$67),0) -> 166673.98 | H37: =ASSUMPTIONS!$B$26*(1+ASSUMPTIONS!$B$27)^24 -> 369.96853 | I37: =ASSUMPTIONS!$B$70*12*(1+ASSUMPTIONS!$B$71)^32 -> 73971.415 | J37: =ASSUMPTIONS!$B$61*12 -> 6000 | K37: =E37+F37-G37-H37-I37-J37 -> 316367.59 | L37: =L36*(1+ASSUMPTIONS!$B$59)+J37+MAX(K37,0)*0.2 -> 5925051.6 | M37: CS / Tech Job | N37: =ASSUMPTIONS!$C$47*(1+ASSUMPTIONS!$B$51)^30 -> 567594.56 | O37: =ASSUMPTIONS!$C$33*(1+ASSUMPTIONS!$C$34)^30*12 -> 15180.406 | P37: =MAX((N37-O37)*(ASSUMPTIONS!$C$65+ASSUMPTIONS!$C$67),0) -> 160200.11 | Q37: =ASSUMPTIONS!$C$28*(1+ASSUMPTIONS!$C$29)^30 -> 30187.971 | R37: =ASSUMPTIONS!$B$70*12*(1+ASSUMPTIONS!$B$71)^32 -> 73971.415 | S37: =ASSUMPTIONS!$C$61*12 -> 6000 | T37: =N37+O37-P37-Q37-R37-S37 -> 312415.48 | U37: =U36*(1+ASSUMPTIONS!$C$59)+S37+MAX(T37,0)*0.2 -> 5913216 | V37: Research Scientist | W37: =ASSUMPTIONS!$D$48*(1+ASSUMPTIONS!$B$51)^24 -> 589559.96 | X37: =ASSUMPTIONS!$D$33*(1+ASSUMPTIONS!$D$34)^30*12 -> 15180.406 | Y37: =MAX((W37-X37)*(ASSUMPTIONS!$D$66+ASSUMPTIONS!$D$67),0) -> 178057.66 | Z37: =ASSUMPTIONS!$D$28*(1+ASSUMPTIONS!$D$29)^30 -> 0 | AA37: =ASSUMPTIONS!$B$70*12*(1+ASSUMPTIONS!$B$71)^32 -> 73971.415 | AB37: =ASSUMPTIONS!$D$61*12 -> 6000 | AC37: =W37+X37-Y37-Z37-AA37-AB37 -> 346711.29 | AD37: =AD36*(1+ASSUMPTIONS!$D$59)+AB37+MAX(AC37,0)*0.2 -> 5526364.3 | AE37: =(E37+F37)-(N37+O37) -> -19392.021 | AF37: =(E37+F37)-(W37+X37) -> -41357.415 | AG37: =L37-U37 -> 11835.533 | AH37: =L37-AD37 -> 398687.27
A38: 33 | B38: 2059 | C38: 69 | D38: Research Scientist | E38: =ASSUMPTIONS!$B$21*(1+ASSUMPTIONS!$B$23)^25*12+ASSUMPTIONS!$B$48*(1+ASSUMPTIONS!$B$51)^19 -> 571526.3 | F38: =ASSUMPTIONS!$B$33*(1+ASSUMPTIONS!$B$34)^25*12 -> 13222.629 | G38: =MAX((E38-F38)*(ASSUMPTIONS!$B$66+ASSUMPTIONS!$B$67),0) -> 173074.14 | H38: =ASSUMPTIONS!$B$26*(1+ASSUMPTIONS!$B$27)^25 -> 381.06758 | I38: =ASSUMPTIONS!$B$70*12*(1+ASSUMPTIONS!$B$71)^33 -> 76190.558 | J38: =ASSUMPTIONS!$B$61*12 -> 6000 | K38: =E38+F38-G38-H38-I38-J38 -> 329103.16 | L38: =L37*(1+ASSUMPTIONS!$B$59)+J38+MAX(K38,0)*0.2 -> 6411625.8 | M38: CS / Tech Job | N38: =ASSUMPTIONS!$C$47*(1+ASSUMPTIONS!$B$51)^31 -> 590298.35 | O38: =ASSUMPTIONS!$C$33*(1+ASSUMPTIONS!$C$34)^31*12 -> 15605.457 | P38: =MAX((N38-O38)*(ASSUMPTIONS!$C$65+ASSUMPTIONS!$C$67),0) -> 166660.94 | Q38: =ASSUMPTIONS!$C$28*(1+ASSUMPTIONS!$C$29)^31 -> 32603.008 | R38: =ASSUMPTIONS!$B$70*12*(1+ASSUMPTIONS!$B$71)^33 -> 76190.558 | S38: =ASSUMPTIONS!$C$61*12 -> 6000 | T38: =N38+O38-P38-Q38-R38-S38 -> 324449.3 | U38: =U37*(1+ASSUMPTIONS!$C$59)+S38+MAX(T38,0)*0.2 -> 6398031 | V38: Research Scientist | W38: =ASSUMPTIONS!$D$48*(1+ASSUMPTIONS!$B$51)^25 -> 613142.36 | X38: =ASSUMPTIONS!$D$33*(1+ASSUMPTIONS!$D$34)^31*12 -> 15605.457 | Y38: =MAX((W38-X38)*(ASSUMPTIONS!$D$66+ASSUMPTIONS!$D$67),0) -> 185236.44 | Z38: =ASSUMPTIONS!$D$28*(1+ASSUMPTIONS!$D$29)^31 -> 0 | AA38: =ASSUMPTIONS!$B$70*12*(1+ASSUMPTIONS!$B$71)^33 -> 76190.558 | AB38: =ASSUMPTIONS!$D$61*12 -> 6000 | AC38: =W38+X38-Y38-Z38-AA38-AB38 -> 361320.82 | AD38: =AD37*(1+ASSUMPTIONS!$D$59)+AB38+MAX(AC38,0)*0.2 -> 5991474 | AE38: =(E38+F38)-(N38+O38) -> -21154.879 | AF38: =(E38+F38)-(W38+X38) -> -43998.888 | AG38: =L38-U38 -> 13594.793 | AH38: =L38-AD38 -> 420151.85
A39: 34 | B39: 2060 | C39: 70 | D39: Research Scientist | E39: =ASSUMPTIONS!$B$21*(1+ASSUMPTIONS!$B$23)^26*12+ASSUMPTIONS!$B$48*(1+ASSUMPTIONS!$B$51)^20 -> 593343.94 | F39: =ASSUMPTIONS!$B$33*(1+ASSUMPTIONS!$B$34)^26*12 -> 13592.863 | G39: =MAX((E39-F39)*(ASSUMPTIONS!$B$66+ASSUMPTIONS!$B$67),0) -> 179722.83 | H39: =ASSUMPTIONS!$B$26*(1+ASSUMPTIONS!$B$27)^26 -> 392.49961 | I39: =ASSUMPTIONS!$B$70*12*(1+ASSUMPTIONS!$B$71)^34 -> 78476.274 | J39: =ASSUMPTIONS!$B$61*12 -> 6000 | K39: =E39+F39-G39-H39-I39-J39 -> 342345.19 | L39: =L38*(1+ASSUMPTIONS!$B$59)+J39+MAX(K39,0)*0.2 -> 6934908.6 | M39: CS / Tech Job | N39: =ASSUMPTIONS!$C$47*(1+ASSUMPTIONS!$B$51)^32 -> 613910.28 | O39: =ASSUMPTIONS!$C$33*(1+ASSUMPTIONS!$C$34)^32*12 -> 16042.41 | P39: =MAX((N39-O39)*(ASSUMPTIONS!$C$65+ASSUMPTIONS!$C$67),0) -> 173381.68 | Q39: =ASSUMPTIONS!$C$28*(1+ASSUMPTIONS!$C$29)^32 -> 35211.249 | R39: =ASSUMPTIONS!$B$70*12*(1+ASSUMPTIONS!$B$71)^34 -> 78476.274 | S39: =ASSUMPTIONS!$C$61*12 -> 6000 | T39: =N39+O39-P39-Q39-R39-S39 -> 336883.48 | U39: =U38*(1+ASSUMPTIONS!$C$59)+S39+MAX(T39,0)*0.2 -> 6919269.9 | V39: Research Scientist | W39: =ASSUMPTIONS!$D$48*(1+ASSUMPTIONS!$B$51)^26 -> 637668.05 | X39: =ASSUMPTIONS!$D$33*(1+ASSUMPTIONS!$D$34)^32*12 -> 16042.41 | Y39: =MAX((W39-X39)*(ASSUMPTIONS!$D$66+ASSUMPTIONS!$D$67),0) -> 192703.95 | Z39: =ASSUMPTIONS!$D$28*(1+ASSUMPTIONS!$D$29)^32 -> 0 | AA39: =ASSUMPTIONS!$B$70*12*(1+ASSUMPTIONS!$B$71)^34 -> 78476.274 | AB39: =ASSUMPTIONS!$D$61*12 -> 6000 | AC39: =W39+X39-Y39-Z39-AA39-AB39 -> 376530.24 | AD39: =AD38*(1+ASSUMPTIONS!$D$59)+AB39+MAX(AC39,0)*0.2 -> 6492183.2 | AE39: =(E39+F39)-(N39+O39) -> -23015.892 | AF39: =(E39+F39)-(W39+X39) -> -46773.662 | AG39: =L39-U39 -> 15638.77 | AH39: =L39-AD39 -> 442725.47
A40: 35 | B40: 2061 | C40: 71 | D40: Research Scientist | E40: =ASSUMPTIONS!$B$21*(1+ASSUMPTIONS!$B$23)^27*12+ASSUMPTIONS!$B$48*(1+ASSUMPTIONS!$B$51)^21 -> 616005.07 | F40: =ASSUMPTIONS!$B$33*(1+ASSUMPTIONS!$B$34)^27*12 -> 13973.463 | G40: =MAX((E40-F40)*(ASSUMPTIONS!$B$66+ASSUMPTIONS!$B$67),0) -> 186629.8 | H40: =ASSUMPTIONS!$B$26*(1+ASSUMPTIONS!$B$27)^27 -> 404.2746 | I40: =ASSUMPTIONS!$B$70*12*(1+ASSUMPTIONS!$B$71)^35 -> 80830.563 | J40: =ASSUMPTIONS!$B$61*12 -> 6000 | K40: =E40+F40-G40-H40-I40-J40 -> 356113.89 | L40: =L39*(1+ASSUMPTIONS!$B$59)+J40+MAX(K40,0)*0.2 -> 7497575 | M40: CS / Tech Job | N40: =ASSUMPTIONS!$C$47*(1+ASSUMPTIONS!$B$51)^33 -> 638466.69 | O40: =ASSUMPTIONS!$C$33*(1+ASSUMPTIONS!$C$34)^33*12 -> 16491.598 | P40: =MAX((N40-O40)*(ASSUMPTIONS!$C$65+ASSUMPTIONS!$C$67),0) -> 180372.78 | Q40: =ASSUMPTIONS!$C$28*(1+ASSUMPTIONS!$C$29)^33 -> 38028.149 | R40: =ASSUMPTIONS!$B$70*12*(1+ASSUMPTIONS!$B$71)^35 -> 80830.563 | S40: =ASSUMPTIONS!$C$61*12 -> 6000 | T40: =N40+O40-P40-Q40-R40-S40 -> 349726.8 | U40: =U39*(1+ASSUMPTIONS!$C$59)+S40+MAX(T40,0)*0.2 -> 7479564.1 | V40: Research Scientist | W40: =ASSUMPTIONS!$D$48*(1+ASSUMPTIONS!$B$51)^27 -> 663174.77 | X40: =ASSUMPTIONS!$D$33*(1+ASSUMPTIONS!$D$34)^33*12 -> 16491.598 | Y40: =MAX((W40-X40)*(ASSUMPTIONS!$D$66+ASSUMPTIONS!$D$67),0) -> 200471.78 | Z40: =ASSUMPTIONS!$D$28*(1+ASSUMPTIONS!$D$29)^33 -> 0 | AA40: =ASSUMPTIONS!$B$70*12*(1+ASSUMPTIONS!$B$71)^35 -> 80830.563 | AB40: =ASSUMPTIONS!$D$61*12 -> 6000 | AC40: =W40+X40-Y40-Z40-AA40-AB40 -> 392364.02 | AD40: =AD39*(1+ASSUMPTIONS!$D$59)+AB40+MAX(AC40,0)*0.2 -> 7031108.8 | AE40: =(E40+F40)-(N40+O40) -> -24979.76 | AF40: =(E40+F40)-(W40+X40) -> -49687.841 | AG40: =L40-U40 -> 18010.903 | AH40: =L40-AD40 -> 466466.23
A41: 36 | B41: 2062 | C41: 72 | D41: Research Scientist | E41: =ASSUMPTIONS!$B$21*(1+ASSUMPTIONS!$B$23)^28*12+ASSUMPTIONS!$B$48*(1+ASSUMPTIONS!$B$51)^22 -> 639542.61 | F41: =ASSUMPTIONS!$B$33*(1+ASSUMPTIONS!$B$34)^28*12 -> 14364.72 | G41: =MAX((E41-F41)*(ASSUMPTIONS!$B$66+ASSUMPTIONS!$B$67),0) -> 193805.15 | H41: =ASSUMPTIONS!$B$26*(1+ASSUMPTIONS!$B$27)^28 -> 416.40284 | I41: =ASSUMPTIONS!$B$70*12*(1+ASSUMPTIONS!$B$71)^36 -> 83255.48 | J41: =ASSUMPTIONS!$B$61*12 -> 6000 | K41: =E41+F41-G41-H41-I41-J41 -> 370430.3 | L41: =L40*(1+ASSUMPTIONS!$B$59)+J41+MAX(K41,0)*0.2 -> 8102491.3 | M41: CS / Tech Job | N41: =ASSUMPTIONS!$C$47*(1+ASSUMPTIONS!$B$51)^34 -> 664005.36 | O41: =ASSUMPTIONS!$C$33*(1+ASSUMPTIONS!$C$34)^34*12 -> 16953.362 | P41: =MAX((N41-O41)*(ASSUMPTIONS!$C$65+ASSUMPTIONS!$C$67),0) -> 187645.08 | Q41: =ASSUMPTIONS!$C$28*(1+ASSUMPTIONS!$C$29)^34 -> 41070.401 | R41: =ASSUMPTIONS!$B$70*12*(1+ASSUMPTIONS!$B$71)^36 -> 83255.48 | S41: =ASSUMPTIONS!$C$61*12 -> 6000 | T41: =N41+O41-P41-Q41-R41-S41 -> 362987.76 | U41: =U40*(1+ASSUMPTIONS!$C$59)+S41+MAX(T41,0)*0.2 -> 8081731.2 | V41: Research Scientist | W41: =ASSUMPTIONS!$D$48*(1+ASSUMPTIONS!$B$51)^28 -> 689701.76 | X41: =ASSUMPTIONS!$D$33*(1+ASSUMPTIONS!$D$34)^34*12 -> 16953.362 | Y41: =MAX((W41-X41)*(ASSUMPTIONS!$D$66+ASSUMPTIONS!$D$67),0) -> 208552 | Z41: =ASSUMPTIONS!$D$28*(1+ASSUMPTIONS!$D$29)^34 -> 0 | AA41: =ASSUMPTIONS!$B$70*12*(1+ASSUMPTIONS!$B$71)^36 -> 83255.48 | AB41: =ASSUMPTIONS!$D$61*12 -> 6000 | AC41: =W41+X41-Y41-Z41-AA41-AB41 -> 408847.64 | AD41: =AD40*(1+ASSUMPTIONS!$D$59)+AB41+MAX(AC41,0)*0.2 -> 7611055.9 | AE41: =(E41+F41)-(N41+O41) -> -27051.394 | AF41: =(E41+F41)-(W41+X41) -> -52747.798 | AG41: =L41-U41 -> 20760.174 | AH41: =L41-AD41 -> 491435.39
A42: 37 | B42: 2063 | C42: 73 | D42: Research Scientist | E42: =ASSUMPTIONS!$B$21*(1+ASSUMPTIONS!$B$23)^29*12+ASSUMPTIONS!$B$48*(1+ASSUMPTIONS!$B$51)^23 -> 663990.78 | F42: =ASSUMPTIONS!$B$33*(1+ASSUMPTIONS!$B$34)^29*12 -> 14766.932 | G42: =MAX((E42-F42)*(ASSUMPTIONS!$B$66+ASSUMPTIONS!$B$67),0) -> 201259.39 | H42: =ASSUMPTIONS!$B$26*(1+ASSUMPTIONS!$B$27)^29 -> 428.89492 | I42: =ASSUMPTIONS!$B$70*12*(1+ASSUMPTIONS!$B$71)^37 -> 85753.144 | J42: =ASSUMPTIONS!$B$61*12 -> 6000 | K42: =E42+F42-G42-H42-I42-J42 -> 385316.28 | L42: =L41*(1+ASSUMPTIONS!$B$59)+J42+MAX(K42,0)*0.2 -> 8752729 | M42: CS / Tech Job | N42: =ASSUMPTIONS!$C$47*(1+ASSUMPTIONS!$B$51)^35 -> 690565.57 | O42: =ASSUMPTIONS!$C$33*(1+ASSUMPTIONS!$C$34)^35*12 -> 17428.057 | P42: =MAX((N42-O42)*(ASSUMPTIONS!$C$65+ASSUMPTIONS!$C$67),0) -> 195209.88 | Q42: =ASSUMPTIONS!$C$28*(1+ASSUMPTIONS!$C$29)^35 -> 44356.033 | R42: =ASSUMPTIONS!$B$70*12*(1+ASSUMPTIONS!$B$71)^37 -> 85753.144 | S42: =ASSUMPTIONS!$C$61*12 -> 6000 | T42: =N42+O42-P42-Q42-R42-S42 -> 376674.57 | U42: =U41*(1+ASSUMPTIONS!$C$59)+S42+MAX(T42,0)*0.2 -> 8728787.3 | V42: Research Scientist | W42: =ASSUMPTIONS!$D$48*(1+ASSUMPTIONS!$B$51)^29 -> 717289.83 | X42: =ASSUMPTIONS!$D$33*(1+ASSUMPTIONS!$D$34)^35*12 -> 17428.057 | Y42: =MAX((W42-X42)*(ASSUMPTIONS!$D$66+ASSUMPTIONS!$D$67),0) -> 216957.15 | Z42: =ASSUMPTIONS!$D$28*(1+ASSUMPTIONS!$D$29)^35 -> 0 | AA42: =ASSUMPTIONS!$B$70*12*(1+ASSUMPTIONS!$B$71)^37 -> 85753.144 | AB42: =ASSUMPTIONS!$D$61*12 -> 6000 | AC42: =W42+X42-Y42-Z42-AA42-AB42 -> 426007.6 | AD42: =AD41*(1+ASSUMPTIONS!$D$59)+AB42+MAX(AC42,0)*0.2 -> 8235031.4 | AE42: =(E42+F42)-(N42+O42) -> -29235.922 | AF42: =(E42+F42)-(W42+X42) -> -55960.182 | AG42: =L42-U42 -> 23941.727 | AH42: =L42-AD42 -> 517697.61
A43: 38 | B43: 2064 | C43: 74 | D43: Research Scientist | E43: =ASSUMPTIONS!$B$21*(1+ASSUMPTIONS!$B$23)^30*12+ASSUMPTIONS!$B$48*(1+ASSUMPTIONS!$B$51)^24 -> 689385.13 | F43: =ASSUMPTIONS!$B$33*(1+ASSUMPTIONS!$B$34)^30*12 -> 15180.406 | G43: =MAX((E43-F43)*(ASSUMPTIONS!$B$66+ASSUMPTIONS!$B$67),0) -> 209003.47 | H43: =ASSUMPTIONS!$B$26*(1+ASSUMPTIONS!$B$27)^30 -> 441.76177 | I43: =ASSUMPTIONS!$B$70*12*(1+ASSUMPTIONS!$B$71)^38 -> 88325.738 | J43: =ASSUMPTIONS!$B$61*12 -> 6000 | K43: =E43+F43-G43-H43-I43-J43 -> 400794.57 | L43: =L42*(1+ASSUMPTIONS!$B$59)+J43+MAX(K43,0)*0.2 -> 9451578.9 | M43: CS / Tech Job | N43: =ASSUMPTIONS!$C$47*(1+ASSUMPTIONS!$B$51)^36 -> 718188.2 | O43: =ASSUMPTIONS!$C$33*(1+ASSUMPTIONS!$C$34)^36*12 -> 17916.042 | P43: =MAX((N43-O43)*(ASSUMPTIONS!$C$65+ASSUMPTIONS!$C$67),0) -> 203078.92 | Q43: =ASSUMPTIONS!$C$28*(1+ASSUMPTIONS!$C$29)^36 -> 47904.516 | R43: =ASSUMPTIONS!$B$70*12*(1+ASSUMPTIONS!$B$71)^38 -> 88325.738 | S43: =ASSUMPTIONS!$C$61*12 -> 6000 | T43: =N43+O43-P43-Q43-R43-S43 -> 390795.06 | U43: =U42*(1+ASSUMPTIONS!$C$59)+S43+MAX(T43,0)*0.2 -> 9423961.4 | V43: Research Scientist | W43: =ASSUMPTIONS!$D$48*(1+ASSUMPTIONS!$B$51)^30 -> 745981.43 | X43: =ASSUMPTIONS!$D$33*(1+ASSUMPTIONS!$D$34)^36*12 -> 17916.042 | Y43: =MAX((W43-X43)*(ASSUMPTIONS!$D$66+ASSUMPTIONS!$D$67),0) -> 225700.27 | Z43: =ASSUMPTIONS!$D$28*(1+ASSUMPTIONS!$D$29)^36 -> 0 | AA43: =ASSUMPTIONS!$B$70*12*(1+ASSUMPTIONS!$B$71)^38 -> 88325.738 | AB43: =ASSUMPTIONS!$D$61*12 -> 6000 | AC43: =W43+X43-Y43-Z43-AA43-AB43 -> 443871.46 | AD43: =AD42*(1+ASSUMPTIONS!$D$59)+AB43+MAX(AC43,0)*0.2 -> 8906257.9 | AE43: =(E43+F43)-(N43+O43) -> -31538.699 | AF43: =(E43+F43)-(W43+X43) -> -59331.93 | AG43: =L43-U43 -> 27617.551 | AH43: =L43-AD43 -> 545321.06
A44: 39 | B44: 2065 | C44: 75 | D44: Research Scientist | E44: =ASSUMPTIONS!$B$21*(1+ASSUMPTIONS!$B$23)^31*12+ASSUMPTIONS!$B$48*(1+ASSUMPTIONS!$B$51)^25 -> 715762.64 | F44: =ASSUMPTIONS!$B$33*(1+ASSUMPTIONS!$B$34)^31*12 -> 15605.457 | G44: =MAX((E44-F44)*(ASSUMPTIONS!$B$66+ASSUMPTIONS!$B$67),0) -> 217048.73 | H44: =ASSUMPTIONS!$B$26*(1+ASSUMPTIONS!$B$27)^31 -> 455.01462 | I44: =ASSUMPTIONS!$B$70*12*(1+ASSUMPTIONS!$B$71)^39 -> 90975.51 | J44: =ASSUMPTIONS!$B$61*12 -> 6000 | K44: =E44+F44-G44-H44-I44-J44 -> 416888.84 | L44: =L43*(1+ASSUMPTIONS!$B$59)+J44+MAX(K44,0)*0.2 -> 10202567 | M44: CS / Tech Job | N44: =ASSUMPTIONS!$C$47*(1+ASSUMPTIONS!$B$51)^37 -> 746915.72 | O44: =ASSUMPTIONS!$C$33*(1+ASSUMPTIONS!$C$34)^37*12 -> 18417.691 | P44: =MAX((N44-O44)*(ASSUMPTIONS!$C$65+ASSUMPTIONS!$C$67),0) -> 211264.43 | Q44: =ASSUMPTIONS!$C$28*(1+ASSUMPTIONS!$C$29)^37 -> 51736.877 | R44: =ASSUMPTIONS!$B$70*12*(1+ASSUMPTIONS!$B$71)^39 -> 90975.51 | S44: =ASSUMPTIONS!$C$61*12 -> 6000 | T44: =N44+O44-P44-Q44-R44-S44 -> 405356.6 | U44: =U43*(1+ASSUMPTIONS!$C$59)+S44+MAX(T44,0)*0.2 -> 10170710 | V44: Research Scientist | W44: =ASSUMPTIONS!$D$48*(1+ASSUMPTIONS!$B$51)^31 -> 775820.68 | X44: =ASSUMPTIONS!$D$33*(1+ASSUMPTIONS!$D$34)^37*12 -> 18417.691 | Y44: =MAX((W44-X44)*(ASSUMPTIONS!$D$66+ASSUMPTIONS!$D$67),0) -> 234794.93 | Z44: =ASSUMPTIONS!$D$28*(1+ASSUMPTIONS!$D$29)^37 -> 0 | AA44: =ASSUMPTIONS!$B$70*12*(1+ASSUMPTIONS!$B$71)^39 -> 90975.51 | AB44: =ASSUMPTIONS!$D$61*12 -> 6000 | AC44: =W44+X44-Y44-Z44-AA44-AB44 -> 462467.94 | AD44: =AD43*(1+ASSUMPTIONS!$D$59)+AB44+MAX(AC44,0)*0.2 -> 9628189.5 | AE44: =(E44+F44)-(N44+O44) -> -33965.322 | AF44: =(E44+F44)-(W44+X44) -> -62870.281 | AG44: =L44-U44 -> 31857.228 | AH44: =L44-AD44 -> 574377.72
A45: 40 | B45: 2066 | C45: 76 | D45: Research Scientist | E45: =ASSUMPTIONS!$B$21*(1+ASSUMPTIONS!$B$23)^32*12+ASSUMPTIONS!$B$48*(1+ASSUMPTIONS!$B$51)^26 -> 743161.7 | F45: =ASSUMPTIONS!$B$33*(1+ASSUMPTIONS!$B$34)^32*12 -> 16042.41 | G45: =MAX((E45-F45)*(ASSUMPTIONS!$B$66+ASSUMPTIONS!$B$67),0) -> 225406.98 | H45: =ASSUMPTIONS!$B$26*(1+ASSUMPTIONS!$B$27)^32 -> 468.66506 | I45: =ASSUMPTIONS!$B$70*12*(1+ASSUMPTIONS!$B$71)^40 -> 93704.776 | J45: =ASSUMPTIONS!$B$61*12 -> 6000 | K45: =E45+F45-G45-H45-I45-J45 -> 433623.69 | L45: =L44*(1+ASSUMPTIONS!$B$59)+J45+MAX(K45,0)*0.2 -> 11009472 | M45: CS / Tech Job | N45: =ASSUMPTIONS!$C$47*(1+ASSUMPTIONS!$B$51)^38 -> 776792.35 | O45: =ASSUMPTIONS!$C$33*(1+ASSUMPTIONS!$C$34)^38*12 -> 18933.387 | P45: =MAX((N45-O45)*(ASSUMPTIONS!$C$65+ASSUMPTIONS!$C$67),0) -> 219779.1 | Q45: =ASSUMPTIONS!$C$28*(1+ASSUMPTIONS!$C$29)^38 -> 55875.827 | R45: =ASSUMPTIONS!$B$70*12*(1+ASSUMPTIONS!$B$71)^40 -> 93704.776 | S45: =ASSUMPTIONS!$C$61*12 -> 6000 | T45: =N45+O45-P45-Q45-R45-S45 -> 420366.04 | U45: =U44*(1+ASSUMPTIONS!$C$59)+S45+MAX(T45,0)*0.2 -> 10972733 | V45: Research Scientist | W45: =ASSUMPTIONS!$D$48*(1+ASSUMPTIONS!$B$51)^32 -> 806853.51 | X45: =ASSUMPTIONS!$D$33*(1+ASSUMPTIONS!$D$34)^38*12 -> 18933.387 | Y45: =MAX((W45-X45)*(ASSUMPTIONS!$D$66+ASSUMPTIONS!$D$67),0) -> 244255.24 | Z45: =ASSUMPTIONS!$D$28*(1+ASSUMPTIONS!$D$29)^38 -> 0 | AA45: =ASSUMPTIONS!$B$70*12*(1+ASSUMPTIONS!$B$71)^40 -> 93704.776 | AB45: =ASSUMPTIONS!$D$61*12 -> 6000 | AC45: =W45+X45-Y45-Z45-AA45-AB45 -> 481826.88 | AD45: =AD44*(1+ASSUMPTIONS!$D$59)+AB45+MAX(AC45,0)*0.2 -> 10404528 | AE45: =(E45+F45)-(N45+O45) -> -36521.631 | AF45: =(E45+F45)-(W45+X45) -> -66582.789 | AG45: =L45-U45 -> 36738.764 | AH45: =L45-AD45 -> 604943.52 | AI45: ◀ Age 76 — Extended Horizon Marker
A46: 41 | B46: 2067 | C46: 77 | D46: Research Scientist | E46: =ASSUMPTIONS!$B$21*(1+ASSUMPTIONS!$B$23)^33*12+ASSUMPTIONS!$B$48*(1+ASSUMPTIONS!$B$51)^27 -> 771622.24 | F46: =ASSUMPTIONS!$B$33*(1+ASSUMPTIONS!$B$34)^33*12 -> 16491.598 | G46: =MAX((E46-F46)*(ASSUMPTIONS!$B$66+ASSUMPTIONS!$B$67),0) -> 234090.5 | H46: =ASSUMPTIONS!$B$26*(1+ASSUMPTIONS!$B$27)^33 -> 482.72501 | I46: =ASSUMPTIONS!$B$70*12*(1+ASSUMPTIONS!$B$71)^41 -> 96515.919 | J46: =ASSUMPTIONS!$B$61*12 -> 6000 | K46: =E46+F46-G46-H46-I46-J46 -> 451024.7 | L46: =L45*(1+ASSUMPTIONS!$B$59)+J46+MAX(K46,0)*0.2 -> 11876340 | M46: CS / Tech Job | N46: =ASSUMPTIONS!$C$47*(1+ASSUMPTIONS!$B$51)^39 -> 807864.05 | O46: =ASSUMPTIONS!$C$33*(1+ASSUMPTIONS!$C$34)^39*12 -> 19463.521 | P46: =MAX((N46-O46)*(ASSUMPTIONS!$C$65+ASSUMPTIONS!$C$67),0) -> 228636.15 | Q46: =ASSUMPTIONS!$C$28*(1+ASSUMPTIONS!$C$29)^39 -> 60345.893 | R46: =ASSUMPTIONS!$B$70*12*(1+ASSUMPTIONS!$B$71)^41 -> 96515.919 | S46: =ASSUMPTIONS!$C$61*12 -> 6000 | T46: =N46+O46-P46-Q46-R46-S46 -> 435829.6 | U46: =U45*(1+ASSUMPTIONS!$C$59)+S46+MAX(T46,0)*0.2 -> 11833990 | V46: Research Scientist | W46: =ASSUMPTIONS!$D$48*(1+ASSUMPTIONS!$B$51)^33 -> 839127.65 | X46: =ASSUMPTIONS!$D$33*(1+ASSUMPTIONS!$D$34)^39*12 -> 19463.521 | Y46: =MAX((W46-X46)*(ASSUMPTIONS!$D$66+ASSUMPTIONS!$D$67),0) -> 254095.88 | Z46: =ASSUMPTIONS!$D$28*(1+ASSUMPTIONS!$D$29)^39 -> 0 | AA46: =ASSUMPTIONS!$B$70*12*(1+ASSUMPTIONS!$B$71)^41 -> 96515.919 | AB46: =ASSUMPTIONS!$D$61*12 -> 6000 | AC46: =W46+X46-Y46-Z46-AA46-AB46 -> 501979.37 | AD46: =AD45*(1+ASSUMPTIONS!$D$59)+AB46+MAX(AC46,0)*0.2 -> 11239241 | AE46: =(E46+F46)-(N46+O46) -> -39213.729 | AF46: =(E46+F46)-(W46+X46) -> -70477.333 | AG46: =L46-U46 -> 42349.496 | AH46: =L46-AD46 -> 637098.63
A47: 42 | B47: 2068 | C47: 78 | D47: Research Scientist | E47: =ASSUMPTIONS!$B$21*(1+ASSUMPTIONS!$B$23)^34*12+ASSUMPTIONS!$B$48*(1+ASSUMPTIONS!$B$51)^28 -> 801185.76 | F47: =ASSUMPTIONS!$B$33*(1+ASSUMPTIONS!$B$34)^34*12 -> 16953.362 | G47: =MAX((E47-F47)*(ASSUMPTIONS!$B$66+ASSUMPTIONS!$B$67),0) -> 243112.04 | H47: =ASSUMPTIONS!$B$26*(1+ASSUMPTIONS!$B$27)^34 -> 497.20676 | I47: =ASSUMPTIONS!$B$70*12*(1+ASSUMPTIONS!$B$71)^42 -> 99411.397 | J47: =ASSUMPTIONS!$B$61*12 -> 6000 | K47: =E47+F47-G47-H47-I47-J47 -> 469118.48 | L47: =L46*(1+ASSUMPTIONS!$B$59)+J47+MAX(K47,0)*0.2 -> 12807507 | M47: CS / Tech Job | N47: =ASSUMPTIONS!$C$47*(1+ASSUMPTIONS!$B$51)^40 -> 840178.61 | O47: =ASSUMPTIONS!$C$33*(1+ASSUMPTIONS!$C$34)^40*12 -> 20008.5 | P47: =MAX((N47-O47)*(ASSUMPTIONS!$C$65+ASSUMPTIONS!$C$67),0) -> 237849.33 | Q47: =ASSUMPTIONS!$C$28*(1+ASSUMPTIONS!$C$29)^40 -> 65173.564 | R47: =ASSUMPTIONS!$B$70*12*(1+ASSUMPTIONS!$B$71)^42 -> 99411.397 | S47: =ASSUMPTIONS!$C$61*12 -> 6000 | T47: =N47+O47-P47-Q47-R47-S47 -> 451752.82 | U47: =U46*(1+ASSUMPTIONS!$C$59)+S47+MAX(T47,0)*0.2 -> 12758720 | V47: Research Scientist | W47: =ASSUMPTIONS!$D$48*(1+ASSUMPTIONS!$B$51)^34 -> 872692.76 | X47: =ASSUMPTIONS!$D$33*(1+ASSUMPTIONS!$D$34)^40*12 -> 20008.5 | Y47: =MAX((W47-X47)*(ASSUMPTIONS!$D$66+ASSUMPTIONS!$D$67),0) -> 264332.12 | Z47: =ASSUMPTIONS!$D$28*(1+ASSUMPTIONS!$D$29)^40 -> 0 | AA47: =ASSUMPTIONS!$B$70*12*(1+ASSUMPTIONS!$B$71)^42 -> 99411.397 | AB47: =ASSUMPTIONS!$D$61*12 -> 6000 | AC47: =W47+X47-Y47-Z47-AA47-AB47 -> 522957.74 | AD47: =AD46*(1+ASSUMPTIONS!$D$59)+AB47+MAX(AC47,0)*0.2 -> 12136579 | AE47: =(E47+F47)-(N47+O47) -> -42047.984 | AF47: =(E47+F47)-(W47+X47) -> -74562.133 | AG47: =L47-U47 -> 48787.093 | AH47: =L47-AD47 -> 670927.68
A48: 43 | B48: 2069 | C48: 79 | D48: Research Scientist | E48: =ASSUMPTIONS!$B$21*(1+ASSUMPTIONS!$B$23)^35*12+ASSUMPTIONS!$B$48*(1+ASSUMPTIONS!$B$51)^29 -> 831895.39 | F48: =ASSUMPTIONS!$B$33*(1+ASSUMPTIONS!$B$34)^35*12 -> 17428.057 | G48: =MAX((E48-F48)*(ASSUMPTIONS!$B$66+ASSUMPTIONS!$B$67),0) -> 252484.87 | H48: =ASSUMPTIONS!$B$26*(1+ASSUMPTIONS!$B$27)^35 -> 512.12297 | I48: =ASSUMPTIONS!$B$70*12*(1+ASSUMPTIONS!$B$71)^43 -> 102393.74 | J48: =ASSUMPTIONS!$B$61*12 -> 6000 | K48: =E48+F48-G48-H48-I48-J48 -> 487932.71 | L48: =L47*(1+ASSUMPTIONS!$B$59)+J48+MAX(K48,0)*0.2 -> 13807619 | M48: CS / Tech Job | N48: =ASSUMPTIONS!$C$47*(1+ASSUMPTIONS!$B$51)^41 -> 873785.75 | O48: =ASSUMPTIONS!$C$33*(1+ASSUMPTIONS!$C$34)^41*12 -> 20568.738 | P48: =MAX((N48-O48)*(ASSUMPTIONS!$C$65+ASSUMPTIONS!$C$67),0) -> 247432.93 | Q48: =ASSUMPTIONS!$C$28*(1+ASSUMPTIONS!$C$29)^41 -> 70387.45 | R48: =ASSUMPTIONS!$B$70*12*(1+ASSUMPTIONS!$B$71)^43 -> 102393.74 | S48: =ASSUMPTIONS!$C$61*12 -> 6000 | T48: =N48+O48-P48-Q48-R48-S48 -> 468140.37 | U48: =U47*(1+ASSUMPTIONS!$C$59)+S48+MAX(T48,0)*0.2 -> 13751458 | V48: Research Scientist | W48: =ASSUMPTIONS!$D$48*(1+ASSUMPTIONS!$B$51)^35 -> 907600.47 | X48: =ASSUMPTIONS!$D$33*(1+ASSUMPTIONS!$D$34)^41*12 -> 20568.738 | Y48: =MAX((W48-X48)*(ASSUMPTIONS!$D$66+ASSUMPTIONS!$D$67),0) -> 274979.84 | Z48: =ASSUMPTIONS!$D$28*(1+ASSUMPTIONS!$D$29)^41 -> 0 | AA48: =ASSUMPTIONS!$B$70*12*(1+ASSUMPTIONS!$B$71)^43 -> 102393.74 | AB48: =ASSUMPTIONS!$D$61*12 -> 6000 | AC48: =W48+X48-Y48-Z48-AA48-AB48 -> 544795.63 | AD48: =AD47*(1+ASSUMPTIONS!$D$59)+AB48+MAX(AC48,0)*0.2 -> 13101099 | AE48: =(E48+F48)-(N48+O48) -> -45031.05 | AF48: =(E48+F48)-(W48+X48) -> -78845.764 | AG48: =L48-U48 -> 56160.657 | AH48: =L48-AD48 -> 706520.04
A49: 44 | B49: 2070 | C49: 80 | D49: Research Scientist | E49: =ASSUMPTIONS!$B$21*(1+ASSUMPTIONS!$B$23)^36*12+ASSUMPTIONS!$B$48*(1+ASSUMPTIONS!$B$51)^30 -> 863795.93 | F49: =ASSUMPTIONS!$B$33*(1+ASSUMPTIONS!$B$34)^36*12 -> 17916.042 | G49: =MAX((E49-F49)*(ASSUMPTIONS!$B$66+ASSUMPTIONS!$B$67),0) -> 262222.77 | H49: =ASSUMPTIONS!$B$26*(1+ASSUMPTIONS!$B$27)^36 -> 527.48666 | I49: =ASSUMPTIONS!$B$70*12*(1+ASSUMPTIONS!$B$71)^44 -> 105465.55 | J49: =ASSUMPTIONS!$B$61*12 -> 6000 | K49: =E49+F49-G49-H49-I49-J49 -> 507496.17 | L49: =L48*(1+ASSUMPTIONS!$B$59)+J49+MAX(K49,0)*0.2 -> 14881652 | M49: CS / Tech Job | N49: =ASSUMPTIONS!$C$47*(1+ASSUMPTIONS!$B$51)^42 -> 908737.18 | O49: =ASSUMPTIONS!$C$33*(1+ASSUMPTIONS!$C$34)^42*12 -> 21144.663 | P49: =MAX((N49-O49)*(ASSUMPTIONS!$C$65+ASSUMPTIONS!$C$67),0) -> 257401.83 | Q49: =ASSUMPTIONS!$C$28*(1+ASSUMPTIONS!$C$29)^42 -> 76018.446 | R49: =ASSUMPTIONS!$B$70*12*(1+ASSUMPTIONS!$B$71)^44 -> 105465.55 | S49: =ASSUMPTIONS!$C$61*12 -> 6000 | T49: =N49+O49-P49-Q49-R49-S49 -> 484996.02 | U49: =U48*(1+ASSUMPTIONS!$C$59)+S49+MAX(T49,0)*0.2 -> 14817060 | V49: Research Scientist | W49: =ASSUMPTIONS!$D$48*(1+ASSUMPTIONS!$B$51)^36 -> 943904.49 | X49: =ASSUMPTIONS!$D$33*(1+ASSUMPTIONS!$D$34)^42*12 -> 21144.663 | Y49: =MAX((W49-X49)*(ASSUMPTIONS!$D$66+ASSUMPTIONS!$D$67),0) -> 286055.55 | Z49: =ASSUMPTIONS!$D$28*(1+ASSUMPTIONS!$D$29)^42 -> 0 | AA49: =ASSUMPTIONS!$B$70*12*(1+ASSUMPTIONS!$B$71)^44 -> 105465.55 | AB49: =ASSUMPTIONS!$D$61*12 -> 6000 | AC49: =W49+X49-Y49-Z49-AA49-AB49 -> 567528.05 | AD49: =AD48*(1+ASSUMPTIONS!$D$59)+AB49+MAX(AC49,0)*0.2 -> 14137682 | AE49: =(E49+F49)-(N49+O49) -> -48169.87 | AF49: =(E49+F49)-(W49+X49) -> -83337.173 | AG49: =L49-U49 -> 64591.934 | AH49: =L49-AD49 -> 743970.06
A50: 45 | B50: 2071 | C50: 81 | D50: Research Scientist | E50: =ASSUMPTIONS!$B$21*(1+ASSUMPTIONS!$B$23)^37*12+ASSUMPTIONS!$B$48*(1+ASSUMPTIONS!$B$51)^31 -> 896934 | F50: =ASSUMPTIONS!$B$33*(1+ASSUMPTIONS!$B$34)^37*12 -> 18417.691 | G50: =MAX((E50-F50)*(ASSUMPTIONS!$B$66+ASSUMPTIONS!$B$67),0) -> 272340.06 | H50: =ASSUMPTIONS!$B$26*(1+ASSUMPTIONS!$B$27)^37 -> 543.31126 | I50: =ASSUMPTIONS!$B$70*12*(1+ASSUMPTIONS!$B$71)^45 -> 108629.52 | J50: =ASSUMPTIONS!$B$61*12 -> 6000 | K50: =E50+F50-G50-H50-I50-J50 -> 527838.81 | L50: =L49*(1+ASSUMPTIONS!$B$59)+J50+MAX(K50,0)*0.2 -> 16034935 | M50: CS / Tech Job | N50: =ASSUMPTIONS!$C$47*(1+ASSUMPTIONS!$B$51)^43 -> 945086.67 | O50: =ASSUMPTIONS!$C$33*(1+ASSUMPTIONS!$C$34)^43*12 -> 21736.713 | P50: =MAX((N50-O50)*(ASSUMPTIONS!$C$65+ASSUMPTIONS!$C$67),0) -> 267771.49 | Q50: =ASSUMPTIONS!$C$28*(1+ASSUMPTIONS!$C$29)^43 -> 82099.921 | R50: =ASSUMPTIONS!$B$70*12*(1+ASSUMPTIONS!$B$71)^45 -> 108629.52 | S50: =ASSUMPTIONS!$C$61*12 -> 6000 | T50: =N50+O50-P50-Q50-R50-S50 -> 502322.46 | U50: =U49*(1+ASSUMPTIONS!$C$59)+S50+MAX(T50,0)*0.2 -> 15960718 | V50: Research Scientist | W50: =ASSUMPTIONS!$D$48*(1+ASSUMPTIONS!$B$51)^37 -> 981660.67 | X50: =ASSUMPTIONS!$D$33*(1+ASSUMPTIONS!$D$34)^43*12 -> 21736.713 | Y50: =MAX((W50-X50)*(ASSUMPTIONS!$D$66+ASSUMPTIONS!$D$67),0) -> 297576.43 | Z50: =ASSUMPTIONS!$D$28*(1+ASSUMPTIONS!$D$29)^43 -> 0 | AA50: =ASSUMPTIONS!$B$70*12*(1+ASSUMPTIONS!$B$71)^45 -> 108629.52 | AB50: =ASSUMPTIONS!$D$61*12 -> 6000 | AC50: =W50+X50-Y50-Z50-AA50-AB50 -> 591191.44 | AD50: =AD49*(1+ASSUMPTIONS!$D$59)+AB50+MAX(AC50,0)*0.2 -> 15251558 | AE50: =(E50+F50)-(N50+O50) -> -51471.696 | AF50: =(E50+F50)-(W50+X50) -> -88045.691 | AG50: =L50-U50 -> 74216.639 | AH50: =L50-AD50 -> 783377.44
A51: 46 | B51: 2072 | C51: 82 | D51: Research Scientist | E51: =ASSUMPTIONS!$B$21*(1+ASSUMPTIONS!$B$23)^38*12+ASSUMPTIONS!$B$48*(1+ASSUMPTIONS!$B$51)^32 -> 931358 | F51: =ASSUMPTIONS!$B$33*(1+ASSUMPTIONS!$B$34)^38*12 -> 18933.387 | G51: =MAX((E51-F51)*(ASSUMPTIONS!$B$66+ASSUMPTIONS!$B$67),0) -> 282851.63 | H51: =ASSUMPTIONS!$B$26*(1+ASSUMPTIONS!$B$27)^38 -> 559.61059 | I51: =ASSUMPTIONS!$B$70*12*(1+ASSUMPTIONS!$B$71)^46 -> 111888.4 | J51: =ASSUMPTIONS!$B$61*12 -> 6000 | K51: =E51+F51-G51-H51-I51-J51 -> 548991.74 | L51: =L50*(1+ASSUMPTIONS!$B$59)+J51+MAX(K51,0)*0.2 -> 17273179 | M51: CS / Tech Job | N51: =ASSUMPTIONS!$C$47*(1+ASSUMPTIONS!$B$51)^44 -> 982890.14 | O51: =ASSUMPTIONS!$C$33*(1+ASSUMPTIONS!$C$34)^44*12 -> 22345.341 | P51: =MAX((N51-O51)*(ASSUMPTIONS!$C$65+ASSUMPTIONS!$C$67),0) -> 278557.99 | Q51: =ASSUMPTIONS!$C$28*(1+ASSUMPTIONS!$C$29)^44 -> 88667.915 | R51: =ASSUMPTIONS!$B$70*12*(1+ASSUMPTIONS!$B$71)^46 -> 111888.4 | S51: =ASSUMPTIONS!$C$61*12 -> 6000 | T51: =N51+O51-P51-Q51-R51-S51 -> 520121.17 | U51: =U50*(1+ASSUMPTIONS!$C$59)+S51+MAX(T51,0)*0.2 -> 17187993 | V51: Research Scientist | W51: =ASSUMPTIONS!$D$48*(1+ASSUMPTIONS!$B$51)^38 -> 1020927.1 | X51: =ASSUMPTIONS!$D$33*(1+ASSUMPTIONS!$D$34)^44*12 -> 22345.341 | Y51: =MAX((W51-X51)*(ASSUMPTIONS!$D$66+ASSUMPTIONS!$D$67),0) -> 309560.34 | Z51: =ASSUMPTIONS!$D$28*(1+ASSUMPTIONS!$D$29)^44 -> 0 | AA51: =ASSUMPTIONS!$B$70*12*(1+ASSUMPTIONS!$B$71)^46 -> 111888.4 | AB51: =ASSUMPTIONS!$D$61*12 -> 6000 | AC51: =W51+X51-Y51-Z51-AA51-AB51 -> 615823.69 | AD51: =AD50*(1+ASSUMPTIONS!$D$59)+AB51+MAX(AC51,0)*0.2 -> 16448331 | AE51: =(E51+F51)-(N51+O51) -> -54944.095 | AF51: =(E51+F51)-(W51+X51) -> -92981.05 | AG51: =L51-U51 -> 85185.918 | AH51: =L51-AD51 -> 824847.47
A52: 47 | B52: 2073 | C52: 83 | D52: Research Scientist | E52: =ASSUMPTIONS!$B$21*(1+ASSUMPTIONS!$B$23)^39*12+ASSUMPTIONS!$B$48*(1+ASSUMPTIONS!$B$51)^33 -> 967118.26 | F52: =ASSUMPTIONS!$B$33*(1+ASSUMPTIONS!$B$34)^39*12 -> 19463.521 | G52: =MAX((E52-F52)*(ASSUMPTIONS!$B$66+ASSUMPTIONS!$B$67),0) -> 293772.97 | H52: =ASSUMPTIONS!$B$26*(1+ASSUMPTIONS!$B$27)^39 -> 576.39891 | I52: =ASSUMPTIONS!$B$70*12*(1+ASSUMPTIONS!$B$71)^47 -> 115245.05 | J52: =ASSUMPTIONS!$B$61*12 -> 6000 | K52: =E52+F52-G52-H52-I52-J52 -> 570987.36 | L52: =L51*(1+ASSUMPTIONS!$B$59)+J52+MAX(K52,0)*0.2 -> 18602499 | M52: CS / Tech Job | N52: =ASSUMPTIONS!$C$47*(1+ASSUMPTIONS!$B$51)^45 -> 1022205.7 | O52: =ASSUMPTIONS!$C$33*(1+ASSUMPTIONS!$C$34)^45*12 -> 22971.011 | P52: =MAX((N52-O52)*(ASSUMPTIONS!$C$65+ASSUMPTIONS!$C$67),0) -> 289778.07 | Q52: =ASSUMPTIONS!$C$28*(1+ASSUMPTIONS!$C$29)^45 -> 95761.348 | R52: =ASSUMPTIONS!$B$70*12*(1+ASSUMPTIONS!$B$71)^47 -> 115245.05 | S52: =ASSUMPTIONS!$C$61*12 -> 6000 | T52: =N52+O52-P52-Q52-R52-S52 -> 538392.28 | U52: =U51*(1+ASSUMPTIONS!$C$59)+S52+MAX(T52,0)*0.2 -> 18504831 | V52: Research Scientist | W52: =ASSUMPTIONS!$D$48*(1+ASSUMPTIONS!$B$51)^39 -> 1061764.2 | X52: =ASSUMPTIONS!$D$33*(1+ASSUMPTIONS!$D$34)^45*12 -> 22971.011 | Y52: =MAX((W52-X52)*(ASSUMPTIONS!$D$66+ASSUMPTIONS!$D$67),0) -> 322025.88 | Z52: =ASSUMPTIONS!$D$28*(1+ASSUMPTIONS!$D$29)^45 -> 0 | AA52: =ASSUMPTIONS!$B$70*12*(1+ASSUMPTIONS!$B$71)^47 -> 115245.05 | AB52: =ASSUMPTIONS!$D$61*12 -> 6000 | AC52: =W52+X52-Y52-Z52-AA52-AB52 -> 641464.25 | AD52: =AD51*(1+ASSUMPTIONS!$D$59)+AB52+MAX(AC52,0)*0.2 -> 17734007 | AE52: =(E52+F52)-(N52+O52) -> -58594.969 | AF52: =(E52+F52)-(W52+X52) -> -98153.402 | AG52: =L52-U52 -> 97667.949 | AH52: =L52-AD52 -> 868491.42
A53: 48 | B53: 2074 | C53: 84 | D53: Research Scientist | E53: =ASSUMPTIONS!$B$21*(1+ASSUMPTIONS!$B$23)^40*12+ASSUMPTIONS!$B$48*(1+ASSUMPTIONS!$B$51)^34 -> 1004267.1 | F53: =ASSUMPTIONS!$B$33*(1+ASSUMPTIONS!$B$34)^40*12 -> 20008.5 | G53: =MAX((E53-F53)*(ASSUMPTIONS!$B$66+ASSUMPTIONS!$B$67),0) -> 305120.17 | H53: =ASSUMPTIONS!$B$26*(1+ASSUMPTIONS!$B$27)^40 -> 593.69088 | I53: =ASSUMPTIONS!$B$70*12*(1+ASSUMPTIONS!$B$71)^48 -> 118702.41 | J53: =ASSUMPTIONS!$B$61*12 -> 6000 | K53: =E53+F53-G53-H53-I53-J53 -> 593859.34 | L53: =L52*(1+ASSUMPTIONS!$B$59)+J53+MAX(K53,0)*0.2 -> 20029446 | M53: CS / Tech Job | N53: =ASSUMPTIONS!$C$47*(1+ASSUMPTIONS!$B$51)^46 -> 1063094 | O53: =ASSUMPTIONS!$C$33*(1+ASSUMPTIONS!$C$34)^46*12 -> 23614.199 | P53: =MAX((N53-O53)*(ASSUMPTIONS!$C$65+ASSUMPTIONS!$C$67),0) -> 301449.13 | Q53: =ASSUMPTIONS!$C$28*(1+ASSUMPTIONS!$C$29)^46 -> 103422.26 | R53: =ASSUMPTIONS!$B$70*12*(1+ASSUMPTIONS!$B$71)^48 -> 118702.41 | S53: =ASSUMPTIONS!$C$61*12 -> 6000 | T53: =N53+O53-P53-Q53-R53-S53 -> 557134.38 | U53: =U52*(1+ASSUMPTIONS!$C$59)+S53+MAX(T53,0)*0.2 -> 19917596 | V53: Research Scientist | W53: =ASSUMPTIONS!$D$48*(1+ASSUMPTIONS!$B$51)^40 -> 1104234.7 | X53: =ASSUMPTIONS!$D$33*(1+ASSUMPTIONS!$D$34)^46*12 -> 23614.199 | Y53: =MAX((W53-X53)*(ASSUMPTIONS!$D$66+ASSUMPTIONS!$D$67),0) -> 334992.37 | Z53: =ASSUMPTIONS!$D$28*(1+ASSUMPTIONS!$D$29)^46 -> 0 | AA53: =ASSUMPTIONS!$B$70*12*(1+ASSUMPTIONS!$B$71)^48 -> 118702.41 | AB53: =ASSUMPTIONS!$D$61*12 -> 6000 | AC53: =W53+X53-Y53-Z53-AA53-AB53 -> 668154.17 | AD53: =AD52*(1+ASSUMPTIONS!$D$59)+AB53+MAX(AC53,0)*0.2 -> 19115019 | AE53: =(E53+F53)-(N53+O53) -> -62432.566 | AF53: =(E53+F53)-(W53+X53) -> -103573.34 | AG53: =L53-U53 -> 111849.7 | AH53: =L53-AD53 -> 914426.85
A54: 49 | B54: 2075 | C54: 85 | D54: Research Scientist | E54: =ASSUMPTIONS!$B$21*(1+ASSUMPTIONS!$B$23)^41*12+ASSUMPTIONS!$B$48*(1+ASSUMPTIONS!$B$51)^35 -> 1042858.9 | F54: =ASSUMPTIONS!$B$33*(1+ASSUMPTIONS!$B$34)^41*12 -> 20568.738 | G54: =MAX((E54-F54)*(ASSUMPTIONS!$B$66+ASSUMPTIONS!$B$67),0) -> 316909.95 | H54: =ASSUMPTIONS!$B$26*(1+ASSUMPTIONS!$B$27)^41 -> 611.5016 | I54: =ASSUMPTIONS!$B$70*12*(1+ASSUMPTIONS!$B$71)^49 -> 122263.48 | J54: =ASSUMPTIONS!$B$61*12 -> 6000 | K54: =E54+F54-G54-H54-I54-J54 -> 617642.71 | L54: =L53*(1+ASSUMPTIONS!$B$59)+J54+MAX(K54,0)*0.2 -> 21561035 | M54: CS / Tech Job | N54: =ASSUMPTIONS!$C$47*(1+ASSUMPTIONS!$B$51)^47 -> 1105617.7 | O54: =ASSUMPTIONS!$C$33*(1+ASSUMPTIONS!$C$34)^47*12 -> 24275.397 | P54: =MAX((N54-O54)*(ASSUMPTIONS!$C$65+ASSUMPTIONS!$C$67),0) -> 313589.28 | Q54: =ASSUMPTIONS!$C$28*(1+ASSUMPTIONS!$C$29)^47 -> 111696.04 | R54: =ASSUMPTIONS!$B$70*12*(1+ASSUMPTIONS!$B$71)^49 -> 122263.48 | S54: =ASSUMPTIONS!$C$61*12 -> 6000 | T54: =N54+O54-P54-Q54-R54-S54 -> 576344.34 | U54: =U53*(1+ASSUMPTIONS!$C$59)+S54+MAX(T54,0)*0.2 -> 21433097 | V54: Research Scientist | W54: =ASSUMPTIONS!$D$48*(1+ASSUMPTIONS!$B$51)^41 -> 1148404.1 | X54: =ASSUMPTIONS!$D$33*(1+ASSUMPTIONS!$D$34)^47*12 -> 24275.397 | Y54: =MAX((W54-X54)*(ASSUMPTIONS!$D$66+ASSUMPTIONS!$D$67),0) -> 348479.91 | Z54: =ASSUMPTIONS!$D$28*(1+ASSUMPTIONS!$D$29)^47 -> 0 | AA54: =ASSUMPTIONS!$B$70*12*(1+ASSUMPTIONS!$B$71)^49 -> 122263.48 | AB54: =ASSUMPTIONS!$D$61*12 -> 6000 | AC54: =W54+X54-Y54-Z54-AA54-AB54 -> 695936.14 | AD54: =AD53*(1+ASSUMPTIONS!$D$59)+AB54+MAX(AC54,0)*0.2 -> 20598257 | AE54: =(E54+F54)-(N54+O54) -> -66465.492 | AF54: =(E54+F54)-(W54+X54) -> -109251.89 | AG54: =L54-U54 -> 127938.85 | AH54: =L54-AD54 -> 962778.04
A55: 50 | B55: 2076 | C55: 86 | D55: Research Scientist | E55: =ASSUMPTIONS!$B$21*(1+ASSUMPTIONS!$B$23)^42*12+ASSUMPTIONS!$B$48*(1+ASSUMPTIONS!$B$51)^36 -> 1082950.2 | F55: =ASSUMPTIONS!$B$33*(1+ASSUMPTIONS!$B$34)^42*12 -> 21144.663 | G55: =MAX((E55-F55)*(ASSUMPTIONS!$B$66+ASSUMPTIONS!$B$67),0) -> 329159.7 | H55: =ASSUMPTIONS!$B$26*(1+ASSUMPTIONS!$B$27)^42 -> 629.84665 | I55: =ASSUMPTIONS!$B$70*12*(1+ASSUMPTIONS!$B$71)^50 -> 125931.38 | J55: =ASSUMPTIONS!$B$61*12 -> 6000 | K55: =E55+F55-G55-H55-I55-J55 -> 642373.89 | L55: =L54*(1+ASSUMPTIONS!$B$59)+J55+MAX(K55,0)*0.2 -> 23204783 | M55: CS / Tech Job | N55: =ASSUMPTIONS!$C$47*(1+ASSUMPTIONS!$B$51)^48 -> 1149842.4 | O55: =ASSUMPTIONS!$C$33*(1+ASSUMPTIONS!$C$34)^48*12 -> 24955.108 | P55: =MAX((N55-O55)*(ASSUMPTIONS!$C$65+ASSUMPTIONS!$C$67),0) -> 326217.33 | Q55: =ASSUMPTIONS!$C$28*(1+ASSUMPTIONS!$C$29)^48 -> 120631.72 | R55: =ASSUMPTIONS!$B$70*12*(1+ASSUMPTIONS!$B$71)^50 -> 125931.38 | S55: =ASSUMPTIONS!$C$61*12 -> 6000 | T55: =N55+O55-P55-Q55-R55-S55 -> 596017.12 | U55: =U54*(1+ASSUMPTIONS!$C$59)+S55+MAX(T55,0)*0.2 -> 23058617 | V55: Research Scientist | W55: =ASSUMPTIONS!$D$48*(1+ASSUMPTIONS!$B$51)^42 -> 1194340.3 | X55: =ASSUMPTIONS!$D$33*(1+ASSUMPTIONS!$D$34)^48*12 -> 24955.108 | Y55: =MAX((W55-X55)*(ASSUMPTIONS!$D$66+ASSUMPTIONS!$D$67),0) -> 362509.41 | Z55: =ASSUMPTIONS!$D$28*(1+ASSUMPTIONS!$D$29)^48 -> 0 | AA55: =ASSUMPTIONS!$B$70*12*(1+ASSUMPTIONS!$B$71)^50 -> 125931.38 | AB55: =ASSUMPTIONS!$D$61*12 -> 6000 | AC55: =W55+X55-Y55-Z55-AA55-AB55 -> 724854.62 | AD55: =AD54*(1+ASSUMPTIONS!$D$59)+AB55+MAX(AC55,0)*0.2 -> 22191106 | AE55: =(E55+F55)-(N55+O55) -> -70702.733 | AF55: =(E55+F55)-(W55+X55) -> -115200.59 | AG55: =L55-U55 -> 146165.92 | AH55: =L55-AD55 -> 1013676.4
A57: KEY RATES (auto-updates): | E57: ="Mil raise: "&TEXT(ASSUMPTIONS!$B$52,"0.0%") -> Mil raise: 2.5% | G57: ="Fed tax (mil): "&TEXT(ASSUMPTIONS!$B$64,"0.0%")&" + CA: "&TEXT(ASSUMPTIONS!$B$67,"0.0%") -> Fed tax (mil): 12.0% + CA: 7.0% | I57: ="Exp growth: "&TEXT(ASSUMPTIONS!$B$71,"0.0%")&"/yr" -> Exp growth: 3.0%/yr | L57: ="Return: "&TEXT(ASSUMPTIONS!$B$59,"0.0%")&"/yr | Start: "&TEXT(ASSUMPTIONS!$B$58,"$#,##0") -> Return: 7.0%/yr | Start: $183,000 | N57: ="CS growth: "&TEXT(ASSUMPTIONS!$B$51,"0.0%") -> CS growth: 4.0% | P57: ="Fed tax (civ): "&TEXT(ASSUMPTIONS!$C$65,"0.0%")&" + CA: "&TEXT(ASSUMPTIONS!$C$67,"0.0%") -> Fed tax (civ): 22.0% + CA: 7.0% | R57: ="Exp growth: "&TEXT(ASSUMPTIONS!$B$71,"0.0%")&"/yr" -> Exp growth: 3.0%/yr | U57: ="Return: "&TEXT(ASSUMPTIONS!$C$59,"0.0%")&"/yr" -> Return: 7.0%/yr | W57: ="Salary growth: "&TEXT(ASSUMPTIONS!$B$51,"0.0%") -> Salary growth: 4.0% | Y57: ="Fed tax (civ): "&TEXT(ASSUMPTIONS!$D$65,"0.0%")&" + CA: "&TEXT(ASSUMPTIONS!$D$67,"0.0%") -> Fed tax (civ): 22.0% + CA: 7.0% | AA57: ="Exp growth: "&TEXT(ASSUMPTIONS!$B$71,"0.0%")&"/yr" -> Exp growth: 3.0%/yr | AD57: ="Return: "&TEXT(ASSUMPTIONS!$D$59,"0.0%")&"/yr" -> Return: 7.0%/yr
A58: 50-YEAR TOTALS & KEY METRICS
A59: Total Gross Income (50 yrs) | E59: =SUM(E5:E55) -> 23189291 | N59: =SUM(N5:N55) -> 25656781 | W59: =SUM(W5:W55) -> 25673725
A60: Total Tax-Free Income | E60: =SUM(F5:F55) -> 1211803.8 | N60: =SUM(O5:O55) -> 757649.54 | W60: =SUM(X5:X55) -> 1062169.5
A61: Total Taxes Paid | E61: =SUM(G5:G55) -> 6763165.5 | N61: =SUM(P5:P55) -> 7214981.7 | W61: =SUM(Y5:Y55) -> 7680941
A62: Total Healthcare Costs | E62: =SUM(H5:H55) -> 15421.568 | N62: =SUM(Q5:Q55) -> 1591028.2 | W62: =SUM(Z5:Z55) -> 3000
A63: Final Portfolio Value (Year 50) | E63: =L55 -> 23204783 | N63: =U55 -> 23058617 | W63: =AD55 -> 22191106
A64: Lifetime Pension Value (Path A) | E64: =IF(ASSUMPTIONS!$B$23>0,ASSUMPTIONS!$B$21*((1+ASSUMPTIONS!$B$23)^42-1)/ASSUMPTIONS!$B$23,ASSUMPTIONS!$B$21*42) -> 284076.39 | N64: N/A | W64: N/A
A65: Portfolio Advantage: A vs B | AE65: =L55-U55 -> 146165.92
A66: Portfolio Advantage: A vs C | AE66: =L55-AD55 -> 1013676.4
A69: PROJECTION YEAR DETAIL — Select any year (D70) for a full breakdown with calculation sources
A70: Select Year (0–50): | D70: 0 | E70: =IF(D70=0,"Year 0 — 2026 (Current, Age 36)","Year "&D70&" — "&TEXT(2026+D70,"0")&" (Age "&TEXT(36+D70,"0")&")") -> Year 0 — 2026 (Current, Age 36)
A72: Metric | B72: PATH A — Value | D72: PATH A — How Calculated | F72: PATH B — Value | H72: PATH B — How Calculated | J72: PATH C — Value | L72: PATH C — How Calculated | N72: Formula / Source Reference
A73: CAREER PHASE
A74: Status / Phase | B74: =IFERROR(INDEX(D$5:D$55,D70+1),"—") -> Active Duty | C74: PROJECTIONS col D | F74: =IFERROR(INDEX(M$5:M$55,D70+1),"—") -> Active Duty | G74: PROJECTIONS col M | J74: =IFERROR(INDEX(V$5:V$55,D70+1),"—") -> Active Duty | K74: PROJECTIONS col V | N74: Life phase at selected year: Active Duty / PhD Student / Research Scientist / Gap Year
A75: INCOME SOURCES
A76: Gross Income | B76: =IFERROR(INDEX(E$5:E$55,D70+1),0) -> 67099.92 | C76: → ASSUMPTIONS B42-51 (salary, stipend, pension) | F76: =IFERROR(INDEX(N$5:N$55,D70+1),0) -> 67099.92 | G76: → ASSUMPTIONS C47 (CS salary)×(1+B51)^yrs | J76: =IFERROR(INDEX(W$5:W$55,D70+1),0) -> 67099.92 | K76: → ASSUMPTIONS D46 (stipend) or D48 (RS salary) | N76: PROJECTIONS E/N/W — taxable earned income. Military: base pay×(1+2.5%)^yr
A77: Tax-Free Income | B77: =IFERROR(INDEX(F$5:F$55,D70+1),0) -> 38623.92 | C77: → (B13+B14)×12 active; B33×B34^yr VA; B38×12 GI Bill | F77: =IFERROR(INDEX(O$5:O$55,D70+1),0) -> 38623.92 | G77: → C33×(1+C34)^yr ×12 VA disability after separation | J77: =IFERROR(INDEX(X$5:X$55,D70+1),0) -> 38623.92 | K77: → VA + GI Bill BAH ($D38×12) during PhD phase | N77: PROJECTIONS F/O/X — BAH, BAS, VA disability, GI Bill BAH (all tax-exempt)
A78: EXPENSES & TAXES
A79: Taxes Paid | B79: =IFERROR(INDEX(G$5:G$55,D70+1),0) -> 5410.44 | C79: → MAX((Gross-TaxFree)×(B64+B67),0) | F79: =IFERROR(INDEX(P$5:P$55,D70+1),0) -> 5410.44 | G79: → MAX((Gross-TaxFree)×(C65+C67),0) | J79: =IFERROR(INDEX(Y$5:Y$55,D70+1),0) -> 5410.44 | K79: → PhD: 10% on stipend; RS: (C66+C67) on income | N79: PROJECTIONS G/P/Y — effective federal+state on taxable portion. ASSUMPTIONS rows 64-67
A80: Healthcare Cost | B80: =IFERROR(INDEX(H$5:H$55,D70+1),0) -> 0 | C80: → $0 active duty; TRICARE B26×(1+B27)^yr retired | F80: =IFERROR(INDEX(Q$5:Q$55,D70+1),0) -> 0 | G80: → C28×(1+C29)^yr civilian ($3K+8%/yr inflation) | J80: =IFERROR(INDEX(Z$5:Z$55,D70+1),0) -> 0 | K80: → D30 gap yr; $0 PhD (university-covered); D28 RS | N80: PROJECTIONS H/Q/Z — ASSUMPTIONS rows 25-30 (TRICARE vs civilian vs university)
A81: Living Expenses | B81: =IFERROR(INDEX(I$5:I$55,D70+1),0) -> 28725.84 | C81: → ASSUMPTIONS!B70×12×(1+B71)^yr | F81: =IFERROR(INDEX(R$5:R$55,D70+1),0) -> 28725.84 | G81: → ASSUMPTIONS!B70×12×(1+B71)^yr (same base) | J81: =IFERROR(INDEX(AA$5:AA$55,D70+1),0) -> 28725.84 | K81: → ASSUMPTIONS!B70×12×(1+B71)^yr (same base) | N81: PROJECTIONS I/R/AA — base from EXPENSES grand total; 3%/yr growth. ASSUMPTIONS rows 70-71
A82: CASH FLOW & PORTFOLIO
A83: Retirement Savings | B83: =IFERROR(INDEX(J$5:J$55,D70+1),0) -> 22800 | C83: → B60×12 active; B62×12 PhD; B61×12 RS/civilian | F83: =IFERROR(INDEX(S$5:S$55,D70+1),0) -> 22800 | G83: → C60×12 active; C61×12 CS career | J83: =IFERROR(INDEX(AB$5:AB$55,D70+1),0) -> 22800 | K83: → D60×12 active; D62×12 PhD; D61×12 RS | N83: PROJECTIONS J/S/AB — ASSUMPTIONS rows 60-62 ($1,900 active, $0 PhD, $500 civilian)
A84: Net Cash Flow | B84: =IFERROR(INDEX(K$5:K$55,D70+1),0) -> 48787.56 | C84: → E+F-G-H-I-J = Gross+TaxFree-Tax-HC-Exp-Sav | F84: =IFERROR(INDEX(T$5:T$55,D70+1),0) -> 48787.56 | G84: → N+O-P-Q-R-S = same formula structure | J84: =IFERROR(INDEX(AC$5:AC$55,D70+1),0) -> 48787.56 | K84: → W+X-Y-Z-AA-AB = same formula structure | N84: PROJECTIONS K/T/AC — money remaining after all costs. Positive = surplus to invest
A85: Investment Portfolio | B85: =IFERROR(INDEX(L$5:L$55,D70+1),0) -> 228367.51 | C85: → Prior×(1+B59) + J + MAX(K,0)×0.2 | F85: =IFERROR(INDEX(U$5:U$55,D70+1),0) -> 228367.51 | G85: → Prior×(1+C59) + S + MAX(T,0)×0.2 | J85: =IFERROR(INDEX(AD$5:AD$55,D70+1),0) -> 228367.51 | K85: → Prior×(1+D59) + AB + MAX(AC,0)×0.2 | N85: PROJECTIONS L/U/AD — 7% nominal return (B59) + ret savings + 20% of surplus CF
A86: PATH COMPARISON
A87: A vs B: Total Income Diff | B87: =IFERROR(INDEX(AE$5:AE$55,D70+1),0) -> 0 | C87: → (E+F)-(N+O) : Path A total income minus Path B | F87: —— | G87: Positive = Path A leads | Negative = Path B leads | J87: —— | K87: Both paths vs Path A | N87: PROJECTIONS col AE — positive means Path A earns more total (gross+tax-free) this year
A88: A vs B: Portfolio Diff | B88: =IFERROR(INDEX(AG$5:AG$55,D70+1),0) -> 0 | C88: → L-U : Path A portfolio minus Path B | F88: —— | G88: Positive = Path A portfolio ahead | J88: —— | K88: Tracks pension advantage vs early CS income | N88: PROJECTIONS col AG
A89: A vs C: Total Income Diff | B89: =IFERROR(INDEX(AF$5:AF$55,D70+1),0) -> 0 | C89: → (E+F)-(W+X) : Path A total minus Path C | F89: —— | G89: Path C has 6-yr RS career head start | J89: —— | K89: PhD timing: A starts 2040, C starts 2034 | N89: PROJECTIONS col AF
A90: A vs C: Portfolio Diff | B90: =IFERROR(INDEX(AH$5:AH$55,D70+1),0) -> 0 | C90: → L-AD : Path A portfolio minus Path C | F90: —— | G90: Pension vs earlier RS career earnings | J90: —— | K90: Path C gap yr 2028 + PhD 2029-2033 | N90: PROJECTIONS col AH
A92: =HYPERLINK("#PROJECTIONS!A1","↑ Back to top") -> ↑ Back to top

Sheet CHARTS
A1: CHARTS — Financial Plan Visualizations
A2: CHART 1 — Investment Portfolio Growth (All Three Paths)
A3: Shows total invested assets accumulating over 50 years. All three paths start from the same base (~$114K). Path A (blue) benefits from pension supplementing investments; Path B (green) shows strong growth from early CS career; Path C (purple) shows PhD dip then strong research scientist growth. Add vertical lines at age 66 and 76 markers (rows 35 and 45).
A5: CHART 2 — Annual Net Cash Flow (All Three Paths)
A6: How much money is left each year after taxes, healthcare, expenses, and savings. Path A dips during PhD years (2035-2039) — pension + stipend is tight but positive. Path B shows strongest early cash flow from immediate CS career. Path C dips during PhD years with no pension support.
A8: CHART 3 — Path A vs B Cumulative Advantage
A9: Running lead of Path A over Path B in total cash flow. Positive = Path A is cumulatively ahead. Track whether early CS career income (Path B) eventually surpasses military pension + GI Bill benefits.
A11: CHART 4 — Path A vs C Cumulative Advantage
A12: Same delta chart comparing Path A to Path C (grad school route). Both lead to research scientist roles but Path A has pension and GI Bill stacking. Compare PhD start timing difference (2035 vs 2028).
A14: CHART 5 — Annual Healthcare Costs Comparison
A15: TRICARE retiree (~$182/yr growing slowly, Path A) vs civilian insurance (~$3,000/yr growing 8%/yr, Paths B/C). The gap widens dramatically — 50-year difference can exceed $300K.
A17: CHART 6 — Gross + Tax-Free Income Breakdown
... A21: 1. Select PROJECTIONS data (cols E:F for Path A, N:O for Path B, W:X for Path C + col B for years) 2. Insert → Line Chart 3. Add vertical reference lines at rows 35 (age 66, 2056) and 45 (age 76, 2066) using error bars or helper series 4. Color: Path A = Steel Blue (#2E75B6), Path B = Forest Green (#375623), Path C = Purple (#7030A0)

Sheet GOALS
A1: FINANCIAL GOALS
A2: FINANCIAL GOALS
A3: Short-Term Goals: less than 2 years
A5: Medium-Term Goals: between 2-5 years
A7: Long-Term Goals: over 5 years

Sheet INCOME
A1: INCOME — Monthly Snapshot
A2: City or Zip Code | B2: CURRENT | C2: PATH B — CS / Tech | D2: PATH C — Grad School | E2: Notes
A4: SERVICE MEMBER MONTHLY INCOME
A5: ENTITLEMENTS | B5: CURRENT | C5: PATH B — CS / Tech | D5: PATH C — Grad School | E5: Notes
A6: Monthly Base Pay | B6: 5591.66 | C6: 9803.15 | D6: 3333
A7: BAH (Housing) | B7: 2741.66
A8: BAS | B8: 477
A9: OHA | B9: 0
A10: COLA | B10: 0
A11: Special Pay | B11: 0
A12: Hazard Duty Pay | B12: 0
A13: Flight Duty Pay | B13: 0
A14: Foreign Language Pay | B14: 0
A15: Family Separation Allowance | B15: 0
A16: Other Take Home Pay | B16: 0
A17: Military Retirement Pay | B17: 0
A18: Rental Home Income | B18: 0
... A20: Child Support/Alimony | B20: 0
A24: GROSS MONTHLY INCOME | B24: =SUM(B6:B23) -> 8810.32 | C24: =SUM(C6:C23) -> 9803.15 | D24: =SUM(D6:D23) -> 3333
A26: DEDUCTIONS | B26: CURRENT | C26: PATH B — CS / Tech | D26: PATH C — Grad School | E26: Notes
A27: FITW (Federal Income Tax Withheld) | B27: 467.6 | C27: 1238.42
A28: FICA (Social Security) | B28: 284.28 | C28: 749.92
A29: FICA (Medicare) | B29: 66.49
A30: State Income Tax | B30: 240.08 | C30: 478.75
A31: AFRH (Armed Forces Retirement Home) | B31: 0.5 | C31: 0
A32: SGLI and T-SGLI | B32: 31
A33: SGLI Family/Spouse | B33: 0
A34: TSP | C34: 0
A35: SDP | B35: 0
A36: Partial Pay | B36: 0
A37: Advance Payments | B37: 0
A38: Montgomery GI Bill | B38: 0
A39: Child Support/Alimony Paid | B39: 0
A40: 401K | C40: 541.67 | E40: USER ENTERED — monthly snapshot only. Does NOT feed PROJECTIONS. Zero out if not contributing immediately at CS job start. C45=SUM(C27:C44) includes this in net income calc for the snapshot.
A45: DEDUCTIONS | B45: =SUM(B27:B44) -> 1089.95 | C45: =SUM(C27:C44) -> 3008.76 | D45: =SUM(D27:D44) -> 0
A47: NET MONTHLY INCOME | B47: =B24-B45 -> 7720.37 | C47: =C24-C45 -> 6794.39 | D47: =D24-D45 -> 3333
A49: SPOUSE MONTHLY INCOME
A50: ENTITLEMENTS | B50: CURRENT | C50: PATH B — CS / Tech | D50: PATH C — Grad School | E50: Notes
A51: Monthly Pay
A52: BAH (Housing)
A53: BAS
A54: OHA
A55: COLA
A56: Special Pay
A57: Hazard Duty Pay
A58: Flight Duty Pay
A59: Foreign Language Pay
A60: Family Separation Allowance
A61: Military Retirement Pay
A62: Rental Home Income
... A65: Other Take Home Pay/Second Job
A70: SPOUSE GROSS INCOME | B70: =SUM(B51:B69) -> 0 | C70: =SUM(C51:C69) -> 0 | D70: =SUM(D51:D69) -> 0
A72: DEDUCTIONS | B72: CURRENT | C72: PATH B — CS / Tech | D72: PATH C — Grad School | E72: Notes
A73: FITW (Federal Income Tax Withheld)
A74: FICA (Social Security)
A75: FICA (Medicare)
A76: State Income Tax
A77: AFRH (Armed Forces Retirement Home)
A78: SGLI and T-SGLI
A79: SGLI Family/Spouse
A80: TSP
A81: SDP
A82: Partial Pay
A83: Advance Payments
A84: Montgomery GI Bill
A85: Child Support/Alimony Paid
A90: SPOUSE DEDUCTIONS | B90: =SUM(B73:B89) -> 0 | C90: =SUM(C71:C89) -> 0 | D90: =SUM(D73:D89) -> 0
A92: SPOUSE NET INCOME | B92: =(B70-B90) -> 0 | C92: =C70-C90 -> 0 | D92: =D70-D90 -> 0
A95: TOTAL INCOME
A96: MONTHLY | B96: CURRENT | C96: PATH B — CS / Tech | D96: PATH C — Grad School | E96: Notes
A97: GROSS INCOME | B97: =B24+B70 -> 8810.32 | C97: =C24+C70 -> 9803.15 | D97: =D24+D70 -> 3333
A98: DEDUCTIONS | B98: =B45+B90 -> 1089.95 | C98: =C45+C90 -> 3008.76 | D98: =D45+D90 -> 0
A99: NET INCOME | B99: =B47+B92 -> 7720.37 | C99: =C47+C92 -> 6794.39 | D99: =D47+D92 -> 3333
A100: ANNUAL | B100: CURRENT | C100: PATH B — CS / Tech | D100: PATH C — Grad School | E100: Notes
A101: GROSS INCOME | B101: =B97*12 -> 105723.84 | C101: =C97*12 -> 117637.8 | D101: =D97*12 -> 39996
A102: NET INCOME | B102: =B99*12 -> 92644.44 | C102: =C99*12 -> 81532.68 | D102: =D99*12 -> 39996
A105: PROJECTION LOOKUP — View Any Year's Projected Values
A106: View Year (enter 0–50 or use dropdown): | B106: 0 | C106: =IF(B106=0,"Viewing: Current (Year 0)","Viewing: Year "&B106&" — "&TEXT(2026+B106,"0")&" (Age "&TEXT(36+B106,"0")&")") -> Viewing: Current (Year 0)
A108: Metric | B108: PATH A | C108: PATH B | D108: PATH C | E108: Notes
A109: INCOME PROJECTIONS
A110: Gross Income | B110: =IF(B106=0,B97,INDEX(PROJECTIONS!$E$5:$E$55,B106+1)) -> 8810.32 | C110: =IF(B106=0,C97,INDEX(PROJECTIONS!$N$5:$N$55,B106+1)) -> 9803.15 | D110: =IF(B106=0,D97,INDEX(PROJECTIONS!$W$5:$W$55,B106+1)) -> 3333 | E110: Taxable earned income for the year
A111: Tax-Free Income | B111: =IF(B106=0,"",INDEX(PROJECTIONS!$F$5:$F$55,B106+1)) | C111: =IF(B106=0,"",INDEX(PROJECTIONS!$O$5:$O$55,B106+1)) | D111: =IF(B106=0,"",INDEX(PROJECTIONS!$X$5:$X$55,B106+1)) | E111: BAH, VA disability, GI Bill BAH — not taxed
A112: Taxes Paid | B112: =IF(B106=0,"",INDEX(PROJECTIONS!$G$5:$G$55,B106+1)) | C112: =IF(B106=0,"",INDEX(PROJECTIONS!$P$5:$P$55,B106+1)) | D112: =IF(B106=0,"",INDEX(PROJECTIONS!$Y$5:$Y$55,B106+1)) | E112: Federal + CA state effective rate on taxable income
A113: Healthcare Cost | B113: =IF(B106=0,"",INDEX(PROJECTIONS!$H$5:$H$55,B106+1)) | C113: =IF(B106=0,"",INDEX(PROJECTIONS!$Q$5:$Q$55,B106+1)) | D113: =IF(B106=0,"",INDEX(PROJECTIONS!$Z$5:$Z$55,B106+1)) | E113: Path A: TRICARE ($182/yr). Path B/C: civilian ~$3K+8%/yr
A115: NET POSITION AT SELECTED YEAR
A116: Retirement Savings | B116: =IF(B106=0,"",INDEX(PROJECTIONS!$J$5:$J$55,B106+1)) | C116: =IF(B106=0,"",INDEX(PROJECTIONS!$S$5:$S$55,B106+1)) | D116: =IF(B106=0,"",INDEX(PROJECTIONS!$AB$5,B106+1)) | E116: Annual retirement account contributions
A117: Living Expenses | B117: =IF(B106=0,"",INDEX(PROJECTIONS!$I$5:$I$55,B106+1)) | C117: =IF(B106=0,"",INDEX(PROJECTIONS!$R$5:$R$55,B106+1)) | D117: =IF(B106=0,"",INDEX(PROJECTIONS!$AA$5,B106+1)) | E117: Annual living expenses (3%/yr growth from current)
A118: Net Cash Flow | B118: =IF(B106=0,"",INDEX(PROJECTIONS!$K$5:$K$55,B106+1)) | C118: =IF(B106=0,"",INDEX(PROJECTIONS!$T$5:$T$55,B106+1)) | D118: =IF(B106=0,"",INDEX(PROJECTIONS!$AC$5,B106+1)) | E118: Income + Tax-Free − Taxes − Healthcare − Expenses − Savings
A119: Investment Portfolio | B119: =IF(B106=0,"",INDEX(PROJECTIONS!$L$5:$L$55,B106+1)) | C119: =IF(B106=0,"",INDEX(PROJECTIONS!$U$5:$U$55,B106+1)) | D119: =IF(B106=0,"",INDEX(PROJECTIONS!$AD$5,B106+1)) | E119: Cumulative invested assets at year-end
A121: CAREER PHASE AT SELECTED YEAR
A122: Path A — Status: | B122: =IF(B106=0,"Current: Active Duty",INDEX(PROJECTIONS!$D$5:$D$55,B106+1)) -> Current: Active Duty
A123: Path B — Status: | B123: =IF(B106=0,"Current: Active Duty",INDEX(PROJECTIONS!$M$5:$M$55,B106+1)) -> Current: Active Duty
A124: Path C — Status: | B124: =IF(B106=0,"Current: Active Duty",INDEX(PROJECTIONS!$V$5:$V$55,B106+1)) -> Current: Active Duty
A126: Tip: Change the year in B106 to explore any point in the 50-year projection. Year 0 = today. Year 8 = Path A retirement year. Year 14 = Path A Research Scientist start. Year 8 = Path C Research Scientist start.
A128: CELL FORMATTING LEGEND — Color coding and cell type guide for this sheet
A130: $ 2,393 | C130: EDITABLE INPUT — Ivory + blue. Your cell to change. Enter your actual monthly amount here.
A131: 4293 | C131: CALCULATED FORMULA — White + dark text. Do NOT edit directly. Auto-sums from rows above.
A132: =INCOME!B97 -> 8810.32 | C132: CROSS-SHEET REFERENCE — White + green. Edit this on its SOURCE sheet (INCOME, ASSETS, etc.) — NOT here.
A133: ─ Age 66 ─ | C133: AGE MILESTONE ROW — Amber fill. Age 66 = Social Security / Medicare eligibility. Age 76 = extended horizon.
A134: HOUSING | C134: SECTION HEADER — Dark fill + white bold text. Shows category total. Not editable.
...

Sheet EXPENSES
A1: EXPENSES — Monthly Living Costs
A2: City or Zip Code | B2: CURRENT LOCATION | C2: POTENTIAL LOCATION | D2: POTENTIAL LOCATION
B3: =INCOME!B3 -> 0 | C3: =INCOME!C3 -> 0 | D3: =INCOME!D3 -> 0
A4: LIVING EXPENSES | B4: CURRENT (Year 0) | C4: PATH B — CS / Tech Job | D4: PATH C — Grad School | E4: REMARKS
A5: HOUSING TOTAL | B5: =SUM(B6:B12) -> 500 | C5: =SUM(C6:C12) -> 2600 | D5: =SUM(D6:D12) -> 2580
A6: Fees/HOA Fees/Pool Fees | B6: 0 | C6: 0
A7: Furniture/Decorations | B7: 0 | C7: 0
A8: Home Maintenance/Repairs | B8: 0 | C8: 0
A9: Taxes | B9: 0 | C9: 0
A10: Rent | B10: 500 | C10: 2500 | D10: 2500 | E10: KEY: GI Bill BAH ($4,992/mo Bay Area) is income, not an expense offset. This rent IS your real cost — GI Bill covers it and more. Update to match your admitted school's market rate.
A11: Renters Insurance | C11: 100 | D11: 80 | E11: Renters insurance ~$80/mo typical
A13: UTILITIES TOTAL | B13: =SUM(B14:B20) -> 103.82 | C13: =SUM(C14:C20) -> 103.82 | D13: =SUM(D14:D20) -> 164
A14: Cable/Satellite | B14: 0 | C14: 0
A15: Cell Phone/Phone Cards/Landline | B15: 25 | C15: 25 | D15: 25 | E15: Cell phone — same as current
A16: Internet | B16: 78.82 | C16: 78.82 | D16: 79 | E16: Internet ~$79/mo — university area typical
A17: Electricity | B17: 0 | C17: 0 | D17: 60 | E17: Electricity ~$60/mo for 1BR apt
A18: Natural Gas/Propane | B18: 0 | C18: 0
A19: Garbage | B19: 0 | C19: 0
A20: Water/Sewage | B20: 0
A21: TRANSPORTATION TOTAL | B21: =SUM(B22:B29) -> 490 | C21: =SUM(C22:C29) -> 290 | D21: =SUM(D22:D29) -> 245
A22: Gasoline | B22: 400 | C22: 200 | D22: 80 | E22: Gasoline — reduced; most PhD students use transit near campus
A23: Parking | B23: 0 | C23: 0
A24: Taxes/Registration/Licensing | B24: 15 | C24: 15 | D24: 15
A25: Taxi/Bus/Uber/Lyft/Train | B25: 0 | C25: 0 | D25: 100 | E25: BART/Caltrain/bus pass ~$100-150/mo Bay Area. Many campuses subsidize.
A26: Vehicle Maintenance/Repairs | B26: 75 | C26: 75 | D26: 50 | E26: Vehicle maintenance — reduced mileage
A30: FOOD TOTAL | B30: =SUM(B31:B37) -> 540 | C30: =SUM(C31:C37) -> 540 | D30: =SUM(D31:D37) -> 640
A31: Dining out | B31: 250 | C31: 250 | D31: 200 | E31: Dining out — Bay Area PhD student estimate
A32: Groceries | B32: 250 | C32: 250 | D32: 400 | E32: Groceries — Bay Area avg ~$400/mo single person
A33: Lunches | B33: 40 | C33: 40 | D33: 40
A34: Vending Machines
A38: INSURANCE TOTAL | B38: =SUM(B39:B46) -> 182 | C38: =SUM(C39:C46) -> 802 | D38: =SUM(D39:D46) -> 165
A39: Auto Insurance | B39: 182 | C39: 150 | D39: 150 | E39: Auto insurance — reduced to minimum coverage if needed
A40: Dental Insurance | B40: 0 | C40: 20 | D40: 0 | E40: Dental — most PhD programs include dental in health plan
A41: Health Insurance | B41: 0 | C41: 580 | D41: 0 | E41: Health ins — covered by university stipend package (typical PhD benefit)
A42: Life Insurance | B42: 0 | C42: 52 | D42: 15 | E42: Life insurance ~$15/mo basic term
A43: Renters/Home Insurance | B43: 0 | C43: 0
A47: HEALTHCARE | B47: =SUM(B48:B54) -> 10 | C47: =SUM(C48:C54) -> 150 | D47: =SUM(D48:D54) -> 70
A48: Dental | B48: 0 | C48: 20 | D48: 10 | E48: Dental copays — minimal with university coverage
A49: Doctor/Hospital/Urgent Care | B49: 0 | C49: 100 | D49: 30 | E49: Doctor/urgent care copays
A50: Eye Care | B50: 0 | C50: 20 | D50: 20 | E50: Eye care annual
A51: Prescriptions/Medications | B51: 10 | C51: 10 | D51: 10
A55: CLOTHING TOTAL | B55: =SUM(B56:B60) -> 20 | C55: =SUM(C56:C60) -> 20 | D55: =SUM(D56:D60) -> 30
A56: Laundry/Dry Cleaning | B56: 0
A57: New Clothing Purchase | B57: 20 | C57: 20 | D57: 30 | E57: Clothing — academic environment, slightly higher than current
A61: CHILD CARE TOTAL | B61: =SUM(B62:B68) -> 0 | C61: =SUM(C62:C68) -> 0 | D61: =SUM(D62:D68) -> 0
A62: Allowance | B62: 0 | C62: 0
A63: Child Support | B63: 0 | C63: 0
A64: Day Care | B64: 0 | C64: 0
A65: Diapers/Wipes/Etc. | B65: 0
A69: PET CARE TOTAL | B69: =SUM(B70:B75) -> 0 | C69: =SUM(C70:C75) -> 0 | D69: =SUM(D70:D75) -> 0
A70: Food/Supplies | B70: 0 | C70: 0
A71: Prescriptions/Medications | B71: 0 | C71: 0
A72: Veterinarian/Grooming/Boarding | B72: 0 | C72: 0
A76: PERSONAL TOTAL | B76: =SUM(B77:B85) -> 150 | C76: =SUM(C77:C85) -> 150 | D76: =SUM(D77:D85) -> 130
A77: Beauty Shop/Barber Shop/Salon | B77: 50 | C77: 50 | D77: 30 | E77: Haircuts/barber — reduced
A78: Health Club/Organizational Dues | B78: 0
A79: Nails/Massage/Personal Grooming | B79: 0
A80: Personal Spending Fund | B80: 100 | C80: 100 | D80: 100 | E80: Personal fund — keep same
A81: Personal Supplies | B81: 0
A82: Tobacco/Alcohol | B82: 0
A86: EDUCATION TOTAL | B86: =SUM(B87:B92) -> 0 | C86: =SUM(C87:C92) -> 0 | D86: =SUM(D87:D92) -> 0
A87: Books/Supplies | B87: 0 | C87: 0
A88: Educational Materials | B88: 0 | C88: 0
A89: Lessons/Tutor | C89: 0
A93: LEISURE/HOBBIES/ENTERTAINMENT TOTAL | B93: =SUM(B94:B108) -> 98 | C93: =SUM(C94:C108) -> 98 | D93: =SUM(D94:D108) -> 128
A94: Athletic Events/Sporting Events | B94: 0 | C94: 0
A95: Books/Magazines | B95: 0 | C95: 0 | D95: 30 | E95: Books/materials — supplemental to GI Bill book stipend
A96: Computer Products | B96: 0 | C96: 0
A97: Concerts/Theater | B97: 0 | C97: 0
A98: DVDs & CDs | B98: 0 | C98: 0
A99: Movie/Music Downloads | B99: 0 | C99: 0
A100: Streaming Services | B100: 0 | C100: 0
A101: Toys/Games | B101: 0 | C101: 0
A102: Travel/Lodging | B102: 0 | C102: 0
A103: Netflix, Crunchyroll, Spotify | B103: 42 | C103: 42 | D103: 42 | E103: Streaming — same
A104: CHATGPT | B104: 20 | C104: 20 | D104: 20 | E104: ChatGPT — same
A105: AUDIBLE | B105: 16 | C105: 16 | D105: 16 | E105: Audible — same
A106: Claude | B106: 20 | C106: 20 | D106: 20 | E106: Claude — same
A109: CONTRIBUTIONS TOTAL | B109: =SUM(B110:B114) -> 0 | C109: =SUM(C110:C114) -> 0 | D109: =SUM(D110:D114) -> 0
A110: Charities | B110: 0 | C110: 0
A111: Religious Donations | B111: 0 | C111: 0
A115: GIFTS TOTAL | B115: =SUM(B116:B119) -> 300 | C115: =SUM(C116:C119) -> 300 | D115: =SUM(D116:D119) -> 0
A116: Holiday/Birthday/Anniversary | B116: 300 | C116: 300
A120: MISCELLANEOUS TOTAL | B120: =SUM(B121:B125) -> 0 | C120: =SUM(C121:C125) -> 0 | D120: =SUM(D121:D125) -> 0
A121: ATM Fees/Bank Fees | B121: 0 | C121: 0
A122: Deployment/TAD Expenses | B122: 0 | C122: 0
A123: Membership Fees | B123: 0 | C123: 0
A126: GRAND TOTAL | B126: =SUM(B5,B13,B21,B30,B38,B47,B55,B61,B69,B76,B86,B93,B109,B115,B120) -> 2393.82 | C126: =SUM(C5,C13,C21,C30,C38,C47,C55,C61,C69,C76,C86,C93,C109,C115,C120) -> 5053.82 | D126: =SUM(D5,D13,D21,D30,D38,D47,D55,D61,D69,D76,D86,D93,D109,D115,D120) -> 4152
A128: CELL FORMATTING LEGEND — What each color and style means on this sheet
A130: $ 2,393 | C130: EDITABLE INPUT — Ivory + blue. Your cell to change. Enter your actual monthly amount here.
A131: 4293 | C131: CALCULATED FORMULA — White + dark text. Do NOT edit directly. Auto-sums from rows above.
A132: =INCOME!B97 -> 8810.32 | C132: CROSS-SHEET REFERENCE — White + green. Edit this on its SOURCE sheet (INCOME, ASSETS, etc.) — NOT here.
A133: ─ Age 66 ─ | C133: AGE MILESTONE ROW — Amber fill. Age 66 = Social Security / Medicare eligibility. Age 76 = extended horizon.
A134: HOUSING | C134: SECTION HEADER — Dark fill + white bold text. Shows category total. Not editable.
A135: note text | C135: NOTE / SECONDARY — Light gray + italic gray text. Supporting context, assumptions, or data sources.
A136: [nav link] | C136: NAVIGATION LINK — Pale blue + underlined. Click to jump to a related section or sheet.
A137: ⚠ update | C137: NEEDS ATTENTION — Yellow background. Placeholder or estimate that needs your review and update.
A141: View Year (0–50 or use dropdown): | B141: 0 | C141: =IF(B141=0,"Viewing: Current (Year 0)","Viewing: Year "&B141&" — "&TEXT(2026+B141,"0")&" (Age "&TEXT(36+B141,"0")&")") -> Viewing: Current (Year 0)
A143: Metric | B143: PATH A | C143: PATH B | D143: PATH C | E143: Notes
A144: EXPENSE PROJECTIONS AT SELECTED YEAR
...

Sheet DEBT
A1: JD BRITT — DEBT OBLIGATIONS & DEBT-TO-INCOME RATIO
A2: Ivory = editable input White = calculated formula — = not applicable
A4: Creditor / Description | B4: Monthly Payment | C4: Current Balance | D4: Interest Rate | E4: Payoff Date / Notes | F4: Projected Total Cost
A5: HOUSING
A6: Rent / Primary Home Mortgage
A7: Secondary Home Mortgage
A8: Rental Property Mortgage
A9: Other (Vacation / Trailer / Time-share)
A10: HOUSING TOTAL | B10: =SUM(B6:B9) -> 0 | C10: =SUM(C6:C9) -> 0 | F10: =SUM(F6:F9) -> 0
A12: OTHER DEBT (Auto, Student Loans, Credit Cards, Personal)
A13: Auto Loan
A14: Student Loans
A15: Credit Card 1
A16: Credit Card 2
A17: Personal Loan
A18: USAA / Military Star
A19: Other
A20: Other
A21: OTHER DEBT TOTAL | B21: =SUM(B13:B20) -> 0 | C21: =SUM(C13:C20) -> 0 | F21: =SUM(F13:F20) -> 0
A23: TOTAL MONTHLY DEBT PAYMENTS | B23: =B10+B21 -> 0 | C23: =C10+C21 -> 0
A25: DEBT-TO-INCOME RATIO (DTI)
A26: Metric | B26: Current | C26: Notes
A27: Gross Monthly Income (from INCOME) | B27: =INCOME!B97 -> 8810.32 | C27: Cross-referenced from INCOME sheet
A28: Total Monthly Debt Payments | B28: =B23 -> 0 | C28: Sum of all housing + other debt payments
A29: DEBT-TO-INCOME RATIO | B29: =IF(B27=0,0,B28/B27) -> 0 | C29: Target: < 36% (healthy); < 43% (max for most loans)
A30: Total Outstanding Debt Balance | B30: =C23 -> 0 | C30: Total current balance across all debt

Sheet ASSETS
A1: JD BRITT — ASSETS, LIABILITIES & INVESTMENT PROJECTIONS
A2: Ivory = editable input White = calculated Green text = cross-sheet ref Hover column headers for projection notes
A4: LIQUID SAVINGS & INVESTMENTS (edit values below — update whenever balances change)
A5: Account | B5: Current Balance | C5: Notes
A6: Checking Accounts | B6: 0 | C6: Day-to-day spending. Not invested.
A7: Checking Accounts | B7: 8000 | C7: Day-to-day spending. Not invested.
A8: Savings Accounts | B8: 12000 | C8: Emergency / short-term. Target: 3-6 months expenses.
A9: Emergency Savings | C9: Keep 3-6 months liquid here if separate from savings.
A10: TSP (Roth) | B10: 75000 | C10: All Roth. ~$1,900/mo contributions. C Fund + S Fund. ★ Primary retirement vehicle.
A11: Certificates of Deposit (CDs) | C11: Currently uninvested. Consider total market ETF (VTI/FZROX).
A12: Cash Value of Life Insurance | C12: Civilian employer plan — populate at separation.
A13: U.S. Savings Bonds
A14: Money Market Accounts
A15: Mutual Funds
A16: Stocks / Bonds
A17: College Funds (529)
A18: 401(k) / 403(b) | C18: Civilian employer plan — populate at separation.
A19: Roth IRA | B19: 30000 | C19: Currently uninvested (cash). Move to index funds (VTI or equivalent) ASAP. No RMD requirement — powerful long-term.
A20: Brokerage Account | B20: 58000 | C20: Currently uninvested (cash). No contribution limit. Consider VTI/FZROX. Taxable gains but flexible.
A21: TOTAL LIQUID SAVINGS & INVESTMENTS | B21: =SUM(B7:B20) -> 183000
A23: REAL ESTATE (Market Value)
A24: Primary Home
A25: Secondary Home
A26: Rental Property
A27: Other Real Estate
A29: PERSONAL PROPERTY
A30: Vehicles / Motorcycles / Boats | B30: 25000
A31: Furniture
A32: Jewelry
A33: Other Personal Property
A34: TOTAL ASSETS | B34: =B21+SUM(B24:B27)+SUM(B30:B33) -> 208000
A36: LIABILITIES
A37: Total Debt (from DEBT sheet) | B37: =DEBT!C23 -> 0
A38: NET WORTH (Assets − Liabilities) | B38: =B34-B37 -> 208000
A40: INVESTMENT GROWTH PROJECTIONS (from PROJECTIONS sheet — auto-updates)
A41: Portfolio column in PROJECTIONS = aggregate of all investment accounts (TSP + Roth + Brokerage + new contributions). Values below pull directly from PROJECTIONS. Change ASSUMPTIONS to update projections automatically.
A43: Milestone / Age | B43: Year / Date | C43: Path A Portfolio | D43: Path B Portfolio | E43: Path C Portfolio | F43: 4% Annual Withdrawal (Path A) | G43: Notes
A44: Today (Age 36) | B44: 2026 / Year 0 | C44: =PROJECTIONS!$L$5 -> 228367.51 | D44: =PROJECTIONS!$U$5 -> 228367.51 | E44: =PROJECTIONS!$AD$5 -> 228367.51 | F44: =PROJECTIONS!$L$5*0.04 -> 9134.7005 | G44: Current snapshot
A45: Separation — B/C (Age 37) | B45: 2027 / Year 1 | C45: =PROJECTIONS!$L$6 -> 277239.96 | D45: =PROJECTIONS!$U$6 -> 277239.96 | E45: =PROJECTIONS!$AD$6 -> 277239.96 | F45: =PROJECTIONS!$L$6*0.04 -> 11089.598 | G45: Path B/C leave service Nov 2027
A46: Age 40 | B46: 2030 / Year 4 | C46: =PROJECTIONS!$L$9 -> 447504.57 | D46: =PROJECTIONS!$U$9 -> 421449.34 | E46: =PROJECTIONS!$AD$9 -> 372033.43 | F46: =PROJECTIONS!$L$9*0.04 -> 17900.183
A47: Path A Retirement (44) | B47: 2034 / Year 8 | C47: =PROJECTIONS!$L$13 -> 718927.56 | D47: =PROJECTIONS!$U$13 -> 679041.96 | E47: =PROJECTIONS!$AD$13 -> 571490.51 | F47: =PROJECTIONS!$L$13*0.04 -> 28757.103 | G47: Path A pension begins. GI Bill available.
A48: Age 50 | B48: 2040 / Year 14 | C48: =PROJECTIONS!$L$19 -> 1260478.7 | D48: =PROJECTIONS!$U$19 -> 1259506.3 | E48: =PROJECTIONS!$AD$19 -> 1109626.6 | F48: =PROJECTIONS!$L$19*0.04 -> 50419.149 | G48: Catch-up contribution eligibility begins
A49: Age 59 ½ | B49: 2049 / Year 23 | C49: =PROJECTIONS!$L$28 -> 2836203.6 | D49: =PROJECTIONS!$U$28 -> 2832452.1 | E49: =PROJECTIONS!$AD$28 -> 2589009.9 | F49: =PROJECTIONS!$L$28*0.04 -> 113448.14 | G49: Penalty-free TSP/IRA access begins
A50: Social Security (Age 66) | B50: 2056 / Year 30 | C50: =PROJECTIONS!$L$35 -> 5052211.2 | D50: =PROJECTIONS!$U$35 -> 5043189.4 | E50: =PROJECTIONS!$AD$35 -> 4693343.4 | F50: =PROJECTIONS!$L$35*0.04 -> 202088.45 | G50: Early Social Security eligibility (age 62) or full (66+)
A51: Age 70 | B51: 2060 / Year 34 | C51: =PROJECTIONS!$L$39 -> 6934908.6 | D51: =PROJECTIONS!$U$39 -> 6919269.9 | E51: =PROJECTIONS!$AD$39 -> 6492183.2 | F51: =PROJECTIONS!$L$39*0.04 -> 277396.35 | G51: Delayed SS maximizes monthly benefit
A52: RMDs Begin (Age 73) | B52: 2063 / Year 37 | C52: =PROJECTIONS!$L$42 -> 8752729 | D52: =PROJECTIONS!$U$42 -> 8728787.3 | E52: =PROJECTIONS!$AD$42 -> 8235031.4 | F52: =PROJECTIONS!$L$42*0.04 -> 350109.16 | G52: Required Minimum Distributions from TSP (traditional)
A53: Age 80 | B53: 2070 / Year 44 | C53: =PROJECTIONS!$L$49 -> 14881652 | D53: =PROJECTIONS!$U$49 -> 14817060 | E53: =PROJECTIONS!$AD$49 -> 14137682 | F53: =PROJECTIONS!$L$49*0.04 -> 595266.07
A54: Age 86 (Year 50) | B54: 2076 / Year 50 | C54: =PROJECTIONS!$L$55 -> 23204783 | D54: =PROJECTIONS!$U$55 -> 23058617 | E54: =PROJECTIONS!$AD$55 -> 22191106 | F54: =PROJECTIONS!$L$55*0.04 -> 928191.31 | G54: End of 50-year projection
A56: RETIREMENT ACCOUNT KEY FACTS
A57: 1. TSP contribution limit (2024): $23,000/yr. Catch-up (age 50+): $30,500/yr.
A58: 2. Roth IRA limit (2024): $7,000/yr (income limits apply). No RMDs. Tax-free growth.
A59: 3. Brokerage: No contribution limit. Capital gains tax applies to withdrawals. Most flexible.
A60: 4. TSP employer match: None for pre-BRS (High-3) members. BRS members receive up to 5% match.
A61: 5. Penalty-free access: Age 59½ for all accounts. Age 55 at separation (TSP only, under Rule of 55).
A62: 6. RMDs begin at age 73 for TSP (traditional) and 401k. Roth IRA: NO RMD.
A63: 7. Safe Withdrawal Rate: 4% rule = withdraw 4% of portfolio/year in retirement (historically sustainable 30+ yrs).
A64: 8. Portfolio allocation suggestion: TSP C+S funds (broad market). Roth: VTI or FZROX. Brokerage: index ETFs.

Sheet SUMMARY AND ACTION PLAN
A1: JD BRITT — MONTHLY SUMMARY & ACTION PLAN
A2: All values cross-referenced from INCOME, EXPENSES, DEBT, and PROJECTIONS sheets. Do not edit directly.
A4: MONTHLY SNAPSHOT — CURRENT vs PROJECTED SCENARIOS
A5: Metric | B5: Current (Now) | C5: Path B — CS Job | D5: Path C — Grad School | F5: Notes
A6: Gross Monthly Income | B6: =INCOME!B97 -> 8810.32 | C6: =INCOME!C97 -> 9803.15 | D6: =INCOME!D97 -> 3333
A7: Net Monthly Income | B7: =INCOME!B99 -> 7720.37 | C7: =INCOME!C99 -> 6794.39 | D7: =INCOME!D99 -> 3333 | F7: After all deductions
A8: Monthly Living Expenses | B8: =EXPENSES!B126 -> 2393.82 | C8: =EXPENSES!C126 -> 5053.82 | D8: =EXPENSES!D126 -> 4152 | F8: From EXPENSES sheet
A9: Monthly Debt Payments | B9: =DEBT!B23 -> 0 | C9: =DEBT!B23 -> 0 | D9: =DEBT!B23 -> 0 | F9: From DEBT sheet
A10: Monthly Surplus / Deficit | B10: =B6-B8-B9 -> 6416.5 | C10: =C6-C8-C9 -> 4749.33 | D10: =D6-D8-D9 -> -819 | F10: Net income − expenses − debt
A11: Debt-to-Income Ratio | B11: =DEBT!B29 -> 0 | C11: =DEBT!B29 -> 0 | D11: =DEBT!B29 -> 0 | F11: Current DTI (all paths share same debt)
A13: 50-YEAR PROJECTION — KEY OUTCOMES (from PROJECTIONS sheet)
A14: Metric | B14: Path A | C14: Path B | D14: Path C | F14: Notes
A15: Final Portfolio (Year 50) | B15: =PROJECTIONS!L55 -> 23204783 | C15: =PROJECTIONS!U55 -> 23058617 | D15: =PROJECTIONS!AD55 -> 22191106 | F15: Age 86 total invested assets
A16: Total Gross Income (50 yrs) | B16: =PROJECTIONS!E59 -> 23189291 | C16: =PROJECTIONS!N59 -> 25656781 | D16: =PROJECTIONS!W59 -> 25673725 | F16: From PROJECTIONS totals section
A17: Total Taxes Paid (50 yrs) | B17: =PROJECTIONS!E61 -> 6763165.5 | C17: =PROJECTIONS!N61 -> 7214981.7 | D17: =PROJECTIONS!W61 -> 7680941
A18: Total Healthcare Costs (50 yr) | B18: =PROJECTIONS!E62 -> 15421.568 | C18: =PROJECTIONS!N62 -> 1591028.2 | D18: =PROJECTIONS!W62 -> 3000
A19: Portfolio at Age 66 (yr 30) | B19: =PROJECTIONS!L35 -> 5052211.2 | C19: =PROJECTIONS!U35 -> 5043189.4 | D19: =PROJECTIONS!AD35 -> 4693343.4 | F19: Pre-Social Security retirement threshold
A20: 4% Withdrawal at Age 66 | B20: =B19*0.04 -> 202088.45 | C20: =C19*0.04 -> 201727.57 | D20: =D19*0.04 -> 187733.74 | F20: Sustainable annual draw at age 66
A22: ACTION PLAN — Open Items, Gaps & Sensitivities
A23: # | B23: Category | C23: Item | F23: Notes / Next Step
A24: 1 | B24: VERIFY | C24: Verify actual pension estimate vs DFAS calculator | E24: Open | F24: Run DFAS High-3 calculator with actual service records. Update ASSUMPTIONS!B19.
A25: 2 | B25: VERIFY | C25: Confirm GI Bill BAH rate for target PhD program ZIP codes | E25: Open | F25: Check va.gov BAH calculator for each program ZIP. Update ASSUMPTIONS!B38 if different from Bay Area rate.
A26: 3 | B26: VERIFY | C26: Confirm VA disability estimate (30% assumed) | E26: Open | F26: Actual rating unknown until filed. Range: 10-50%+. Update ASSUMPTIONS!B32-B33 when known.
A27: 4 | B27: VERIFY | C27: Roth IRA + Brokerage: invest these funds | E27: Open | F27: Uninvested cash sitting in Roth and brokerage. Transfer to index funds.
A28: 5 | B28: MODEL GAP | C28: Social Security not modeled | E28: Not modeled | F28: Both paths qualify. Path B/C longer civilian career = higher benefit. Add as income at age 62-70.
A29: 6 | B29: MODEL GAP | C29: Portfolio drawdown not modeled | E29: Not modeled | F29: PROJECTIONS shows portfolio growing forever. Model 4% withdrawal as income at age 66+.
A30: 7 | B30: MODEL GAP | C30: RMDs (Required Minimum Distributions) not modeled | E30: Not modeled | F30: TSP traditional account triggers RMDs at age 73. Adds taxable income. Add to PROJECTIONS yr 37+.
A31: 8 | B31: MODEL GAP | C31: TSP employer match not modeled | E31: Not modeled | F31: Pre-BRS High-3: no automatic match. Confirm with finance. BRS members get up to 5%.
A32: 9 | B32: MODEL GAP | C32: Path B 401k employer match not modeled | E32: Not modeled | F32: CS/Tech jobs typically match 3-6% of salary. At $117K: ~$3.5K-$7K/yr additional. Add to ASSUMPTIONS row 61.
A33: 10 | B33: MODEL GAP | C33: Housing costs not modeled in projection | E33: Partially modeled | F33: Living expenses include rent but no home ownership path. Significant wealth-building lever.
A34: 11 | B34: MODEL GAP | C34: Warrant Officer path not modeled | E34: Not modeled | F34: Higher compensation; affects Path A timeline and pension base. Add as Path D if actively pursued.
A35: 12 | B35: SENSITIVITY | C35: Investment return sensitivity (7% assumption) | E35: Review | F35: Conservative: 5% (Vanguard forecast). Base: 7%. Optimistic: 9%. Model all three for range.
... A38: 15 | B38: CONCERN | C38: Path A PhD cash flow yr 12-13 (GI Bill exhausted) | E38: Flag | F38: After 36 months of PhD, GI Bill BAH stops. Cash flow may go slightly negative. Plan bridge funding.
